Workbook

Sheet Cover Page
B1: APOLLO ENERGY RESOURCES
B2: Pro Forma Financial Model · Confidential · March 2026
B6: KEY MODEL OUTPUTS
B8: ="Exit Equity Value ("&TEXT(Assumptions!G165,"0.0")&"x)" -> Exit Equity Value (5.0x) | C8: DCF Cross-Check | D8: ="Equity MOIC (5-Yr, "&TEXT(Assumptions!G165,"0.0")&"x)" -> Equity MOIC (5-Yr, 5.0x) | E8: Active Scenario
B9: =TEXT('DCF & Returns'!J73,"$#,##0\K") -> $23,406K | C9: =TEXT('DCF & Returns'!B28,"$#,##0\K") -> $16,198K | D9: =TEXT('DCF & Returns'!J84,"0.0\×") -> 15.9× | E9: ='Control Panel'!C7 -> Base
B10: ="WACC "&TEXT(Assumptions!B11,"0.0%")&" · TGR "&TEXT(Assumptions!B12,"0.0%")&" · Active scenario: "&'Control Panel'!C7 -> WACC 11.1% · TGR 2.5% · Active scenario: Base | C10: ="$"&TEXT('DCF & Returns'!B50,"#,##0")&"K equity invested · "&TEXT(Assumptions!G165,"0.0")&"× exit multiple (5-yr)" -> $1,500K equity invested · 5.0× exit multiple (5-yr) | D10: ="Exit multiple: "&TEXT(Assumptions!B165,"0.0")&"× · "&TEXT(Assumptions!B157*100,"0")&"% probability weight" -> Exit multiple: 3.0× · 15% probability weight | E10: ="Exit multiple: "&TEXT(Assumptions!F165,"0.0")&"× · "&TEXT(Assumptions!F157*100,"0")&"% probability weight" -> Exit multiple: 7.5× · 10% probability weight
B11: DCF Enterprise Value | C11: 5-Year MOIC | D11: Exit Equity (Hyper Bear) | E11: Exit Equity (Hyper Bull)
B12: ='DCF & Returns'!B24 -> 18169.2 | C12: ='DCF & Returns'!J84 -> 15.918845 | D12: =Assumptions!B165*'DCF & Returns'!J64-'DCF & Returns'!J65 -> 14733.412 | E12: =Assumptions!F165*'DCF & Returns'!J64-'DCF & Returns'!J65 -> 34245.744
B14: MODEL STRUCTURE
B16: Sheet | C16: Function | D16: Key Output | E16: Status | F16: Color
B17: Assumptions | C17: Inputs, growth rates, margins, scenarios | D17: Scenario toggle (Bull/Base/Bear) | E17: ✓ | F17: ●
B19: Control Panel | C19: 5-scenario × 5-credit-tier toggle interface | D19: Master scenario & credit dropdowns | E19: ✓ | F19: ●
B21: Revenue Build | C21: Monthly revenue by division (5 divs) | D21: ="FY2026E: $"&TEXT('Income Statement'!N3,"#,##0")&"K → FY2030E: $"&TEXT('Income Statement'!R3,"#,##0")&"K" -> FY2026E: $8,365K → FY2030E: $16,689K | E21: ✓ | F21: ●
B22: Income Statement | C22: Monthly → annual consolidated P&L | D22: ="FY2030E NI: $"&TEXT('Income Statement'!R27,"#,##0")&"K" -> FY2030E NI: $1,971K | E22: ✓ | F22: ●
B23: Balance Sheet | C23: Annual balance sheet (FY2026–FY2030) | D23: ="Total assets: $"&TEXT('Balance Sheet'!N26,"#,##0")&"K → $"&TEXT('Balance Sheet'!R26,"#,##0")&"K" -> Total assets: $7,365K → $8,067K | E23: ✓ | F23: ●
B24: Cash Flow | C24: Monthly cash flow statement | D24: Monthly NI sums to annual CF | E24: ✓ | F24: ●
B28: Debt Schedule | C28: Amortization, covenants, monthly detail | D28: ="Total debt: $"&TEXT('Debt Schedule'!N68,"#,##0")&"K → $"&TEXT('Debt Schedule'!R68,"#,##0")&"K (FY2030)" -> Total debt: $4,602K → $477K (FY2030) | E28: ✓ | F28: ●
B30: DCF & Returns | C30: DCF with sensitivity table | D30: ="EV: $"&TEXT('DCF & Returns'!B24,"#,##0")&"K · Equity: $"&TEXT('DCF & Returns'!B28,"#,##0")&"K (cross-ref)" -> EV: $18,169K · Equity: $16,198K (cross-ref) | E30: ✓ | F30: ●
B34: KEY ASSUMPTIONS
B36: Forecast horizon | C36: 5 years (FY2026E – FY2030E) | D36: Entity structure | E36: Pass-through LLC (31% tax rate)
B37: Year 1 granularity | C37: Monthly | D37: Exit multiple | E37: =TEXT(Assumptions!G165,"0.0")&"x EV/EBITDA (scenario-dependent)" -> 5.0x EV/EBITDA (scenario-dependent)
B38: WACC | C38: =Assumptions!B11 -> 0.11147818 | D38: Equity investment | E38: ="$"&TEXT(Assumptions!B79,"#,##0")&"K ("&TEXT(Assumptions!B79/Assumptions!B81,"0%")&" of $"&TEXT(Assumptions!B81,"#,##0")&"K total)" -> $1,500K (50% of $3,000K total)
B39: Terminal growth rate | C39: =Assumptions!B12 -> 0.025 | D39: Total capital injection | E39: ="$"&TEXT(Assumptions!B81,"#,##0")&"K (debt + equity)" -> $3,000K (debt + equity)
B40: Revenue CAGR (5-yr) | C40: =('Income Statement'!R3/'Income Statement'!N3)^(1/5)-1 -> 0.14812617 | D40: Depreciation | E40: 5-year straight-line
B41: FY2025A revenue | C41: $4,916K (Apollo actual, excl. Installations acq.) | D41: Scenario toggle | E41: ='Control Panel'!C7&" (Control Panel!C7)" -> Base (Control Panel!C7)
B42: FY2030E revenue | C42: =TEXT('Income Statement'!R3,"$#,##0")&"K" -> $16,689K | D42: Installations acquisition | E42: FY2026 (Month 16 base timing)
B43: Blended GM (FY2030) | C43: ='Income Statement'!R30/'Income Statement'!R3 -> 0.2598167 | D43: Covenant max Debt/EBITDA | E43: =TEXT(Assumptions!B98,"0.0")&"×" -> 5.5×
B47: COLOR CODING CONVENTIONS
B49: Blue text | C49: Hardcoded inputs — values the user can change for scenario analysis
B50: Black text | C50: Formulas and calculations — do not overwrite
B51: Yellow highlight | C51: Key assumptions that need attention or verification
B52: Green text | C52: Cross-sheet links pulling from other worksheets
B56: SHEET TAB COLORS BY FUNCTION
B58: ● | C58: Dark Navy | D58: Navigation & Controls | E58: Cover Page, Assumptions, Control Panel
B59: ● | C59: Gray | D59: Actuals (locked)
B60: ● | C60: Green | D60: Core Financial Statements | E60: Revenue Build, IS, BS, CF
B61: ● | C61: Red | D61: Risk & Stress Testing
B62: ● | C62: Orange | D62: Debt & Credit | E62: Debt Schedule
B63: ● | C63: Purple | D63: Valuation & Returns | E63: DCF & Returns
B67: CRITICAL NOTES
B69: 1 | C69: The scenario toggle on the Control Panel sheet (C7/C8) drives the entire model. Use the dropdowns to switch scenarios and credit tiers. Revenue, margins, and all downstream sheets update automatically.
B70: 2 | C70: ="FY2026 Debt/EBITDA of "&TEXT('Debt Schedule'!N75,"0.0")&"× vs 3.5× max. Modified FCCR = "&TEXT('Debt Schedule'!N81,"0.00")&"×. Deleverages to "&TEXT('Debt Schedule'!R75,"0.00")&"× by FY2030. 24-month covenant holiday enforced (months 1–24 show HOLIDAY)." -> FY2026 Debt/EBITDA of 4.0× vs 3.5× max. Modified FCCR = 0.92×. Deleverages to 0.11× by FY2030. 24-month covenant holiday enforced (months 1–24 show HOLIDAY).
B71: 3 | C71: All revenue and margin inputs are blue text. All formulas are black. Do not overwrite black cells.
B72: 4 | C72: Installations is an acquisition ($1.8M trailing revenue). FY2025A column shows target's pre-acquisition revenue as CAGR base. Apollo consolidated Installations revenue was $0 in FY2025A — acquisition ideally closes FY2026.
B77: Apollo Energy Resources — Confidential | Pro Forma Financial Model | Mar 2026

Sheet Assumptions
A1: APOLLO ENERGY RESOURCES — KEY ASSUMPTIONS
A3: GENERAL ASSUMPTIONS
A4: Model Start Date | B4: 46023
A5: Forecast Horizon (Years) | B5: 5
A6: Year 1 Granularity | B6: Monthly
A7: Currency | B7: USD ($)
A8: Units | B8: Thousands ($000s)
D9: Installations = acquisition ($1.8M trailing rev). FY2026 = first year under Apollo ownership.
A11: WACC | B11: =IF($B$205="Convergence",B219,0.12) -> 0.11147818
A12: Terminal Growth Rate | B12: =G159 -> 0.025
A13: Effective Tax Rate (Pass-Through) | B13: 0.31
A15: Blended Net Margin Target (5-Yr) | B15: 0.22
A16: Blended Revenue Growth (Avg) | B16: 0.22
A17: CAPEX as % of Revenue Growth | B17: =G161 -> 0.4
A18: Back-Office Efficiency Discount | B18: 0
A19: Depreciation — Useful Life (Years) | B19: 5
A20: Note: FY2026E-FY2030E revenue inputs below are base figures only. Revenue Build applies the selected scenario multiplier and winter/seasonality uplift, so reported revenue can be higher than these base inputs.
A21: REVENUE ASSUMPTIONS BY DIVISION
A22: Revenue ($000s) | B22: 2025A PF | C22: 2026E | D22: 2027E | E22: 2028E | F22: 2029E | G22: 2030E | H22: 5-Yr CAGR
A23: Logistics | B23: 3735 | C23: 4810 | D23: 5291 | E23: 5768 | F23: 6287 | G23: 6859 | H23: =(G23/B23)^(1/5)-1 -> 0.12926025
A24: Field Services | B24: 231 | C24: 623 | D24: 872 | E24: 1134 | F24: 1418 | G24: 1702 | H24: =(G24/B24)^(1/5)-1 -> 0.49097209
A25: Installations | B25: 1800 | C25: 1400 | D25: 2203 | E25: 3304 | F25: 4626 | G25: 5782 | H25: $1.4M FY2026 baseline. Growth trajectory maintained. Target: 18% div net margin FY2026, +5bps/yr improvement (goal).
A26: Apollo Fleet Services | B26: 46 | C26: 111 | D26: 167 | E26: 234 | F26: 304 | G26: 380 | H26: =(G26/B26)^(1/5)-1 -> 0.5254752
A27: Apollo Power Management | B27: 0 | C27: 177 | D27: 230 | E27: 299 | F27: 359 | G27: 413 | H27: =(G27/C27)^(1/4)-1 -> 0.23593092
A29: Total Revenue | B29: =SUM(B23:B27) -> 5812 | C29: ='Revenue Build'!N10 -> 8365.3 | D29: ='Revenue Build'!O10 -> 10079.48 | E29: ='Revenue Build'!P10 -> 12130.851 | F29: ='Revenue Build'!Q10 -> 14465.389 | G29: ='Revenue Build'!R10 -> 16688.973 | H29: =(G29/B29)^(1/5)-1 -> 0.23486875
A30: YoY Revenue Growth | C30: =C29/B29-1 -> 0.43931521 | D30: =D29/C29-1 -> 0.20491554 | E30: =E29/D29-1 -> 0.20351955 | F30: =F29/E29-1 -> 0.19244635 | G30: =G29/F29-1 -> 0.15371751
A31: Brokerage Gross Margin | B31: 0.15 | C31: Pass-through margin on ~$1,182K brokerage revenue
A32: Brokerage Base Revenue ($K) | B32: 1182
A34: Brokerage Annual Growth Rate | B34: 0.04
A35: Other Current Assets (% of Revenue) | B35: ='Balance Sheet'!B9/B29 -> 0.0070543703
A36: GROSS MARGIN ASSUMPTIONS BY DIVISION
A37: Gross Margin % | B37: 2025A PF | C37: 2026E | D37: 2027E | E37: 2028E | F37: 2029E | G37: 2030E | H37: Notes
A38: Logistics | B38: 0.25 | C38: 0.22 | D38: =C38+0.02*$G$223 -> 0.24 | E38: =C38+0.03*$G$223 -> 0.25 | F38: =C38+0.04*$G$223 -> 0.26 | G38: =C38+0.05*$G$223 -> 0.27 | H38: Insurance-heavy; marginal improvement only
A39: Field Services | B39: 0.45 | C39: 0.38 | D39: =C39-0.01*$G$223 -> 0.37 | E39: =C39-0.01*$G$223 -> 0.37 | F39: =C39 -> 0.38 | G39: =C39+0.01*$G$223 -> 0.39 | H39: Ramp from 38% to target +700bps over 5yr; management targets above industry.
A40: Installations | B40: 0.38 | C40: 0.45 | D40: =C40 -> 0.45 | E40: =C40+0.01*$G$223 -> 0.46 | F40: =C40+0.01*$G$223 -> 0.46 | G40: =C40+0.02*$G$223 -> 0.47 | H40: 45% GM per mgmt (electrical contractors avg 40-50%)
A41: Apollo Fleet Services | B41: 0.3 | C41: 0.25 | D41: =C41+0.02*$G$223 -> 0.27 | E41: =C41+0.03*$G$223 -> 0.28 | F41: =C41+0.04*$G$223 -> 0.29 | G41: =C41+0.05*$G$223 -> 0.3 | H41: Equipment maintenance 25-30% GM range; steady improvement via utilization
A42: Apollo Power Management | C42: 0.25 | D42: =C42+0.02*$G$223 -> 0.27 | E42: =C42+0.04*$G$223 -> 0.29 | F42: =C42+0.05*$G$223 -> 0.3 | G42: =C42+0.06*$G$223 -> 0.31 | H42: 25% blended start per mgmt (compliance infra already in place)
A43: Blended Gross Margin | B43: =SUMPRODUCT(B23:B27,B38:B42)/B29 -> 0.29860633 | C43: =SUMPRODUCT(C23:C27,C38:C42)/C29 -> 0.23871708 | D43: =SUMPRODUCT(D23:D27,D38:D42)/D29 -> 0.26698004 | E43: =SUMPRODUCT(E23:E27,E38:E42)/E29 -> 0.29129448 | F43: =SUMPRODUCT(F23:F27,F38:F42)/F29 -> 0.31089934 | G43: =SUMPRODUCT(G23:G27,G38:G42)/G29 -> 0.32807771
A45: OPERATING EXPENSE ASSUMPTIONS
A46: Operating Expenses ($000s) | B46: 2025A | C46: 2026E | D46: 2027E | E46: 2028E | F46: 2029E | G46: 2030E | H46: Notes
A47: Insurance — Installations | B47: 0 | C47: =160*$G$229 -> 160 | D47: =168*$G$229 -> 168 | E47: =176*$G$229 -> 176 | F47: =185*$G$229 -> 185 | G47: =194*$G$229 -> 194 | H47: 5% annual escalation — normalized baseline
A48: Insurance — Logistics | B48: 491 | C48: =400*$G$229 -> 400 | D48: =420*$G$229 -> 420 | E48: =441*$G$229 -> 441 | F48: =463*$G$229 -> 463 | G48: =486*$G$229 -> 486 | H48: 5% annual escalation; normalized baseline
A49: Insurance — Other Divisions | B49: 36 | C49: =65*$G$229 -> 65 | D49: =68*$G$229 -> 68 | E49: =71*$G$229 -> 71 | F49: =75*$G$229 -> 75 | G49: =79*$G$229 -> 79 | H49: 5% annual escalation — Field Svc/Fleet/Power Mgmt combined
A50: Total Insurance | B50: =SUM(B47:B49) -> 527 | C50: =C47+C48+C49 -> 625 | D50: =D47+D48+D49 -> 656 | E50: =E47+E48+E49 -> 688 | F50: =F47+F48+F49 -> 723 | G50: =G47+G48+G49 -> 759
A52: Back-Office / Admin Payroll | B52: 103 | C52: =ROUND(C29*0.025*(1-$B$18),0) -> 209 | D52: =ROUND(D29*0.025*(1-$B$18),0) -> 252 | E52: =ROUND(E29*0.024*(1-$B$18),0) -> 291 | F52: =ROUND(F29*0.023*(1-$B$18),0) -> 333 | G52: =ROUND(G29*0.022*(1-$B$18),0) -> 367 | H52: Industry ~3.5% of revenue
A53: Corporate Overhead (G&A) | B53: 59 | C53: =80*$G$224 -> 80 | D53: =84*$G$224 -> 84 | E53: =88*$G$224 -> 88 | F53: =92*$G$224 -> 92 | G53: =97*$G$224 -> 97 | H53: ~5% annual inflation escalation
A54: Sales & Marketing | B54: 47 | C54: =80*$G$225 -> 80 | D54: =80*$G$225 -> 80 | E54: =100*$G$225 -> 100 | F54: =120*$G$225 -> 120 | G54: =150*$G$225 -> 150 | H54: $80K base FY2026-27; scales with growth FY2028+ per mgmt
A55: Software / Hardware / IT | B55: 24 | C55: =50*$G$226 -> 50 | D55: =35*$G$226 -> 35 | E55: =35*$G$226 -> 35 | F55: =40*$G$226 -> 40 | G55: =40*$G$226 -> 40 | H55: Minimal — owner builds vertical software
A56: Depreciation & Amortization | B56: 237 | C56: =ROUND($B$56+C65/$B$19,0) -> 466 | D56: =ROUND($B$56+C65/$B$19+D65/$B$19,0) -> 634 | E56: =ROUND($B$56+C65/$B$19+D65/$B$19+E65/$B$19,0) -> 834 | F56: =ROUND($B$56+C65/$B$19+D65/$B$19+E65/$B$19+F65/$B$19,0) -> 1064 | G56: =ROUND($B$56+C65/$B$19+D65/$B$19+E65/$B$19+F65/$B$19+G65/$B$19,0) -> 1292 | H56: Linked from Debt Schedule; straight-line 5-yr useful life
A58: Total Operating Expenses | B58: =B50+B52+B53+B54+B55+B56 -> 997 | C58: =C50+C52+C53+C54+C55+C56 -> 1510 | D58: =D50+D52+D53+D54+D55+D56 -> 1741 | E58: =E50+E52+E53+E54+E55+E56 -> 2036 | F58: =F50+F52+F53+F54+F55+F56 -> 2372 | G58: =G50+G52+G53+G54+G55+G56 -> 2705
A59: OpEx as % of Revenue | B59: =B58/B29 -> 0.17154164 | C59: =C58/C29 -> 0.18050757 | D59: =D58/D29 -> 0.17272716 | E59: =E58/E29 -> 0.16783653 | F59: =F58/F29 -> 0.16397761 | G59: =G58/G29 -> 0.16208307
A60: Other Income / Corporate Adjustment | B60: 320 | C60: 0 | D60: 0 | E60: 0 | F60: 0 | G60: 0
A61: CAPEX & WORKING CAPITAL ASSUMPTIONS
A62: CAPEX ($000s) | B62: 2025A | C62: 2026E | D62: 2027E | E62: 2028E | F62: 2029E | G62: 2030E | H62: Notes
A63: Growth CAPEX | C63: =ROUND((C29-B29)*$B$17,0) -> 1021 | D63: =ROUND((D29-C29)*$B$17,0) -> 686 | E63: =ROUND((E29-D29)*$B$17,0) -> 821 | F63: =ROUND((F29-E29)*$B$17,0) -> 934 | G63: =ROUND((G29-F29)*$B$17,0) -> 889 | H63: 40% of incremental revenue growth (midpoint 30-50%)
A64: Maintenance CAPEX | C64: =ROUND(C29*$G$230,0) -> 125 | D64: =ROUND(D29*$G$230,0) -> 151 | E64: =ROUND(E29*$G$230,0) -> 182 | F64: =ROUND(F29*$G$230,0) -> 217 | G64: =ROUND(G29*$G$230,0) -> 250 | H64: 1.5% of revenue — fleet/equipment maintenance
A65: Total CAPEX | C65: =C63+C64 -> 1146 | D65: =D63+D64 -> 837 | E65: =E63+E64 -> 1003 | F65: =F63+F64 -> 1151 | G65: =G63+G64 -> 1139
A67: Working Capital Drivers | B67: Assumption | H67: Notes
A68: Days Sales Outstanding (DSO) | B68: 36 | C68: =$B$68+$G$228 -> 36 | D68: =35+$G$228 -> 35 | E68: =34+$G$228 -> 34 | F68: =33+$G$228 -> 33 | G68: =33+$G$228 -> 33 | H68: Net-30 terms; avg collection 33–36 days. Declining from 36→33 as processes mature.
A69: Days Payable Outstanding (DPO) | B69: 18 | C69: =$B$69 -> 18 | D69: =$B$69 -> 18 | E69: =$B$69 -> 18 | F69: =$B$69 -> 18 | G69: =$B$69 -> 18 | H69: 15-day max to owner-operators; structural float
A70: Inventory Days (Fleet Svc Only) | B70: 37 | C70: =IF('Revenue Build'!N7>0,ROUND('Balance Sheet'!N7/('Revenue Build'!N7/365),0),0) -> 3 | D70: =IF('Revenue Build'!O7>0,ROUND('Balance Sheet'!O7/('Revenue Build'!O7/365),0),0) -> 37 | E70: =IF('Revenue Build'!P7>0,ROUND('Balance Sheet'!P7/('Revenue Build'!P7/365),0),0) -> 36 | F70: =IF('Revenue Build'!Q7>0,ROUND('Balance Sheet'!Q7/('Revenue Build'!Q7/365),0),0) -> 36 | G70: =IF('Revenue Build'!R7>0,ROUND('Balance Sheet'!R7/('Revenue Build'!R7/365),0),0) -> 37 | H70: ~10% of Fleet Services annual revenue
A71: Working Capital Gap (DSO - DPO) | B71: =B68-B69 -> 18 | C71: =C68-C69 -> 18 | D71: =D68-D69 -> 17 | E71: =E68-E69 -> 16 | F71: =F68-F69 -> 15 | G71: =G68-G69 -> 15 | H71: 21-day structural float; key Logistics risk
A73: Inventory as % of Fleet Svc Revenue | B73: 0.1 | H73: Per mgmt guidance
A74: Prepaid Expenses (% of OpEx) | B74: 0.03 | H74: Standard — insurance prepayments
A76: DEBT & CAPITAL STRUCTURE
A77: Capital Injection ($000s) | B77: Amount | C77: % of Total | D77: Rate | E77: Term (Yrs) | F77: Monthly Pmt | H77: Notes
A78: Term Debt | B78: 1500 | C78: =B78/$B$81 -> 0.5 | D78: 0.085 | E78: 5 | F78: =ROUND(-PMT(D78/12,E78*12,B78),1) -> 30.8 | H78: Standard commercial term loan
A79: Equity Investment | B79: 1500 | C79: =B79/$B$81 -> 0.5 | D79: n/a | E79: n/a | F79: n/a | H79: Owner equity contribution
A80: Line of Credit / Mezz Debt | B80: 0 | C80: =B80/$B$81 -> 0 | D80: 0.1 | E80: 3 | F80: =ROUND(B80*D80/12,1) -> 0 | H80: Revolving; interest-only payments
A81: Total Capital Injection | B81: =SUM(B78:B80) -> 3000 | C81: =SUM(C78:C80) -> 1
A83: Existing Debt ($000s) | B83: Balance | C83: % of Total | D83: Rate | E83: Term (Yrs) | F83: Monthly Pmt | H83: Notes
A84: Truck Leases (Existing) | B84: 440 | C84: =B84/$B$86 -> 0.55 | D84: 0.065 | E84: 4 | F84: 17.6 | H84: Balloon option declined; will not own
A85: Other Existing Debt | B85: 360 | C85: =B85/$B$86 -> 0.45 | D85: 0.075 | E85: 4 | F85: 14.4 | H85: Equipment/other financing
A86: Total Existing Debt | B86: =SUM(B84:B85) -> 800 | F86: =SUM(F84:F85) -> 32 | H86: Total debt svc: ~$32K/mo per mgmt
A88: New Debt (May 2026) | B88: Amount | D88: Rate | E88: Term (Yrs) | F88: Monthly Pmt | H88: Notes
A89: ISO Tank Lease-to-Own | B89: 700 | D89: 0.07 | E89: 5 | F89: =ROUND(-PMT(D89/12,E89*12,B89),1) -> 13.9 | H89: Starts May 2026; 80%+ equity at maturity
A90: Work Truck Notes | B90: 50 | D90: 0.07 | E90: 5 | F90: =ROUND(-PMT(D90/12,E90*12,B90),1) -> 1 | H90: 0 down; 5-yr amortizing notes at 7%
A91: Acquisition Debt (Nov 2026)
A92: Seller Note (Installations) | B92: 1400 | D92: 0.07 | E92: 5 | F92: =ROUND(-PMT(D92/12,E92*12,B92),1) -> 27.7 | H92: Seller-financed; 7% fixed, 5-yr amortizing. ~$27.7K/mo.
A93: Apollo Acquisition Term Note | B93: 300 | D93: 0.09 | E93: 5 | F93: =ROUND(-PMT(D93/12,E93*12,B93),1) -> 6.2 | H93: Bank-financed acquisition note; 9% fixed, 5-yr amortizing. ~$6.2K/mo.
A94: Total Acquisition Debt | B94: =SUM(B92:B93) -> 1700 | F94: =SUM(F92:F93) -> 33.9 | H94: Total acquisition debt svc: ~$33.9K/mo
A95: Total Acquisition Cost | B95: 2000 | H95: $2M total: $600K cash at close + $1.4M seller-financed
A96: Covenant Holiday (months) | B96: 24
A97: DEBT COVENANTS | B97: Threshold | C97: Tier 1 | D97: Tier 2 | E97: Tier 3 | F97: Tier 4 | G97: Active | H97: Notes
A98: Max Debt / EBITDA | B98: 5.5 | C98: 4.5 | D98: 3.5 | E98: 3 | F98: 2.5 | G98: =IF($B$183="No Facility",B98,IF($B$183="Tier 1",C98,IF($B$183="Tier 2",D98,IF($B$183="Tier 3",E98,F98)))) -> 3.5 | H98: Industry std for energy services
A99: Min Interest Coverage Ratio | B99: 2.5 | C99: 2.5 | D99: 2.5 | E99: 2.5 | F99: 2.5 | G99: =IF($B$183="No Facility",B99,IF($B$183="Tier 1",C99,IF($B$183="Tier 2",D99,IF($B$183="Tier 3",E99,F99)))) -> 2.5 | H99: EBITDA / Interest Expense ≥ 2.5x
A100: Min Fixed Charge Coverage | B100: 1.25 | C100: 1.25 | D100: 1.25 | E100: 1.2 | F100: 1.15 | G100: =IF($B$183="No Facility",B100,IF($B$183="Tier 1",C100,IF($B$183="Tier 2",D100,IF($B$183="Tier 3",E100,F100)))) -> 1.25 | H100: (EBITDA - CAPEX) / (Debt Svc + Tax) ≥ 1.25x
A101: Min Liquidity ($000s) | B101: 250 | C101: 150 | D101: 200 | E101: 250 | F101: 300 | G101: =IF($B$183="No Facility",B101,IF($B$183="Tier 1",C101,IF($B$183="Tier 2",D101,IF($B$183="Tier 3",E101,F101)))) -> 200 | H101: Cash + available LOC headroom
A102: Max Distributions (% of NI) | B102: 0.4 | H102: Pass-through tax distributions + discretionary
A103: Required Tax Distribution (% of NI) | B103: 0.31 | H103: Mandatory for pass-through tax liability
A104: Discretionary Distribution (% of NI) | B104: 0.09 | H104: Subject to covenant compliance
A106: SEASONALITY CURVE — MONTHLY REVENUE DISTRIBUTION (YEAR 1)
A107: Monthly % of Annual Revenue | B107: Jan | C107: Feb | D107: Mar | E107: Apr | F107: May | G107: Jun | H107: Jul | J107: Aug | K107: Sep | L107: Oct | M107: Nov | N107: Dec | O107: Check
A108: Logistics | B108: 0.065 | C108: 0.065 | D108: 0.075 | E108: 0.085 | F108: 0.095 | G108: 0.1 | H108: 0.105 | J108: 0.105 | K108: 0.095 | L108: 0.08 | M108: 0.065 | N108: 0.065 | O108: =SUM(B108:N108) -> 1
A109: Field Services | B109: 0.06 | C109: 0.06 | D109: 0.07 | E109: 0.085 | F109: 0.1 | G109: 0.11 | H109: 0.115 | J109: 0.11 | K109: 0.095 | L109: 0.075 | M109: 0.065 | N109: 0.055 | O109: =SUM(B109:N109) -> 1
A110: Installations | B110: 0.055 | C110: 0.06 | D110: 0.075 | E110: 0.09 | F110: 0.105 | G110: 0.115 | H110: 0.12 | J110: 0.115 | K110: 0.095 | L110: 0.075 | M110: 0.05 | N110: 0.045 | O110: =SUM(B110:N110) -> 1
A111: Apollo Fleet Services | B111: 0.075 | C111: 0.075 | D111: 0.08 | E111: 0.085 | F111: 0.09 | G111: 0.095 | H111: 0.095 | J111: 0.09 | K111: 0.085 | L111: 0.08 | M111: 0.075 | N111: 0.075 | O111: =SUM(B111:N111) -> 1
A112: Apollo Power Management | B112: 0.04 | C112: 0.045 | D112: 0.06 | E112: 0.08 | F112: 0.1 | G112: 0.13 | H112: 0.14 | J112: 0.13 | K112: 0.1 | L112: 0.075 | M112: 0.055 | N112: 0.045 | O112: =SUM(B112:N112) -> 1
A114: Blended Monthly Weight | B114: =SUMPRODUCT(B108:B112,$C$23:$C$27)/SUM($C$23:$C$27) -> 0.062131021 | C114: =SUMPRODUCT(C108:C112,$C$23:$C$27)/SUM($C$23:$C$27) -> 0.063238309 | D114: =SUMPRODUCT(D108:D112,$C$23:$C$27)/SUM($C$23:$C$27) -> 0.074267659 | E114: =SUMPRODUCT(E108:E112,$C$23:$C$27)/SUM($C$23:$C$27) -> 0.085858728 | F114: =SUMPRODUCT(F108:F112,$C$23:$C$27)/SUM($C$23:$C$27) -> 0.097449796 | G114: =SUMPRODUCT(G108:G112,$C$23:$C$27)/SUM($C$23:$C$27) -> 0.10449164 | H114: =SUMPRODUCT(H108:H112,$C$23:$C$27)/SUM($C$23:$C$27) -> 0.10953799 | J114: =SUMPRODUCT(J108:J112,$C$23:$C$27)/SUM($C$23:$C$27) -> 0.10779104 | K114: =SUMPRODUCT(K108:K112,$C$23:$C$27)/SUM($C$23:$C$27) -> 0.094968403 | L114: =SUMPRODUCT(L108:L112,$C$23:$C$27)/SUM($C$23:$C$27) -> 0.078455273 | M114: =SUMPRODUCT(M108:M112,$C$23:$C$27)/SUM($C$23:$C$27) -> 0.061958292 | N114: =SUMPRODUCT(N108:N112,$C$23:$C$27)/SUM($C$23:$C$27) -> 0.059851847 | O114: =SUM(B114:N114) -> 1
A115: SEASONAL GROSS MARGIN ADJUSTMENTS (Δ GM% by Month)
...

Sheet Control Panel
B2: APOLLO ENERGY RESOURCES
B3: Control Panel — Scenario & Credit Controls
B5: SCENARIO & CREDIT CONTROLS
B7: Active Scenario | C7: Base | E7: ◀ Click to select scenario
B8: Active Credit Tier | C8: Tier 2 | E8: ◀ Click to select credit tier
B11: SCENARIO PARAMETERS
B12: Parameter | C12: Active | E12: Hyper Bear | F12: Bear | G12: Base | H12: Bull | I12: Hyper Bull
B13: Rev Multiplier — Logistics | C13: =Assumptions!G170 -> 1 | E13: =Assumptions!B170 -> 0.75 | F13: =Assumptions!C170 -> 0.88 | G13: =Assumptions!D170 -> 1 | H13: =Assumptions!E170 -> 1.08 | I13: =Assumptions!F170 -> 1.15
B14: Rev Multiplier — Field Services | C14: =Assumptions!G171 -> 1 | E14: =Assumptions!B171 -> 0.35 | F14: =Assumptions!C171 -> 0.62 | G14: =Assumptions!D171 -> 1 | H14: =Assumptions!E171 -> 1.2 | I14: =Assumptions!F171 -> 1.45
B15: Rev Multiplier — Installations | C15: =Assumptions!G174 -> 1 | E15: =Assumptions!B174 -> 0.82 | F15: =Assumptions!C174 -> 0.91 | G15: =Assumptions!D174 -> 1 | H15: =Assumptions!E174 -> 1.12 | I15: =Assumptions!F174 -> 1.22
B16: Rev Multiplier — Fleet Services | C16: =Assumptions!G172 -> 1 | E16: =Assumptions!B172 -> 0.9 | F16: =Assumptions!C172 -> 0.95 | G16: =Assumptions!D172 -> 1 | H16: =Assumptions!E172 -> 1.04 | I16: =Assumptions!F172 -> 1.07
B17: Rev Multiplier — Power Mgmt | C17: =Assumptions!G173 -> 1 | E17: =Assumptions!B173 -> 0.8 | F17: =Assumptions!C173 -> 0.9 | G17: =Assumptions!D173 -> 1 | H17: =Assumptions!E173 -> 1.1 | I17: =Assumptions!F173 -> 1.18
B18: GM Delta — Avg (ppt) | C18: =AVERAGE(Assumptions!G177:G181) -> 0 | E18: =AVERAGE(Assumptions!B177:B181) -> -0.098 | F18: =AVERAGE(Assumptions!C177:C181) -> -0.051 | G18: =AVERAGE(Assumptions!D177:D181) -> 0 | H18: =AVERAGE(Assumptions!E177:E181) -> 0.024 | I18: =AVERAGE(Assumptions!F177:F181) -> 0.041
B19: Insurance Multiplier | C19: =Assumptions!G158 -> 1 | E19: =Assumptions!B158 -> 1.25 | F19: =Assumptions!C158 -> 1.12 | G19: =Assumptions!D158 -> 1 | H19: =Assumptions!E158 -> 1.02 | I19: =Assumptions!F158 -> 1.1
B20: CAPEX Reinvestment % | C20: =Assumptions!G161 -> 0.4 | E20: =Assumptions!B161 -> 0.15 | F20: =Assumptions!C161 -> 0.25 | G20: =Assumptions!D161 -> 0.4 | H20: =Assumptions!E161 -> 0.5 | I20: =Assumptions!F161 -> 0.55
B21: Terminal Growth Rate | C21: =Assumptions!G159 -> 0.025 | E21: =Assumptions!B159 -> 0.005 | F21: =Assumptions!C159 -> 0.015 | G21: =Assumptions!D159 -> 0.025 | H21: =Assumptions!E159 -> 0.025 | I21: =Assumptions!F159 -> 0.025
B22: WACC Scenario Adj | C22: =Assumptions!G160 -> 0 | E22: =Assumptions!B160 -> 0.025 | F22: =Assumptions!C160 -> 0.0125 | G22: =Assumptions!D160 -> 0 | H22: =Assumptions!E160 -> -0.005 | I22: =Assumptions!F160 -> -0.01
B23: Exit Multiple (EV/EBITDA) | C23: =Assumptions!G165 -> 5 | E23: =Assumptions!B165 -> 3 | F23: =Assumptions!C165 -> 4 | G23: =Assumptions!D165 -> 5 | H23: =Assumptions!E165 -> 6 | I23: =Assumptions!F165 -> 7.5
B24: Working Capital Days (net) | C24: =Assumptions!G167 -> 30 | E24: =Assumptions!B167 -> 50 | F24: =Assumptions!C167 -> 38 | G24: =Assumptions!D167 -> 30 | H24: =Assumptions!E167 -> 28 | I24: =Assumptions!F167 -> 25
B25: Probability Weights | C25: =Assumptions!G157 -> 1 | E25: =Assumptions!B157 -> 0.15 | F25: =Assumptions!C157 -> 0.25 | G25: =Assumptions!D157 -> 0.35 | H25: =Assumptions!E157 -> 0.15 | I25: =Assumptions!F157 -> 0.1
B26: EXTENDED SCENARIO PARAMETERS
B27: GM Ramp Pace | C27: =Assumptions!G223 -> 1 | E27: =Assumptions!B223 -> 0 | F27: =Assumptions!C223 -> 0.5 | G27: =Assumptions!D223 -> 1 | H27: =Assumptions!E223 -> 1.3 | I27: =Assumptions!F223 -> 1.5
B28: G&A Multiplier | C28: =Assumptions!G224 -> 1 | E28: =Assumptions!B224 -> 1.15 | F28: =Assumptions!C224 -> 1.08 | G28: =Assumptions!D224 -> 1 | H28: =Assumptions!E224 -> 0.97 | I28: =Assumptions!F224 -> 0.95
B29: S&M Multiplier | C29: =Assumptions!G225 -> 1 | E29: =Assumptions!B225 -> 0.7 | F29: =Assumptions!C225 -> 0.85 | G29: =Assumptions!D225 -> 1 | H29: =Assumptions!E225 -> 1.15 | I29: =Assumptions!F225 -> 1.3
B30: IT Multiplier | C30: =Assumptions!G226 -> 1 | E30: =Assumptions!B226 -> 1.1 | F30: =Assumptions!C226 -> 1.05 | G30: =Assumptions!D226 -> 1 | H30: =Assumptions!E226 -> 1 | I30: =Assumptions!F226 -> 0.95
B31: Rev Trajectory Drift | C31: =Assumptions!G227 -> 0 | E31: =Assumptions!B227 -> -0.03 | F31: =Assumptions!C227 -> -0.015 | G31: =Assumptions!D227 -> 0 | H31: =Assumptions!E227 -> 0.03 | I31: =Assumptions!F227 -> 0.05
B32: DSO Adjustment (days) | C32: =Assumptions!G228 -> 0 | E32: =Assumptions!B228 -> 8 | F32: =Assumptions!C228 -> 4 | G32: =Assumptions!D228 -> 0 | H32: =Assumptions!E228 -> -2 | I32: =Assumptions!F228 -> -3
B33: Insurance Base Factor | C33: =Assumptions!G229 -> 1 | E33: =Assumptions!B229 -> 1.1 | F33: =Assumptions!C229 -> 1.05 | G33: =Assumptions!D229 -> 1 | H33: =Assumptions!E229 -> 0.98 | I33: =Assumptions!F229 -> 0.95
B34: Maintenance CAPEX % | C34: =Assumptions!G230 -> 0.015 | E34: =Assumptions!B230 -> 0.012 | F34: =Assumptions!C230 -> 0.013 | G34: =Assumptions!D230 -> 0.015 | H34: =Assumptions!E230 -> 0.017 | I34: =Assumptions!F230 -> 0.018
B36: ACTIVE CREDIT FACILITY | E36: KEY MODEL OUTPUTS
B37: Parameter | C37: Active Value | E37: Metric | F37: FY2026E | G37: FY2027E | H37: FY2028E | I37: FY2029E
B38: Commitment ($K) | C38: =Assumptions!G187 -> 1000 | E38: Revenue ($K) | F38: ='Income Statement'!N3 -> 8365.3 | G38: ='Income Statement'!O3 -> 10079.48 | H38: ='Income Statement'!P3 -> 12130.851 | I38: ='Income Statement'!Q3 -> 14465.389
B39: Interest Rate | C39: =Assumptions!G188 -> 0.06 | E39: Gross Margin % | F39: ='Income Statement'!N6 -> 0.26257095 | G39: ='Income Statement'!O6 -> 0.2884748 | H39: ='Income Statement'!P6 -> 0.31056153 | I39: ='Income Statement'!Q6 -> 0.32841165
B40: Commitment Fee | C40: =Assumptions!G189 -> 0.006 | E40: EBITDA ($K) | F40: ='Income Statement'!N30 -> 1152.4848 | G40: ='Income Statement'!O30 -> 1800.676 | H40: ='Income Statement'!P30 -> 2565.3757 | I40: ='Income Statement'!Q30 -> 3442.6024
B41: Draw Schedule (%) | C41: =Assumptions!G191 -> 0.6 | E41: Net Income ($K) | F41: ='Income Statement'!N27 -> 235.44245 | G41: ='Income Statement'!O27 -> 524.42731 | H41: ='Income Statement'!P27 -> 978.49323 | I41: ='Income Statement'!Q27 -> 1469.5411
B42: Term (Months) | C42: =Assumptions!G192 -> 48 | E42: Free Cash Flow ($K) | F42: ='Cash Flow'!N15+'Cash Flow'!N22 -> -1277.5575 | G42: ='Cash Flow'!O15+'Cash Flow'!O22 -> 75.427307 | H42: ='Cash Flow'!P15+'Cash Flow'!P22 -> 744.49323 | I42: ='Cash Flow'!Q15+'Cash Flow'!Q22 -> 1304.5411
E43: Total Debt ($K) | F43: ='Debt Schedule'!N68 -> 4602.3639 | G43: ='Debt Schedule'!O68 -> 2967.6003 | H43: ='Debt Schedule'!P68 -> 2123.0706 | I43: ='Debt Schedule'!Q68 -> 1330.7032
B44: VALUATION SUMMARY
B45: Metric | C45: Value | E45: MODEL INTEGRITY CHECKS
B46: WACC | C46: =Assumptions!B11 -> 0.11147818 | E46: Check | G46: Status
B47: Terminal Growth Rate | C47: =Assumptions!B12 -> 0.025 | E47: Balance Sheet Balances | G47: =IF(ABS('Balance Sheet'!N49)<2,"✓ PASS","✗ FAIL: "&'Balance Sheet'!N49) -> ✓ PASS
B48: Enterprise Value ($K) | C48: ='DCF & Returns'!B24 -> 18169.2 | E48: Cash Flow Reconciles | G48: =IF(ABS('Cash Flow'!N38)<1,"✓ PASS","✗ FAIL: "&TEXT('Cash Flow'!N38,"#,##0.0")) -> ✓ PASS
B49: Net Debt ($K) | C49: ='DCF & Returns'!B26 -> -4602.3639 | E49: WACC > TGR | G49: =IF(Assumptions!B11>Assumptions!B12,"✓ PASS","✗ FAIL: WACC ≤ TGR") -> ✓ PASS
E50: Gross Margin Realistic | G50: =IF(AND('Income Statement'!N6>0.05,'Income Statement'!N6<0.6),"✓ PASS: "&TEXT('Income Statement'!N6,"0.0%"),"✗ FAIL: "&TEXT('Income Statement'!N6,"0.0%")) -> ✓ PASS: 26.3%
B51: Equity Value ($K) | C51: ='DCF & Returns'!B28 -> 16197.8 | E51: Revenue Positive | G51: =IF('Income Statement'!N3>0,"✓ PASS","✗ FAIL") -> ✓ PASS
E52: Equity Value Positive | G52: =IF('DCF & Returns'!B28>0,"✓ PASS: "&TEXT('DCF & Returns'!B28,"$#,##0"),"✗ WARNING: Negative equity") -> ✓ PASS: $16,198

Sheet Revenue Build
A1: APOLLO ENERGY RESOURCES — REVENUE BUILD
B2: 46048 | C2: 46079 | D2: 46107 | E2: 46138 | F2: 46168 | G2: 46199 | H2: 46229 | I2: 46260 | J2: 46291 | K2: 46321 | L2: 46352 | M2: 46382 | N2: FY2026 | O2: FY2027 | P2: FY2028 | Q2: FY2029 | R2: FY2030
A3: REVENUE BY DIVISION ($000s)
A4: Logistics | B4: =Assumptions!C23*Assumptions!B108*Assumptions!$G$170*(1-Assumptions!$G$162) -> 312.65 | C4: =Assumptions!C23*Assumptions!C108*Assumptions!$G$170*(1-Assumptions!$G$162) -> 312.65 | D4: =Assumptions!C23*Assumptions!D108*Assumptions!$G$170*(1-Assumptions!$G$162) -> 360.75 | E4: =Assumptions!C23*Assumptions!E108*Assumptions!$G$170*(1-Assumptions!$G$162) -> 408.85 | F4: =Assumptions!C23*Assumptions!F108*Assumptions!$G$170*(1-Assumptions!$G$162) -> 456.95 | G4: =Assumptions!C23*Assumptions!G108*Assumptions!$G$170*(1-Assumptions!$G$162) -> 481 | H4: =Assumptions!C23*Assumptions!H108*Assumptions!$G$170*(1-Assumptions!$G$162) -> 505.05 | I4: =Assumptions!C23*Assumptions!J108*Assumptions!$G$170*(1-Assumptions!$G$162) -> 505.05 | J4: =Assumptions!C23*Assumptions!K108*Assumptions!$G$170*(1-Assumptions!$G$162) -> 456.95 | K4: =Assumptions!C23*Assumptions!L108*Assumptions!$G$170*(1-Assumptions!$G$162) -> 384.8 | L4: =Assumptions!C23*Assumptions!M108*Assumptions!$G$170*(1-Assumptions!$G$162) -> 312.65 | M4: =Assumptions!C23*Assumptions!N108*Assumptions!$G$170*(1-Assumptions!$G$162) -> 312.65 | N4: =SUM(B4:M4) -> 4810 | O4: =Assumptions!D23*Assumptions!$G$170*(1+Assumptions!$G$227)^1*(1-Assumptions!$G$162) -> 5291 | P4: =Assumptions!E23*Assumptions!$G$170*(1+Assumptions!$G$227)^2*(1-Assumptions!$G$162) -> 5768 | Q4: =Assumptions!F23*Assumptions!$G$170*(1+Assumptions!$G$227)^3*(1-Assumptions!$G$162) -> 6287 | R4: =Assumptions!G23*Assumptions!$G$170*(1+Assumptions!$G$227)^4*(1-Assumptions!$G$162) -> 6859
A5: Field Services | B5: =Assumptions!C24*Assumptions!B109*Assumptions!$G$171*(1+Assumptions!$G$164*Assumptions!$G$163/5) -> 41.118 | C5: =Assumptions!C24*Assumptions!C109*Assumptions!$G$171*(1+Assumptions!$G$164*Assumptions!$G$163/5) -> 41.118 | D5: =Assumptions!C24*Assumptions!D109*Assumptions!$G$171*(1+Assumptions!$G$164*Assumptions!$G$163/5) -> 47.971 | E5: =Assumptions!C24*Assumptions!E109*Assumptions!$G$171*(1+Assumptions!$G$164*Assumptions!$G$163/5) -> 58.2505 | F5: =Assumptions!C24*Assumptions!F109*Assumptions!$G$171*(1+Assumptions!$G$164*Assumptions!$G$163/5) -> 68.53 | G5: =Assumptions!C24*Assumptions!G109*Assumptions!$G$171*(1+Assumptions!$G$164*Assumptions!$G$163/5) -> 75.383 | H5: =Assumptions!C24*Assumptions!H109*Assumptions!$G$171*(1+Assumptions!$G$164*Assumptions!$G$163/5) -> 78.8095 | I5: =Assumptions!C24*Assumptions!J109*Assumptions!$G$171*(1+Assumptions!$G$164*Assumptions!$G$163/5) -> 75.383 | J5: =Assumptions!C24*Assumptions!K109*Assumptions!$G$171*(1+Assumptions!$G$164*Assumptions!$G$163/5) -> 65.1035 | K5: =Assumptions!C24*Assumptions!L109*Assumptions!$G$171*(1+Assumptions!$G$164*Assumptions!$G$163/5) -> 51.3975 | L5: =Assumptions!C24*Assumptions!M109*Assumptions!$G$171*(1+Assumptions!$G$164*Assumptions!$G$163/5) -> 44.5445 | M5: =Assumptions!C24*Assumptions!N109*Assumptions!$G$171*(1+Assumptions!$G$164*Assumptions!$G$163/5) -> 37.6915 | N5: =SUM(B5:M5) -> 685.3 | O5: =Assumptions!D24*Assumptions!$G$171*(1+Assumptions!$G$227)^1*(1+Assumptions!$G$164*Assumptions!$G$163/5) -> 959.2 | P5: =Assumptions!E24*Assumptions!$G$171*(1+Assumptions!$G$227)^2*(1+Assumptions!$G$164*Assumptions!$G$163/5) -> 1247.4 | Q5: =Assumptions!F24*Assumptions!$G$171*(1+Assumptions!$G$227)^3*(1+Assumptions!$G$164*Assumptions!$G$163/5) -> 1559.8 | R5: =Assumptions!G24*Assumptions!$G$171*(1+Assumptions!$G$227)^4*(1+Assumptions!$G$164*Assumptions!$G$163/5) -> 1872.2
A6: Installations | B6: =Assumptions!C25*Assumptions!B110*Assumptions!$G$174 -> 77 | C6: =Assumptions!C25*Assumptions!C110*Assumptions!$G$174 -> 84 | D6: =Assumptions!C25*Assumptions!D110*Assumptions!$G$174 -> 105 | E6: =Assumptions!C25*Assumptions!E110*Assumptions!$G$174 -> 126 | F6: =Assumptions!C25*Assumptions!F110*Assumptions!$G$174 -> 147 | G6: =Assumptions!C25*Assumptions!G110*Assumptions!$G$174 -> 161 | H6: =Assumptions!C25*Assumptions!H110*Assumptions!$G$174 -> 168 | I6: =Assumptions!C25*Assumptions!J110*Assumptions!$G$174 -> 161 | J6: =Assumptions!C25*Assumptions!K110*Assumptions!$G$174 -> 133 | K6: =Assumptions!C25*Assumptions!L110*Assumptions!$G$174 -> 105 | L6: =Assumptions!C25*Assumptions!M110*Assumptions!$G$174 -> 70 | M6: =Assumptions!C25*Assumptions!N110*Assumptions!$G$174 -> 63 | N6: =SUM(B6:M6) -> 1400 | O6: =Assumptions!D25*Assumptions!$G$174*(1+Assumptions!$G$227)^1 -> 2203 | P6: =Assumptions!E25*Assumptions!$G$174*(1+Assumptions!$G$227)^2 -> 3304 | Q6: =Assumptions!F25*Assumptions!$G$174*(1+Assumptions!$G$227)^3 -> 4626 | R6: =Assumptions!G25*Assumptions!$G$174*(1+Assumptions!$G$227)^4 -> 5782
A7: Apollo Fleet Services | B7: =Assumptions!C26*Assumptions!B111*Assumptions!$G$172 -> 8.325 | C7: =Assumptions!C26*Assumptions!C111*Assumptions!$G$172 -> 8.325 | D7: =Assumptions!C26*Assumptions!D111*Assumptions!$G$172 -> 8.88 | E7: =Assumptions!C26*Assumptions!E111*Assumptions!$G$172 -> 9.435 | F7: =Assumptions!C26*Assumptions!F111*Assumptions!$G$172 -> 9.99 | G7: =Assumptions!C26*Assumptions!G111*Assumptions!$G$172 -> 10.545 | H7: =Assumptions!C26*Assumptions!H111*Assumptions!$G$172 -> 10.545 | I7: =Assumptions!C26*Assumptions!J111*Assumptions!$G$172 -> 9.99 | J7: =Assumptions!C26*Assumptions!K111*Assumptions!$G$172 -> 9.435 | K7: =Assumptions!C26*Assumptions!L111*Assumptions!$G$172 -> 8.88 | L7: =Assumptions!C26*Assumptions!M111*Assumptions!$G$172 -> 8.325 | M7: =Assumptions!C26*Assumptions!N111*Assumptions!$G$172 -> 8.325 | N7: =SUM(B7:M7) -> 111 | O7: =Assumptions!D26*Assumptions!$G$172*(1+Assumptions!$G$227)^1 -> 167 | P7: =Assumptions!E26*Assumptions!$G$172*(1+Assumptions!$G$227)^2 -> 234 | Q7: =Assumptions!F26*Assumptions!$G$172*(1+Assumptions!$G$227)^3 -> 304 | R7: =Assumptions!G26*Assumptions!$G$172*(1+Assumptions!$G$227)^4 -> 380
A8: Apollo Power Management | B8: =Assumptions!C27*Assumptions!B112*Assumptions!$G$173 -> 7.08 | C8: =Assumptions!C27*Assumptions!C112*Assumptions!$G$173 -> 7.965 | D8: =Assumptions!C27*Assumptions!D112*Assumptions!$G$173 -> 10.62 | E8: =Assumptions!C27*Assumptions!E112*Assumptions!$G$173 -> 14.16 | F8: =Assumptions!C27*Assumptions!F112*Assumptions!$G$173 -> 17.7 | G8: =Assumptions!C27*Assumptions!G112*Assumptions!$G$173 -> 23.01 | H8: =Assumptions!C27*Assumptions!H112*Assumptions!$G$173 -> 24.78 | I8: =Assumptions!C27*Assumptions!J112*Assumptions!$G$173 -> 23.01 | J8: =Assumptions!C27*Assumptions!K112*Assumptions!$G$173 -> 17.7 | K8: =Assumptions!C27*Assumptions!L112*Assumptions!$G$173 -> 13.275 | L8: =Assumptions!C27*Assumptions!M112*Assumptions!$G$173 -> 9.735 | M8: =Assumptions!C27*Assumptions!N112*Assumptions!$G$173 -> 7.965 | N8: =SUM(B8:M8) -> 177 | O8: =Assumptions!D27*Assumptions!$G$173*(1+Assumptions!$G$227)^1 -> 230 | P8: =Assumptions!E27*Assumptions!$G$173*(1+Assumptions!$G$227)^2 -> 299 | Q8: =Assumptions!F27*Assumptions!$G$173*(1+Assumptions!$G$227)^3 -> 359 | R8: =Assumptions!G27*Assumptions!$G$173*(1+Assumptions!$G$227)^4 -> 413
A9: Brokerage | B9: =Assumptions!$B$32/12 -> 98.5 | C9: =Assumptions!$B$32/12 -> 98.5 | D9: =Assumptions!$B$32/12 -> 98.5 | E9: =Assumptions!$B$32/12 -> 98.5 | F9: =Assumptions!$B$32/12 -> 98.5 | G9: =Assumptions!$B$32/12 -> 98.5 | H9: =Assumptions!$B$32/12 -> 98.5 | I9: =Assumptions!$B$32/12 -> 98.5 | ... M9: =Assumptions!$B$32/12 -> 98.5 | N9: =SUM(B9:M9) -> 1182 | O9: =N9*(1+Assumptions!$B$34) -> 1229.28 | P9: =O9*(1+Assumptions!$B$34) -> 1278.4512 | Q9: =P9*(1+Assumptions!$B$34) -> 1329.5892 | R9: =Q9*(1+Assumptions!$B$34) -> 1382.7728
A10: Total Revenue | B10: =SUM(B4:B9) -> 544.673 | C10: =SUM(C4:C9) -> 552.558 | D10: =SUM(D4:D9) -> 631.721 | E10: =SUM(E4:E9) -> 715.1955 | F10: =SUM(F4:F9) -> 798.67 | G10: =SUM(G4:G9) -> 849.438 | H10: =SUM(H4:H9) -> 885.6845 | I10: =SUM(I4:I9) -> 872.933 | ... M10: =SUM(M4:M9) -> 528.1315 | N10: =SUM(B10:M10) -> 8365.3 | O10: =SUM(O4:O9) -> 10079.48 | P10: =SUM(P4:P9) -> 12130.851 | Q10: =SUM(Q4:Q9) -> 14465.389 | R10: =SUM(R4:R9) -> 16688.973
A12: COST OF GOODS SOLD ($000s)
A13: Logistics | B13: =-B4*(1-(Assumptions!C38+Assumptions!$G$177+Assumptions!B117)) -> -237.614 | C13: =-C4*(1-(Assumptions!C38+Assumptions!$G$177+Assumptions!C117)) -> -237.614 | D13: =-D4*(1-(Assumptions!C38+Assumptions!$G$177+Assumptions!D117)) -> -277.7775 | E13: =-E4*(1-(Assumptions!C38+Assumptions!$G$177+Assumptions!E117)) -> -318.903 | F13: =-F4*(1-(Assumptions!C38+Assumptions!$G$177+Assumptions!F117)) -> -360.9905 | G13: =-G4*(1-(Assumptions!C38+Assumptions!$G$177+Assumptions!G117)) -> -384.8 | H13: =-H4*(1-(Assumptions!C38+Assumptions!$G$177+Assumptions!H117)) -> -404.04 | I13: =-I4*(1-(Assumptions!C38+Assumptions!$G$177+Assumptions!J117)) -> -404.04 | J13: =-J4*(1-(Assumptions!C38+Assumptions!$G$177+Assumptions!K117)) -> -360.9905 | K13: =-K4*(1-(Assumptions!C38+Assumptions!$G$177+Assumptions!L117)) -> -300.144 | L13: =-L4*(1-(Assumptions!C38+Assumptions!$G$177+Assumptions!M117)) -> -240.7405 | M13: =-M4*(1-(Assumptions!C38+Assumptions!$G$177+Assumptions!N117)) -> -237.614 | N13: =SUM(B13:M13) -> -3765.268 | O13: =-O4*(1-(Assumptions!D38+Assumptions!$G$177)) -> -4021.16 | P13: =-P4*(1-(Assumptions!E38+Assumptions!$G$177)) -> -4326 | Q13: =-Q4*(1-(Assumptions!F38+Assumptions!$G$177)) -> -4652.38 | R13: =-R4*(1-(Assumptions!G38+Assumptions!$G$177)) -> -5007.07
A14: Field Services | B14: =-B5*(1-(Assumptions!C39+Assumptions!$G$178+Assumptions!B118)) -> -26.7267 | C14: =-C5*(1-(Assumptions!C39+Assumptions!$G$178+Assumptions!C118)) -> -26.7267 | D14: =-D5*(1-(Assumptions!C39+Assumptions!$G$178+Assumptions!D118)) -> -30.22173 | E14: =-E5*(1-(Assumptions!C39+Assumptions!$G$178+Assumptions!E118)) -> -35.532805 | F14: =-F5*(1-(Assumptions!C39+Assumptions!$G$178+Assumptions!F118)) -> -41.118 | G14: =-G5*(1-(Assumptions!C39+Assumptions!$G$178+Assumptions!G118)) -> -44.47597 | H14: =-H5*(1-(Assumptions!C39+Assumptions!$G$178+Assumptions!H118)) -> -46.497605 | I14: =-I5*(1-(Assumptions!C39+Assumptions!$G$178+Assumptions!J118)) -> -44.47597 | J14: =-J5*(1-(Assumptions!C39+Assumptions!$G$178+Assumptions!K118)) -> -39.713135 | K14: =-K5*(1-(Assumptions!C39+Assumptions!$G$178+Assumptions!L118)) -> -32.380425 | L14: =-L5*(1-(Assumptions!C39+Assumptions!$G$178+Assumptions!M118)) -> -28.50848 | M14: =-M5*(1-(Assumptions!C39+Assumptions!$G$178+Assumptions!N118)) -> -24.499475 | N14: =SUM(B14:M14) -> -420.877 | O14: =-O5*(1-(Assumptions!D39+Assumptions!$G$178)) -> -604.296 | P14: =-P5*(1-(Assumptions!E39+Assumptions!$G$178)) -> -785.862 | Q14: =-Q5*(1-(Assumptions!F39+Assumptions!$G$178)) -> -967.076 | R14: =-R5*(1-(Assumptions!G39+Assumptions!$G$178)) -> -1142.042
A15: Installations | B15: =-B6*(1-(Assumptions!C40+Assumptions!$G$181+Assumptions!B119)) -> -43.89 | C15: =-C6*(1-(Assumptions!C40+Assumptions!$G$181+Assumptions!C119)) -> -47.88 | D15: =-D6*(1-(Assumptions!C40+Assumptions!$G$181+Assumptions!D119)) -> -58.8 | E15: =-E6*(1-(Assumptions!C40+Assumptions!$G$181+Assumptions!E119)) -> -68.04 | F15: =-F6*(1-(Assumptions!C40+Assumptions!$G$181+Assumptions!F119)) -> -77.91 | G15: =-G6*(1-(Assumptions!C40+Assumptions!$G$181+Assumptions!G119)) -> -85.33 | H15: =-H6*(1-(Assumptions!C40+Assumptions!$G$181+Assumptions!H119)) -> -89.04 | I15: =-I6*(1-(Assumptions!C40+Assumptions!$G$181+Assumptions!J119)) -> -85.33 | J15: =-J6*(1-(Assumptions!C40+Assumptions!$G$181+Assumptions!K119)) -> -73.15 | K15: =-K6*(1-(Assumptions!C40+Assumptions!$G$181+Assumptions!L119)) -> -58.8 | L15: =-L6*(1-(Assumptions!C40+Assumptions!$G$181+Assumptions!M119)) -> -39.2 | M15: =-M6*(1-(Assumptions!C40+Assumptions!$G$181+Assumptions!N119)) -> -35.91 | N15: =SUM(B15:M15) -> -763.28 | O15: =-O6*(1-(Assumptions!D40+Assumptions!$G$181)) -> -1211.65 | P15: =-P6*(1-(Assumptions!E40+Assumptions!$G$181)) -> -1784.16 | Q15: =-Q6*(1-(Assumptions!F40+Assumptions!$G$181)) -> -2498.04 | R15: =-R6*(1-(Assumptions!G40+Assumptions!$G$181)) -> -3064.46
A16: Apollo Fleet Services | B16: =-B7*(1-(Assumptions!C41+Assumptions!$G$179+Assumptions!B120)) -> -6.24375 | C16: =-C7*(1-(Assumptions!C41+Assumptions!$G$179+Assumptions!C120)) -> -6.24375 | D16: =-D7*(1-(Assumptions!C41+Assumptions!$G$179+Assumptions!D120)) -> -6.66 | E16: =-E7*(1-(Assumptions!C41+Assumptions!$G$179+Assumptions!E120)) -> -7.07625 | F16: =-F7*(1-(Assumptions!C41+Assumptions!$G$179+Assumptions!F120)) -> -7.4925 | G16: =-G7*(1-(Assumptions!C41+Assumptions!$G$179+Assumptions!G120)) -> -7.90875 | H16: =-H7*(1-(Assumptions!C41+Assumptions!$G$179+Assumptions!H120)) -> -7.90875 | I16: =-I7*(1-(Assumptions!C41+Assumptions!$G$179+Assumptions!J120)) -> -7.4925 | J16: =-J7*(1-(Assumptions!C41+Assumptions!$G$179+Assumptions!K120)) -> -7.07625 | K16: =-K7*(1-(Assumptions!C41+Assumptions!$G$179+Assumptions!L120)) -> -6.66 | L16: =-L7*(1-(Assumptions!C41+Assumptions!$G$179+Assumptions!M120)) -> -6.24375 | M16: =-M7*(1-(Assumptions!C41+Assumptions!$G$179+Assumptions!N120)) -> -6.24375 | N16: =SUM(B16:M16) -> -83.25 | O16: =-O7*(1-(Assumptions!D41+Assumptions!$G$179)) -> -121.91 | P16: =-P7*(1-(Assumptions!E41+Assumptions!$G$179)) -> -168.48 | Q16: =-Q7*(1-(Assumptions!F41+Assumptions!$G$179)) -> -215.84 | R16: =-R7*(1-(Assumptions!G41+Assumptions!$G$179)) -> -266
A17: Apollo Power Management | B17: =-B8*(1-(Assumptions!C42+Assumptions!$G$180+Assumptions!B121)) -> -5.4516 | C17: =-C8*(1-(Assumptions!C42+Assumptions!$G$180+Assumptions!C121)) -> -6.13305 | D17: =-D8*(1-(Assumptions!C42+Assumptions!$G$180+Assumptions!D121)) -> -8.0712 | E17: =-E8*(1-(Assumptions!C42+Assumptions!$G$180+Assumptions!E121)) -> -10.7616 | F17: =-F8*(1-(Assumptions!C42+Assumptions!$G$180+Assumptions!F121)) -> -13.098 | G17: =-G8*(1-(Assumptions!C42+Assumptions!$G$180+Assumptions!G121)) -> -16.5672 | H17: =-H8*(1-(Assumptions!C42+Assumptions!$G$180+Assumptions!H121)) -> -17.8416 | I17: =-I8*(1-(Assumptions!C42+Assumptions!$G$180+Assumptions!J121)) -> -16.7973 | J17: =-J8*(1-(Assumptions!C42+Assumptions!$G$180+Assumptions!K121)) -> -13.098 | K17: =-K8*(1-(Assumptions!C42+Assumptions!$G$180+Assumptions!L121)) -> -10.089 | L17: =-L8*(1-(Assumptions!C42+Assumptions!$G$180+Assumptions!M121)) -> -7.3986 | M17: =-M8*(1-(Assumptions!C42+Assumptions!$G$180+Assumptions!N121)) -> -6.13305 | N17: =SUM(B17:M17) -> -131.4402 | O17: =-O8*(1-(Assumptions!D42+Assumptions!$G$180)) -> -167.9 | P17: =-P8*(1-(Assumptions!E42+Assumptions!$G$180)) -> -212.29 | Q17: =-Q8*(1-(Assumptions!F42+Assumptions!$G$180)) -> -251.3 | R17: =-R8*(1-(Assumptions!G42+Assumptions!$G$180)) -> -284.97
A18: Brokerage | B18: =-B9*(1-Assumptions!$B$31) -> -83.725 | C18: =-C9*(1-Assumptions!$B$31) -> -83.725 | D18: =-D9*(1-Assumptions!$B$31) -> -83.725 | E18: =-E9*(1-Assumptions!$B$31) -> -83.725 | F18: =-F9*(1-Assumptions!$B$31) -> -83.725 | G18: =-G9*(1-Assumptions!$B$31) -> -83.725 | H18: =-H9*(1-Assumptions!$B$31) -> -83.725 | I18: =-I9*(1-Assumptions!$B$31) -> -83.725 | ... M18: =-M9*(1-Assumptions!$B$31) -> -83.725 | N18: =SUM(B18:M18) -> -1004.7 | O18: =-O9*(1-Assumptions!$B$31) -> -1044.888 | P18: =-P9*(1-Assumptions!$B$31) -> -1086.6835 | Q18: =-Q9*(1-Assumptions!$B$31) -> -1130.1509 | R18: =-R9*(1-Assumptions!$B$31) -> -1175.3569
A19: Total COGS | B19: =SUM(B13:B18) -> -403.65105 | C19: =SUM(C13:C18) -> -408.3225 | D19: =SUM(D13:D18) -> -465.25543 | E19: =SUM(E13:E18) -> -524.03866 | F19: =SUM(F13:F18) -> -584.334 | G19: =SUM(G13:G18) -> -622.80692 | H19: =SUM(H13:H18) -> -649.05295 | I19: =SUM(I13:I18) -> -641.86077 | ... M19: =SUM(M13:M18) -> -394.12528 | N19: =SUM(B19:M19) -> -6168.8152 | O19: =SUM(O13:O18) -> -7171.804 | P19: =SUM(P13:P18) -> -8363.4755 | Q19: =SUM(Q13:Q18) -> -9714.7869 | R19: =SUM(R13:R18) -> -10939.899
A20: Gross Margin % | B20: =1+B19/B10 -> 0.25891122 | C20: =1+C19/C10 -> 0.26103233 | D20: =1+D19/D10 -> 0.26351122 | E20: =1+E19/E10 -> 0.26727915 | F20: =1+F19/F10 -> 0.26836616 | G20: =1+G19/G10 -> 0.2668012 | H20: =1+H19/H10 -> 0.26717363 | I20: =1+I19/I10 -> 0.26470786 | ... R20: =1+R19/R10 -> 0.34448339
A22: GROSS PROFIT ($000s)
A23: Gross Profit | B23: =B10+B19 -> 141.02195 | C23: =C10+C19 -> 144.2355 | D23: =D10+D19 -> 166.46557 | E23: =E10+E19 -> 191.15684 | F23: =F10+F19 -> 214.336 | G23: =G10+G19 -> 226.63108 | H23: =H10+H19 -> 236.63154 | I23: =I10+I19 -> 231.07223 | ... R23: =R10+R19 -> 5749.0739
A24: Gross Margin % | B24: =B23/B10 -> 0.25891122 | C24: =C23/C10 -> 0.26103233 | D24: =D23/D10 -> 0.26351122 | E24: =E23/E10 -> 0.26727915 | F24: =F23/F10 -> 0.26836616 | G24: =G23/G10 -> 0.2668012 | H24: =H23/H10 -> 0.26717363 | I24: =I23/I10 -> 0.26470786 | ... R24: =R23/R10 -> 0.34448339
A25: Apollo Energy Resources — Confidential | Revenue Build | Mar 2026

Sheet Income Statement
A1: APOLLO ENERGY RESOURCES — CONSOLIDATED INCOME STATEMENT ($000s)
B2: 46048 | C2: 46079 | D2: 46107 | E2: 46138 | F2: 46168 | G2: 46199 | H2: 46229 | I2: 46260 | J2: 46291 | K2: 46321 | L2: 46352 | M2: 46382 | N2: FY2026 | O2: FY2027 | P2: FY2028 | Q2: FY2029 | R2: FY2030
A3: Revenue | B3: ='Revenue Build'!B10 -> 544.673 | C3: ='Revenue Build'!C10 -> 552.558 | D3: ='Revenue Build'!D10 -> 631.721 | E3: ='Revenue Build'!E10 -> 715.1955 | F3: ='Revenue Build'!F10 -> 798.67 | G3: ='Revenue Build'!G10 -> 849.438 | H3: ='Revenue Build'!H10 -> 885.6845 | I3: ='Revenue Build'!I10 -> 872.933 | ... M3: ='Revenue Build'!M10 -> 528.1315 | N3: =SUM(B3:M3) -> 8365.3 | O3: ='Revenue Build'!O10 -> 10079.48 | P3: ='Revenue Build'!P10 -> 12130.851 | Q3: ='Revenue Build'!Q10 -> 14465.389 | R3: ='Revenue Build'!R10 -> 16688.973
A4: Cost of Goods Sold | B4: ='Revenue Build'!B19 -> -403.65105 | C4: ='Revenue Build'!C19 -> -408.3225 | D4: ='Revenue Build'!D19 -> -465.25543 | E4: ='Revenue Build'!E19 -> -524.03866 | F4: ='Revenue Build'!F19 -> -584.334 | G4: ='Revenue Build'!G19 -> -622.80692 | H4: ='Revenue Build'!H19 -> -649.05295 | I4: ='Revenue Build'!I19 -> -641.86077 | ... M4: ='Revenue Build'!M19 -> -394.12528 | N4: =SUM(B4:M4) -> -6168.8152 | O4: ='Revenue Build'!O19 -> -7171.804 | P4: ='Revenue Build'!P19 -> -8363.4755 | Q4: ='Revenue Build'!Q19 -> -9714.7869 | R4: ='Revenue Build'!R19 -> -10939.899
A5: Gross Profit | B5: =B3+B4 -> 141.02195 | C5: =C3+C4 -> 144.2355 | D5: =D3+D4 -> 166.46557 | E5: =E3+E4 -> 191.15684 | F5: =F3+F4 -> 214.336 | G5: =G3+G4 -> 226.63108 | H5: =H3+H4 -> 236.63154 | I5: =I3+I4 -> 231.07223 | ... R5: =R3+R4 -> 5749.0739
A6: Gross Margin % | B6: =B5/B3 -> 0.25891122 | C6: =C5/C3 -> 0.26103233 | D6: =D5/D3 -> 0.26351122 | E6: =E5/E3 -> 0.26727915 | F6: =F5/F3 -> 0.26836616 | G6: =G5/G3 -> 0.2668012 | H6: =H5/H3 -> 0.26717363 | I6: =I5/I3 -> 0.26470786 | ... R6: =R5/R3 -> 0.34448339
A8: Operating Expenses:
A9: Insurance — Total | B9: =Assumptions!$C50*Assumptions!$G$158*(0.7/12+0.3*'Revenue Build'!B10/'Revenue Build'!$N10) -> 48.666645 | C9: =Assumptions!$C50*Assumptions!$G$158*(0.7/12+0.3*'Revenue Build'!C10/'Revenue Build'!$N10) -> 48.843379 | D9: =Assumptions!$C50*Assumptions!$G$158*(0.7/12+0.3*'Revenue Build'!D10/'Revenue Build'!$N10) -> 50.61774 | E9: =Assumptions!$C50*Assumptions!$G$158*(0.7/12+0.3*'Revenue Build'!E10/'Revenue Build'!$N10) -> 52.488739 | F9: =Assumptions!$C50*Assumptions!$G$158*(0.7/12+0.3*'Revenue Build'!F10/'Revenue Build'!$N10) -> 54.359739 | G9: =Assumptions!$C50*Assumptions!$G$158*(0.7/12+0.3*'Revenue Build'!G10/'Revenue Build'!$N10) -> 55.497654 | H9: =Assumptions!$C50*Assumptions!$G$158*(0.7/12+0.3*'Revenue Build'!H10/'Revenue Build'!$N10) -> 56.310083 | I9: =Assumptions!$C50*Assumptions!$G$158*(0.7/12+0.3*'Revenue Build'!I10/'Revenue Build'!$N10) -> 56.024271 | ... M9: =Assumptions!$C50*Assumptions!$G$158*(0.7/12+0.3*'Revenue Build'!M10/'Revenue Build'!$N10) -> 48.295883 | N9: =SUM(B9:M9) -> 625 | O9: =Assumptions!D50*Assumptions!$G$158 -> 656 | P9: =Assumptions!E50*Assumptions!$G$158 -> 688 | Q9: =Assumptions!F50*Assumptions!$G$158 -> 723 | R9: =Assumptions!G50*Assumptions!$G$158 -> 759
A10: Back-Office / Admin Payroll | B10: =Assumptions!$C52*(0.7/12+0.3*'Revenue Build'!B10/'Revenue Build'!$N10) -> 16.274126 | C10: =Assumptions!$C52*(0.7/12+0.3*'Revenue Build'!C10/'Revenue Build'!$N10) -> 16.333226 | D10: =Assumptions!$C52*(0.7/12+0.3*'Revenue Build'!D10/'Revenue Build'!$N10) -> 16.926572 | E10: =Assumptions!$C52*(0.7/12+0.3*'Revenue Build'!E10/'Revenue Build'!$N10) -> 17.552234 | F10: =Assumptions!$C52*(0.7/12+0.3*'Revenue Build'!F10/'Revenue Build'!$N10) -> 18.177897 | G10: =Assumptions!$C52*(0.7/12+0.3*'Revenue Build'!G10/'Revenue Build'!$N10) -> 18.558415 | H10: =Assumptions!$C52*(0.7/12+0.3*'Revenue Build'!H10/'Revenue Build'!$N10) -> 18.830092 | I10: =Assumptions!$C52*(0.7/12+0.3*'Revenue Build'!I10/'Revenue Build'!$N10) -> 18.734516 | ... M10: =Assumptions!$C52*(0.7/12+0.3*'Revenue Build'!M10/'Revenue Build'!$N10) -> 16.150143 | N10: =SUM(B10:M10) -> 209 | O10: =Assumptions!D52 -> 252 | P10: =Assumptions!E52 -> 291 | Q10: =Assumptions!F52 -> 333 | R10: =Assumptions!G52 -> 367
A11: Corporate Overhead (G&A) | B11: =Assumptions!$C53*(0.7/12+0.3*'Revenue Build'!B10/'Revenue Build'!$N10) -> 6.2293305 | C11: =Assumptions!$C53*(0.7/12+0.3*'Revenue Build'!C10/'Revenue Build'!$N10) -> 6.2519526 | D11: =Assumptions!$C53*(0.7/12+0.3*'Revenue Build'!D10/'Revenue Build'!$N10) -> 6.4790708 | E11: =Assumptions!$C53*(0.7/12+0.3*'Revenue Build'!E10/'Revenue Build'!$N10) -> 6.7185586 | F11: =Assumptions!$C53*(0.7/12+0.3*'Revenue Build'!F10/'Revenue Build'!$N10) -> 6.9580465 | G11: =Assumptions!$C53*(0.7/12+0.3*'Revenue Build'!G10/'Revenue Build'!$N10) -> 7.1036996 | H11: =Assumptions!$C53*(0.7/12+0.3*'Revenue Build'!H10/'Revenue Build'!$N10) -> 7.2076907 | I11: =Assumptions!$C53*(0.7/12+0.3*'Revenue Build'!I10/'Revenue Build'!$N10) -> 7.1711067 | ... M11: =Assumptions!$C53*(0.7/12+0.3*'Revenue Build'!M10/'Revenue Build'!$N10) -> 6.1818731 | N11: =SUM(B11:M11) -> 80 | O11: =Assumptions!D53 -> 84 | P11: =Assumptions!E53 -> 88 | Q11: =Assumptions!F53 -> 92 | R11: =Assumptions!G53 -> 97
A12: Sales & Marketing | B12: =Assumptions!$C54*(0.7/12+0.3*'Revenue Build'!B10/'Revenue Build'!$N10) -> 6.2293305 | C12: =Assumptions!$C54*(0.7/12+0.3*'Revenue Build'!C10/'Revenue Build'!$N10) -> 6.2519526 | D12: =Assumptions!$C54*(0.7/12+0.3*'Revenue Build'!D10/'Revenue Build'!$N10) -> 6.4790708 | E12: =Assumptions!$C54*(0.7/12+0.3*'Revenue Build'!E10/'Revenue Build'!$N10) -> 6.7185586 | F12: =Assumptions!$C54*(0.7/12+0.3*'Revenue Build'!F10/'Revenue Build'!$N10) -> 6.9580465 | G12: =Assumptions!$C54*(0.7/12+0.3*'Revenue Build'!G10/'Revenue Build'!$N10) -> 7.1036996 | H12: =Assumptions!$C54*(0.7/12+0.3*'Revenue Build'!H10/'Revenue Build'!$N10) -> 7.2076907 | I12: =Assumptions!$C54*(0.7/12+0.3*'Revenue Build'!I10/'Revenue Build'!$N10) -> 7.1711067 | ... M12: =Assumptions!$C54*(0.7/12+0.3*'Revenue Build'!M10/'Revenue Build'!$N10) -> 6.1818731 | N12: =SUM(B12:M12) -> 80 | O12: =Assumptions!D54 -> 80 | P12: =Assumptions!E54 -> 100 | Q12: =Assumptions!F54 -> 120 | R12: =Assumptions!G54 -> 150
A13: Software / Hardware / IT | B13: =Assumptions!$C55*(0.7/12+0.3*'Revenue Build'!B10/'Revenue Build'!$N10) -> 3.8933316 | C13: =Assumptions!$C55*(0.7/12+0.3*'Revenue Build'!C10/'Revenue Build'!$N10) -> 3.9074703 | D13: =Assumptions!$C55*(0.7/12+0.3*'Revenue Build'!D10/'Revenue Build'!$N10) -> 4.0494192 | E13: =Assumptions!$C55*(0.7/12+0.3*'Revenue Build'!E10/'Revenue Build'!$N10) -> 4.1990992 | F13: =Assumptions!$C55*(0.7/12+0.3*'Revenue Build'!F10/'Revenue Build'!$N10) -> 4.3487791 | G13: =Assumptions!$C55*(0.7/12+0.3*'Revenue Build'!G10/'Revenue Build'!$N10) -> 4.4398123 | H13: =Assumptions!$C55*(0.7/12+0.3*'Revenue Build'!H10/'Revenue Build'!$N10) -> 4.5048067 | I13: =Assumptions!$C55*(0.7/12+0.3*'Revenue Build'!I10/'Revenue Build'!$N10) -> 4.4819417 | ... M13: =Assumptions!$C55*(0.7/12+0.3*'Revenue Build'!M10/'Revenue Build'!$N10) -> 3.8636707 | N13: =SUM(B13:M13) -> 50 | O13: =Assumptions!D55 -> 35 | P13: =Assumptions!E55 -> 35 | Q13: =Assumptions!F55 -> 40 | R13: =Assumptions!G55 -> 40
A14: Depreciation & Amortization | B14: =Assumptions!C56/12 -> 38.833333 | C14: =Assumptions!C56/12 -> 38.833333 | D14: =Assumptions!C56/12 -> 38.833333 | E14: =Assumptions!C56/12 -> 38.833333 | F14: =Assumptions!C56/12 -> 38.833333 | G14: =Assumptions!C56/12 -> 38.833333 | H14: =Assumptions!C56/12 -> 38.833333 | I14: =Assumptions!C56/12 -> 38.833333 | J14: =Assumptions!C56/12 -> 38.833333 | K14: =Assumptions!C56/12 -> 38.833333 | L14: =Assumptions!C56/12 -> 38.833333 | M14: =Assumptions!C56/12 -> 38.833333 | N14: =SUM(B14:M14)+80 -> 546 | O14: =Assumptions!D56+80 -> 714 | P14: =Assumptions!E56+80 -> 914 | Q14: =Assumptions!F56+80 -> 1144 | R14: =Assumptions!G56+80 -> 1372
A16: Total Operating Expenses | B16: =SUM(B9:B14) -> 120.1261 | C16: =SUM(C9:C14) -> 120.42131 | D16: =SUM(D9:D14) -> 123.38521 | E16: =SUM(E9:E14) -> 126.51052 | F16: =SUM(F9:F14) -> 129.63584 | G16: =SUM(G9:G14) -> 131.53661 | H16: =SUM(H9:H14) -> 132.8937 | I16: =SUM(I9:I14) -> 132.41628 | ... R16: =SUM(R9:R14) -> 2785
A17: OpEx as % of Revenue | B17: =B16/B3 -> 0.22054718 | C17: =C16/C3 -> 0.21793425 | D17: =D16/D3 -> 0.19531598 | E17: =E16/E3 -> 0.17688943 | F17: =F16/F3 -> 0.16231465 | G17: =G16/G3 -> 0.15485134 | H17: =H16/H3 -> 0.15004632 | I17: =I16/I3 -> 0.15169122 | ... R17: =R16/R3 -> 0.16687666
A19: EBIT (Operating Income) | B19: =B5-B16 -> 20.895853 | C19: =C5-C16 -> 23.814186 | D19: =D5-D16 -> 43.080363 | E19: =E5-E16 -> 64.646321 | F19: =F5-F16 -> 84.700159 | G19: =G5-G16 -> 95.094466 | H19: =H5-H16 -> 103.73785 | I19: =I5-I16 -> 98.655955 | ... R19: =R5-R16 -> 2964.0739
A20: EBIT Margin % | B20: =B19/B3 -> 0.038364034 | C20: =C19/C3 -> 0.043098075 | D20: =D19/D3 -> 0.068195237 | E20: =E19/E3 -> 0.09038972 | F20: =F19/F3 -> 0.10605151 | G20: =G19/G3 -> 0.11194986 | H20: =H19/H3 -> 0.11712732 | I20: =I19/I3 -> 0.11301664 | ... R20: =R19/R3 -> 0.17760673
A22: Interest Expense | B22: ='Debt Schedule'!B69 -> 18.458333 | C22: ='Debt Schedule'!C69 -> 18.157066 | D22: ='Debt Schedule'!D69 -> 17.853865 | E22: ='Debt Schedule'!E69 -> 17.548719 | F22: ='Debt Schedule'!F69 -> 21.616614 | G22: ='Debt Schedule'!G69 -> 21.246142 | H22: ='Debt Schedule'!H69 -> 20.873327 | I22: ='Debt Schedule'!I69 -> 20.498156 | ... R22: ='Debt Schedule'!R69 -> 107.56207
A23: Other Income / Corporate Adjustment | B23: 0 | C23: 0 | D23: 0 | E23: 0 | F23: 0 | G23: 0 | H23: 0 | I23: 0 | J23: 0 | K23: 0 | L23: 0 | M23: 0 | N23: =SUM(B23:M23) -> 0 | O23: 0 | P23: 0 | Q23: 0 | R23: 0
A24: EBT (Earnings Before Tax) | B24: =B19-B22+B23 -> 2.4375199 | C24: =C19-C22+C23 -> 5.6571199 | D24: =D19-D22+D23 -> 25.226498 | E24: =E19-E22+E23 -> 47.097603 | F24: =F19-F22+F23 -> 63.083546 | G24: =G19-G22+G23 -> 73.848325 | H24: =H19-H22+H23 -> 82.864521 | I24: =I19-I22+I23 -> 78.157799 | ... R24: =R19-R22+R23 -> 2856.5119
A25: Tax Distributions (Pass-Through) | B25: =IF(B24>0,B24*Assumptions!$B$13,0) -> 0.75563118 | C25: =IF(C24>0,C24*Assumptions!$B$13,0) -> 1.7537072 | D25: =IF(D24>0,D24*Assumptions!$B$13,0) -> 7.8202143 | E25: =IF(E24>0,E24*Assumptions!$B$13,0) -> 14.600257 | F25: =IF(F24>0,F24*Assumptions!$B$13,0) -> 19.555899 | G25: =IF(G24>0,G24*Assumptions!$B$13,0) -> 22.892981 | H25: =IF(H24>0,H24*Assumptions!$B$13,0) -> 25.688002 | I25: =IF(I24>0,I24*Assumptions!$B$13,0) -> 24.228918 | ... R25: =IF(R24>0,R24*Assumptions!$B$13,0) -> 885.51868
A27: Net Income | B27: =B24-B25 -> 1.6818888 | C27: =C24-C25 -> 3.9034127 | D27: =D24-D25 -> 17.406284 | E27: =E24-E25 -> 32.497346 | F27: =F24-F25 -> 43.527647 | G27: =G24-G25 -> 50.955344 | H27: =H24-H25 -> 57.17652 | I27: =I24-I25 -> 53.928881 | ... R27: =R24-R25 -> 1970.9932
A28: Net Margin % | B28: =B27/B3 -> 0.0030878872 | C28: =C27/C3 -> 0.0070642589 | D28: =D27/D3 -> 0.027553752 | E28: =E27/E3 -> 0.045438409 | F28: =F27/F3 -> 0.054500165 | G28: =G27/G3 -> 0.059987126 | H28: =H27/H3 -> 0.064556306 | I28: =I27/I3 -> 0.061778947 | ... R28: =R27/R3 -> 0.11810153
A30: EBITDA | B30: =B19+B14 -> 59.729187 | C30: =C19+C14 -> 62.647519 | D30: =D19+D14 -> 81.913697 | E30: =E19+E14 -> 103.47965 | F30: =F19+F14 -> 123.53349 | G30: =G19+G14 -> 133.9278 | H30: =H19+H14 -> 142.57118 | I30: =I19+I14 -> 137.48929 | ... R30: =R19+R14 -> 4336.0739
A32: Apollo Energy Resources — Confidential | Income Statement | Mar 2026

Sheet Balance Sheet
A1: APOLLO ENERGY RESOURCES — BALANCE SHEET ($000s)
B2: Opening | C2: 46048 | D2: 46079 | E2: 46107 | F2: 46138 | G2: 46168 | H2: 46199 | I2: 46229 | J2: 46260 | K2: 46291 | L2: 46321 | M2: 46352 | N2: 46382 | O2: FY2027E | P2: FY2028E | Q2: FY2029E | R2: FY2030E
A3: ASSETS
A4: Current Assets
A5: Cash & Cash Equivalents | B5: =Assumptions!B127 -> 34 | C5: =C47-C6-C7-C8-C9-C15-C16-C17-C18-C19-C20-C21-C23 -> 3225.3222 | D5: =D47-D6-D7-D8-D9-D15-D16-D17-D18-D19-D20-D21-D23 -> 3149.3647 | E5: =E47-E6-E7-E8-E9-E15-E16-E17-E18-E19-E20-E21-E23 -> 3000.3916 | F5: =F47-F6-F7-F8-F9-F15-F16-F17-F18-F19-F20-F21-F23 -> 2861.8462 | G5: =G47-G6-G7-G8-G9-G15-G16-G17-G18-G19-G20-G21-G23 -> 3458.5063 | H5: =H47-H6-H7-H8-H9-H15-H16-H17-H18-H19-H20-H21-H23 -> 3342.5552 | I5: =I47-I6-I7-I8-I9-I15-I16-I17-I18-I19-I20-I21-I23 -> 3229.8925 | J5: =J47-J6-J7-J8-J9-J15-J16-J17-J18-J19-J20-J21-J23 -> 3138.8993 | ... M5: =M47-M6-M7-M8-M9-M15-M16-M17-M18-M19-M20-M21-M23 -> 2762.1768 | N5: ='Cash Flow'!N36 -> 2631.0098 | O5: ='Cash Flow'!O36 -> 1024.4751 | P5: ='Cash Flow'!P36 -> 836.37422 | Q5: ='Cash Flow'!Q36 -> 1216.2893 | R5: ='Cash Flow'!R36 -> 2202.2551
A6: Accounts Receivable | B6: =Assumptions!B128 -> 274 | C6: =ROUND('Income Statement'!B3/30*Assumptions!$B$68,0) -> 654 | D6: =ROUND('Income Statement'!C3/30*Assumptions!$B$68,0) -> 663 | E6: =ROUND('Income Statement'!D3/30*Assumptions!$B$68,0) -> 758 | F6: =ROUND('Income Statement'!E3/30*Assumptions!$B$68,0) -> 858 | G6: =ROUND('Income Statement'!F3/30*Assumptions!$B$68,0) -> 958 | H6: =ROUND('Income Statement'!G3/30*Assumptions!$B$68,0) -> 1019 | I6: =ROUND('Income Statement'!H3/30*Assumptions!$B$68,0) -> 1063 | J6: =ROUND('Income Statement'!I3/30*Assumptions!$B$68,0) -> 1048 | ... N6: =ROUND('Income Statement'!M3/30*Assumptions!$B$68,0) -> 634 | O6: =ROUND('Income Statement'!O3*Assumptions!D68/365,0) -> 967 | P6: =ROUND('Income Statement'!P3*Assumptions!E68/365,0) -> 1130 | Q6: =ROUND('Income Statement'!Q3*Assumptions!F68/365,0) -> 1308 | R6: =ROUND('Income Statement'!R3*Assumptions!G68/365,0) -> 1509
A7: Inventory (Fleet Services) | B7: =Assumptions!B129 -> 5 | C7: =ROUND('Revenue Build'!B7*Assumptions!$B$73,0) -> 1 | D7: =ROUND('Revenue Build'!C7*Assumptions!$B$73,0) -> 1 | E7: =ROUND('Revenue Build'!D7*Assumptions!$B$73,0) -> 1 | F7: =ROUND('Revenue Build'!E7*Assumptions!$B$73,0) -> 1 | G7: =ROUND('Revenue Build'!F7*Assumptions!$B$73,0) -> 1 | H7: =ROUND('Revenue Build'!G7*Assumptions!$B$73,0) -> 1 | I7: =ROUND('Revenue Build'!H7*Assumptions!$B$73,0) -> 1 | J7: =ROUND('Revenue Build'!I7*Assumptions!$B$73,0) -> 1 | ... N7: =ROUND('Revenue Build'!M7*Assumptions!$B$73,0) -> 1 | O7: =ROUND('Revenue Build'!O7*Assumptions!$B$73,0) -> 17 | P7: =ROUND('Revenue Build'!P7*Assumptions!$B$73,0) -> 23 | Q7: =ROUND('Revenue Build'!Q7*Assumptions!$B$73,0) -> 30 | R7: =ROUND('Revenue Build'!R7*Assumptions!$B$73,0) -> 38
A8: Prepaid Expenses | B8: =Assumptions!B130 -> 30 | C8: =ROUND('Income Statement'!B16*Assumptions!$B$74,0) -> 4 | D8: =ROUND('Income Statement'!C16*Assumptions!$B$74,0) -> 4 | E8: =ROUND('Income Statement'!D16*Assumptions!$B$74,0) -> 4 | F8: =ROUND('Income Statement'!E16*Assumptions!$B$74,0) -> 4 | G8: =ROUND('Income Statement'!F16*Assumptions!$B$74,0) -> 4 | H8: =ROUND('Income Statement'!G16*Assumptions!$B$74,0) -> 4 | I8: =ROUND('Income Statement'!H16*Assumptions!$B$74,0) -> 4 | J8: =ROUND('Income Statement'!I16*Assumptions!$B$74,0) -> 4 | ... N8: =ROUND('Income Statement'!M16*Assumptions!$B$74,0) -> 4 | O8: =ROUND('Income Statement'!O16*Assumptions!$B$74,0) -> 55 | P8: =ROUND('Income Statement'!P16*Assumptions!$B$74,0) -> 63 | Q8: =ROUND('Income Statement'!Q16*Assumptions!$B$74,0) -> 74 | R8: =ROUND('Income Statement'!R16*Assumptions!$B$74,0) -> 84
A9: Other Current Assets | B9: =Assumptions!B131 -> 41 | C9: =B9 -> 41 | D9: =B9 -> 41 | E9: =B9 -> 41 | F9: =B9 -> 41 | G9: =B9 -> 41 | H9: =B9 -> 41 | I9: =B9 -> 41 | J9: =B9 -> 41 | K9: =B9 -> 41 | L9: =B9 -> 41 | M9: =B9 -> 41 | N9: =ROUND('Income Statement'!N3*Assumptions!$B$35,0) -> 59 | O9: =ROUND('Income Statement'!O3*Assumptions!$B$35,0) -> 71 | P9: =ROUND('Income Statement'!P3*Assumptions!$B$35,0) -> 86 | Q9: =ROUND('Income Statement'!Q3*Assumptions!$B$35,0) -> 102 | R9: =ROUND('Income Statement'!R3*Assumptions!$B$35,0) -> 118
A10: Total Current Assets | B10: =SUM(B5:B9) -> 384 | C10: =SUM(C5:C9) -> 3925.3222 | D10: =SUM(D5:D9) -> 3858.3647 | E10: =SUM(E5:E9) -> 3804.3916 | F10: =SUM(F5:F9) -> 3765.8462 | G10: =SUM(G5:G9) -> 4462.5063 | H10: =SUM(H5:H9) -> 4407.5552 | I10: =SUM(I5:I9) -> 4338.8925 | ... R10: =SUM(R5:R9) -> 3951.2551
A12: Non-Current Assets
A13: PP&E (Gross) | B13: =Assumptions!B134 -> 1733 | C13: =B13+Assumptions!$C$65/12 -> 1828.5 | D13: =C13+Assumptions!$C$65/12 -> 1924 | E13: =D13+Assumptions!$C$65/12 -> 2019.5 | F13: =E13+Assumptions!$C$65/12 -> 2115 | G13: =F13+Assumptions!$C$65/12 -> 2210.5 | H13: =G13+Assumptions!$C$65/12 -> 2306 | I13: =H13+Assumptions!$C$65/12 -> 2401.5 | J13: =I13+Assumptions!$C$65/12 -> 2497 | K13: =J13+Assumptions!$C$65/12+200 -> 2792.5 | L13: =K13+Assumptions!$C$65/12 -> 2888 | M13: =L13+Assumptions!$C$65/12 -> 2983.5 | N13: =M13+Assumptions!$C$65/12 -> 3079 | O13: =N13+Assumptions!$D$65 -> 3916 | P13: =O13+Assumptions!$E$65 -> 4919 | Q13: =P13+Assumptions!$F$65 -> 6070 | R13: =Q13+Assumptions!$G$65 -> 7209
A14: Less: Accumulated Depreciation | B14: =Assumptions!B135 -> -394 | C14: =B14-'Income Statement'!B14 -> -432.83333 | D14: =C14-'Income Statement'!C14 -> -471.66667 | E14: =D14-'Income Statement'!D14 -> -510.5 | F14: =E14-'Income Statement'!E14 -> -549.33333 | G14: =F14-'Income Statement'!F14 -> -588.16667 | H14: =G14-'Income Statement'!G14 -> -627 | I14: =H14-'Income Statement'!H14 -> -665.83333 | J14: =I14-'Income Statement'!I14 -> -704.66667 | ... N14: =M14-'Income Statement'!M14 -> -860 | O14: =N14-Assumptions!$D$56 -> -1494 | P14: =O14-Assumptions!$E$56 -> -2328 | Q14: =P14-Assumptions!$F$56 -> -3392 | R14: =Q14-Assumptions!$G$56 -> -4684
A15: PP&E (Net) | B15: =B13+B14 -> 1339 | C15: =C13+C14 -> 1395.6667 | D15: =D13+D14 -> 1452.3333 | E15: =E13+E14 -> 1509 | F15: =F13+F14 -> 1565.6667 | G15: =G13+G14 -> 1622.3333 | H15: =H13+H14 -> 1679 | I15: =I13+I14 -> 1735.6667 | ... R15: =R13+R14 -> 2525
A16: Goodwill ¹ | B16: 0 | C16: 0 | D16: 0 | E16: 0 | F16: 0 | G16: 0 | H16: 0 | I16: 0 | J16: 0 | K16: 591.82 | L16: =K16 -> 591.82 | M16: =L16 -> 591.82 | N16: =N47-(N10+N15+SUM(N17:N23)) -> 647.01979 | O16: =N16 -> 647.01979 | P16: =O16 -> 647.01979 | Q16: =P16 -> 647.01979 | R16: =Q16 -> 647.01979
A17: Customer Relationships ¹ | B17: 0 | C17: 0 | D17: 0 | E17: 0 | F17: 0 | G17: 0 | H17: 0 | I17: 0 | J17: 0 | K17: 380 | L17: =K17 -> 380 | M17: =L17 -> 380 | N17: =K17-380/10 -> 342 | O17: =N17-380/10 -> 304 | P17: =O17-380/10 -> 266 | Q17: =P17-380/10 -> 228 | R17: =Q17-380/10 -> 190
A18: Assembled Workforce ¹ | B18: 0 | C18: 0 | D18: 0 | E18: 0 | F18: 0 | G18: 0 | H18: 0 | I18: 0 | J18: 0 | K18: 175 | L18: =K18 -> 175 | M18: =L18 -> 175 | N18: =K18-175/10 -> 157.5 | O18: =N18-175/10 -> 140 | P18: =O18-175/10 -> 122.5 | Q18: =P18-175/10 -> 105 | R18: =Q18-175/10 -> 87.5
A19: Backlog / Excess Opportunities ¹ | B19: 0 | C19: 0 | D19: 0 | E19: 0 | F19: 0 | G19: 0 | H19: 0 | I19: 0 | J19: 0 | K19: 145 | L19: =K19 -> 145 | M19: =L19 -> 145 | N19: =K19-145/10 -> 130.5 | O19: =N19-145/10 -> 116 | P19: =O19-145/10 -> 101.5 | Q19: =P19-145/10 -> 87 | R19: =Q19-145/10 -> 72.5
A20: Intangible Assets (Trade Name) ¹ | B20: 0 | C20: 0 | D20: 0 | E20: 0 | F20: 0 | G20: 0 | H20: 0 | I20: 0 | J20: 0 | K20: 100 | L20: =K20 -> 100 | M20: =L20 -> 100 | N20: =K20-100/10 -> 90 | O20: =N20-100/10 -> 80 | P20: =O20-100/10 -> 70 | Q20: =P20-100/10 -> 60 | R20: =Q20-100/10 -> 50
A21: Acquired AR, Inventory & Cash ¹ | B21: 0 | C21: 0 | D21: 0 | E21: 0 | F21: 0 | G21: 0 | H21: 0 | I21: 0 | J21: 0 | K21: 400 | L21: =K21 -> 400 | M21: =L21 -> 400 | N21: =M21 -> 400 | O21: =N21 -> 400 | P21: =O21 -> 400 | Q21: =P21 -> 400 | R21: =Q21 -> 400
A22: ¹ Installations Acquisition — See Assumptions
A23: Other Long-Term Assets | B23: =Assumptions!B137 -> 50 | C23: =B23 -> 50 | D23: =C23 -> 50 | E23: =D23 -> 50 | F23: =E23 -> 50 | G23: =F23 -> 50 | H23: =G23 -> 50 | I23: =H23 -> 50 | J23: =I23 -> 50 | ... N23: =M23 -> 50 | O23: =ROUND('Income Statement'!O3*($B$23/Assumptions!$B$29),0) -> 87 | P23: =ROUND('Income Statement'!P3*($B$23/Assumptions!$B$29),0) -> 104 | Q23: =ROUND('Income Statement'!Q3*($B$23/Assumptions!$B$29),0) -> 124 | R23: =ROUND('Income Statement'!R3*($B$23/Assumptions!$B$29),0) -> 144
A24: Total Non-Current Assets | B24: =SUM(B15:B23) -> 1389 | C24: =SUM(C15:C23) -> 1445.6667 | D24: =SUM(D15:D23) -> 1502.3333 | E24: =SUM(E15:E23) -> 1559 | F24: =SUM(F15:F23) -> 1615.6667 | G24: =SUM(G15:G23) -> 1672.3333 | H24: =SUM(H15:H23) -> 1729 | I24: =SUM(I15:I23) -> 1785.6667 | ... R24: =SUM(R15:R23) -> 4116.0198
A26: TOTAL ASSETS | B26: =B10+B24 -> 1773 | C26: =C10+C24 -> 5370.9889 | D26: =D10+D24 -> 5360.698 | E26: =E10+E24 -> 5363.3916 | F26: =F10+F24 -> 5381.5129 | G26: =G10+G24 -> 6134.8397 | H26: =H10+H24 -> 6136.5552 | I26: =I10+I24 -> 6124.5591 | ... R26: =R10+R24 -> 8067.2749
A28: LIABILITIES
A29: Current Liabilities
A30: Accounts Payable | B30: =Assumptions!B141 -> 201 | C30: =ROUND(-'Income Statement'!C4/30*Assumptions!$B$69,0) -> 245 | D30: =ROUND(-'Income Statement'!D4/30*Assumptions!$B$69,0) -> 279 | E30: =ROUND(-'Income Statement'!E4/30*Assumptions!$B$69,0) -> 314 | F30: =ROUND(-'Income Statement'!F4/30*Assumptions!$B$69,0) -> 351 | G30: =ROUND(-'Income Statement'!G4/30*Assumptions!$B$69,0) -> 374 | H30: =ROUND(-'Income Statement'!H4/30*Assumptions!$B$69,0) -> 389 | I30: =ROUND(-'Income Statement'!I4/30*Assumptions!$B$69,0) -> 385 | J30: =ROUND(-'Income Statement'!J4/30*Assumptions!$B$69,0) -> 347 | ... M30: =ROUND(-'Income Statement'!M4/30*Assumptions!$B$69,0) -> 236 | N30: =ROUND(-'Income Statement'!M4/30*Assumptions!$B$69,0) -> 236 | O30: =ROUND(-'Income Statement'!O4*Assumptions!D69/365,0) -> 354 | P30: =ROUND(-'Income Statement'!P4*Assumptions!E69/365,0) -> 412 | Q30: =ROUND(-'Income Statement'!Q4*Assumptions!F69/365,0) -> 479 | R30: =ROUND(-'Income Statement'!R4*Assumptions!G69/365,0) -> 540
A31: Accrued Expenses | B31: =Assumptions!B142 -> 25 | C31: =B31 -> 25 | D31: =C31 -> 25 | E31: =D31 -> 25 | F31: =E31 -> 25 | G31: =F31 -> 25 | H31: =G31 -> 25 | I31: =H31 -> 25 | J31: =I31 -> 25 | ... N31: =M31 -> 25 | O31: =ROUND(N31*('Income Statement'!O3/'Income Statement'!N3),0) -> 30 | P31: =ROUND(O31*('Income Statement'!P3/'Income Statement'!O3),0) -> 36 | Q31: =ROUND(P31*('Income Statement'!Q3/'Income Statement'!P3),0) -> 43 | R31: =ROUND(Q31*('Income Statement'!R3/'Income Statement'!Q3),0) -> 50
A32: Current Portion of LTD | B32: 0 | C32: 0 | D32: 0 | E32: 0 | F32: 0 | G32: 0 | H32: 0 | I32: 0 | J32: 0 | K32: 0 | L32: 0 | M32: 0 | N32: =MIN('Debt Schedule'!O70,'Debt Schedule'!N68) -> 1034.7636 | O32: =MIN('Debt Schedule'!P70,'Debt Schedule'!O68) -> 844.52971 | P32: =MIN('Debt Schedule'!Q70,'Debt Schedule'!P68) -> 792.36739 | Q32: =MIN('Debt Schedule'!R70,'Debt Schedule'!Q68) -> 853.63793 | R32: =MAX(0,'Debt Schedule'!R68) -> 477.06525
A33: Total Current Liabilities | B33: =SUM(B30:B32) -> 226 | C33: =SUM(C30:C32) -> 270 | D33: =SUM(D30:D32) -> 304 | E33: =SUM(E30:E32) -> 339 | F33: =SUM(F30:F32) -> 376 | G33: =SUM(G30:G32) -> 399 | H33: =SUM(H30:H32) -> 414 | I33: =SUM(I30:I32) -> 410 | ... R33: =SUM(R30:R32) -> 1067.0653
A35: Non-Current Liabilities
A36: Long-Term Debt | B36: =Assumptions!B86 -> 800 | C36: ='Debt Schedule'!B68 -> 2852.4583 | D36: ='Debt Schedule'!C68 -> 2804.6154 | E36: ='Debt Schedule'!D68 -> 2756.4693 | F36: ='Debt Schedule'!E68 -> 2708.018 | G36: ='Debt Schedule'!F68 -> 3398.7346 | H36: ='Debt Schedule'!G68 -> 3339.0807 | I36: ='Debt Schedule'!H68 -> 3279.0541 | J36: ='Debt Schedule'!I68 -> 3218.6522 | ... M36: ='Debt Schedule'!L68 -> 4688.0616 | N36: ='Debt Schedule'!N68-N32 -> 3567.6003 | O36: ='Debt Schedule'!O68-O32 -> 2123.0706 | P36: ='Debt Schedule'!P68-P32 -> 1330.7032 | Q36: ='Debt Schedule'!Q68-Q32 -> 477.06525 | R36: ='Debt Schedule'!R68-R32 -> 0
A37: Total Non-Current Liabilities | B37: =B36 -> 800 | C37: =C36 -> 2852.4583 | D37: =D36 -> 2804.6154 | E37: =E36 -> 2756.4693 | F37: =F36 -> 2708.018 | G37: =G36 -> 3398.7346 | H37: =H36 -> 3339.0807 | I37: =I36 -> 3279.0541 | ... R37: =R36 -> 0
A39: TOTAL LIABILITIES | B39: =B33+B37 -> 1026 | C39: =C33+C37 -> 3122.4583 | D39: =D33+D37 -> 3108.6154 | E39: =E33+E37 -> 3095.4693 | F39: =F33+F37 -> 3084.018 | G39: =G33+G37 -> 3797.7346 | H39: =H33+H37 -> 3753.0807 | I39: =I33+I37 -> 3689.0541 | ... R39: =R33+R37 -> 1067.0653
A41: EQUITY
A42: Beginning Equity | B42: =Assumptions!B150 -> 747 | C42: =B45+Assumptions!B79 -> 2247 | D42: =C45 -> 2248.5305 | E42: =D45 -> 2252.0826 | F42: =E45 -> 2267.9223 | G42: =F45 -> 2297.4949 | H42: =G45 -> 2337.1051 | I42: =H45 -> 2383.4744 | J42: =I45 -> 2435.5051 | K42: =J45 -> 2484.5804 | ... R42: =Q45 -> 5206.6059
A43: Net Income | B43: 0 | C43: ='Income Statement'!B27 -> 1.6818888 | D43: ='Income Statement'!C27 -> 3.9034127 | E43: ='Income Statement'!D27 -> 17.406284 | F43: ='Income Statement'!E27 -> 32.497346 | G43: ='Income Statement'!F27 -> 43.527647 | H43: ='Income Statement'!G27 -> 50.955344 | I43: ='Income Statement'!H27 -> 57.17652 | J43: ='Income Statement'!I27 -> 53.928881 | ... N43: ='Income Statement'!M27 -> -14.602788 | O43: ='Income Statement'!O27 -> 524.42731 | P43: ='Income Statement'!P27 -> 978.49323 | Q43: ='Income Statement'!Q27 -> 1469.5411 | R43: ='Income Statement'!R27 -> 1970.9932
A44: Distributions / Draws | B44: 0 | C44: =IF(C43>0,C43*Assumptions!$B$104,0) -> 0.15136999 | D44: =IF(D43>0,D43*Assumptions!$B$104,0) -> 0.35130715 | E44: =IF(E43>0,E43*Assumptions!$B$104,0) -> 1.5665655 | F44: =IF(F43>0,F43*Assumptions!$B$104,0) -> 2.9247611 | G44: =IF(G43>0,G43*Assumptions!$B$104,0) -> 3.9174882 | H44: =IF(H43>0,H43*Assumptions!$B$104,0) -> 4.585981 | I44: =IF(I43>0,I43*Assumptions!$B$104,0) -> 5.1458868 | J44: =IF(J43>0,J43*Assumptions!$B$104,0) -> 4.8535993 | ... N44: =IF(N43>0,N43*Assumptions!$B$104,0) -> 0 | O44: =MIN(IF(O43>0,O43*Assumptions!$B$104,0),MAX(0,'Cash Flow'!N36+'Cash Flow'!O15+'Cash Flow'!O22+'Cash Flow'!O25+'Cash Flow'!O26+'Cash Flow'!O27+'Cash Flow'!O29+'Cash Flow'!O30-Assumptions!$G$101)) -> 47.198458 | P44: =MIN(IF(P43>0,P43*Assumptions!$B$104,0),MAX(0,'Cash Flow'!O36+'Cash Flow'!P15+'Cash Flow'!P22+'Cash Flow'!P25+'Cash Flow'!P26+'Cash Flow'!P27+'Cash Flow'!P29+'Cash Flow'!P30-Assumptions!$G$101)) -> 88.064391 | Q44: =MIN(IF(Q43>0,Q43*Assumptions!$B$104,0),MAX(0,'Cash Flow'!P36+'Cash Flow'!Q15+'Cash Flow'!Q22+'Cash Flow'!Q25+'Cash Flow'!Q26+'Cash Flow'!Q27+'Cash Flow'!Q29+'Cash Flow'!Q30-Assumptions!$G$101)) -> 132.2587 | R44: =MIN(IF(R43>0,R43*Assumptions!$B$104,0),MAX(0,'Cash Flow'!Q36+'Cash Flow'!R15+'Cash Flow'!R22+'Cash Flow'!R25+'Cash Flow'!R26+'Cash Flow'!R27+'Cash Flow'!R29+'Cash Flow'!R30-Assumptions!$G$101)) -> 177.38939
A45: Ending Equity | B45: =B42+B43-B44 -> 747 | C45: =C42+C43-C44 -> 2248.5305 | D45: =D42+D43-D44 -> 2252.0826 | E45: =E42+E43-E44 -> 2267.9223 | F45: =F42+F43-F44 -> 2297.4949 | G45: =G42+G43-G44 -> 2337.1051 | H45: =H42+H43-H44 -> 2383.4744 | I45: =I42+I43-I44 -> 2435.5051 | ... R45: =R42+R43-R44 -> 7000.2097
A47: TOTAL LIABILITIES & EQUITY | B47: =B39+B45 -> 1773 | C47: =C39+C45 -> 5370.9889 | D47: =D39+D45 -> 5360.698 | E47: =E39+E45 -> 5363.3916 | F47: =F39+F45 -> 5381.5129 | G47: =G39+G45 -> 6134.8397 | H47: =H39+H45 -> 6136.5552 | I47: =I39+I45 -> 6124.5591 | ... R47: =R39+R45 -> 8067.2749
A49: Balance Check (Assets - L&E) | B49: =B26-B47 -> 0 | C49: =C26-C47 -> 0 | D49: =D26-D47 -> 0 | E49: =E26-E47 -> 0 | F49: =F26-F47 -> 0 | G49: =G26-G47 -> 0 | H49: =H26-H47 -> 0 | I49: =I26-I47 -> 0 | ... R49: =R26-R47 -> 0
A51: Apollo Energy Resources — Confidential | Balance Sheet | Mar 2026

Sheet Cash Flow
A1: APOLLO ENERGY RESOURCES — CASH FLOW STATEMENT
B2: 46048 | C2: 46079 | D2: 46107 | E2: 46138 | F2: 46168 | G2: 46199 | H2: 46229 | I2: 46260 | J2: 46291 | K2: 46321 | L2: 46352 | M2: 46382 | N2: FY2026 | O2: FY2027E | P2: FY2028E | Q2: FY2029E | R2: FY2030E
A3: OPERATING ACTIVITIES
A4: Net Income | B4: ='Income Statement'!B27 -> 1.6818888 | C4: ='Income Statement'!C27 -> 3.9034127 | D4: ='Income Statement'!D27 -> 17.406284 | E4: ='Income Statement'!E27 -> 32.497346 | F4: ='Income Statement'!F27 -> 43.527647 | G4: ='Income Statement'!G27 -> 50.955344 | H4: ='Income Statement'!H27 -> 57.17652 | I4: ='Income Statement'!I27 -> 53.928881 | ... R4: ='Income Statement'!R27 -> 1970.9932
A5: Depreciation & Amortization | B5: ='Income Statement'!B14 -> 38.833333 | C5: ='Income Statement'!C14 -> 38.833333 | D5: ='Income Statement'!D14 -> 38.833333 | E5: ='Income Statement'!E14 -> 38.833333 | F5: ='Income Statement'!F14 -> 38.833333 | G5: ='Income Statement'!G14 -> 38.833333 | H5: ='Income Statement'!H14 -> 38.833333 | I5: ='Income Statement'!I14 -> 38.833333 | ... M5: ='Income Statement'!M14 -> 38.833333 | N5: =SUM(B5:M5)+80 -> 546 | O5: ='Income Statement'!O14 -> 714 | P5: ='Income Statement'!P14 -> 914 | Q5: ='Income Statement'!Q14 -> 1144 | R5: ='Income Statement'!R14 -> 1372
A6: Changes in Working Capital:
A7: Change in Accounts Receivable | B7: =-('Balance Sheet'!C6-'Balance Sheet'!B6) -> -380 | C7: =-('Balance Sheet'!D6-'Balance Sheet'!C6) -> -9 | D7: =-('Balance Sheet'!E6-'Balance Sheet'!D6) -> -95 | E7: =-('Balance Sheet'!F6-'Balance Sheet'!E6) -> -100 | F7: =-('Balance Sheet'!G6-'Balance Sheet'!F6) -> -100 | G7: =-('Balance Sheet'!H6-'Balance Sheet'!G6) -> -61 | H7: =-('Balance Sheet'!I6-'Balance Sheet'!H6) -> -44 | I7: =-('Balance Sheet'!J6-'Balance Sheet'!I6) -> 15 | ... M7: =-('Balance Sheet'!N6-'Balance Sheet'!M6) -> 19 | N7: =SUM(B7:M7) -> -360 | O7: =-('Balance Sheet'!O6-'Balance Sheet'!N6) -> -333 | P7: =-('Balance Sheet'!P6-'Balance Sheet'!O6) -> -163 | Q7: =-('Balance Sheet'!Q6-'Balance Sheet'!P6) -> -178 | R7: =-('Balance Sheet'!R6-'Balance Sheet'!Q6) -> -201
A8: Change in Inventory | B8: =-('Balance Sheet'!C7-'Balance Sheet'!B7) -> 4 | C8: =-('Balance Sheet'!D7-'Balance Sheet'!C7) -> 0 | D8: =-('Balance Sheet'!E7-'Balance Sheet'!D7) -> 0 | E8: =-('Balance Sheet'!F7-'Balance Sheet'!E7) -> 0 | F8: =-('Balance Sheet'!G7-'Balance Sheet'!F7) -> 0 | G8: =-('Balance Sheet'!H7-'Balance Sheet'!G7) -> 0 | H8: =-('Balance Sheet'!I7-'Balance Sheet'!H7) -> 0 | I8: =-('Balance Sheet'!J7-'Balance Sheet'!I7) -> 0 | ... M8: =-('Balance Sheet'!N7-'Balance Sheet'!M7) -> 0 | N8: =SUM(B8:M8) -> 4 | O8: =-('Balance Sheet'!O7-'Balance Sheet'!N7) -> -16 | P8: =-('Balance Sheet'!P7-'Balance Sheet'!O7) -> -6 | Q8: =-('Balance Sheet'!Q7-'Balance Sheet'!P7) -> -7 | R8: =-('Balance Sheet'!R7-'Balance Sheet'!Q7) -> -8
A9: Change in Prepaid Expenses | B9: =-('Balance Sheet'!C8-'Balance Sheet'!B8) -> 26 | C9: =-('Balance Sheet'!D8-'Balance Sheet'!C8) -> 0 | D9: =-('Balance Sheet'!E8-'Balance Sheet'!D8) -> 0 | E9: =-('Balance Sheet'!F8-'Balance Sheet'!E8) -> 0 | F9: =-('Balance Sheet'!G8-'Balance Sheet'!F8) -> 0 | G9: =-('Balance Sheet'!H8-'Balance Sheet'!G8) -> 0 | H9: =-('Balance Sheet'!I8-'Balance Sheet'!H8) -> 0 | I9: =-('Balance Sheet'!J8-'Balance Sheet'!I8) -> 0 | ... M9: =-('Balance Sheet'!N8-'Balance Sheet'!M8) -> 0 | N9: =SUM(B9:M9) -> 26 | O9: =-('Balance Sheet'!O8-'Balance Sheet'!N8) -> -51 | P9: =-('Balance Sheet'!P8-'Balance Sheet'!O8) -> -8 | Q9: =-('Balance Sheet'!Q8-'Balance Sheet'!P8) -> -11 | R9: =-('Balance Sheet'!R8-'Balance Sheet'!Q8) -> -10
A10: Change in Accounts Payable | B10: ='Balance Sheet'!C30-'Balance Sheet'!B30 -> 44 | C10: ='Balance Sheet'!D30-'Balance Sheet'!C30 -> 34 | D10: ='Balance Sheet'!E30-'Balance Sheet'!D30 -> 35 | E10: ='Balance Sheet'!F30-'Balance Sheet'!E30 -> 37 | F10: ='Balance Sheet'!G30-'Balance Sheet'!F30 -> 23 | G10: ='Balance Sheet'!H30-'Balance Sheet'!G30 -> 15 | H10: ='Balance Sheet'!I30-'Balance Sheet'!H30 -> -4 | I10: ='Balance Sheet'!J30-'Balance Sheet'!I30 -> -38 | ... M10: ='Balance Sheet'!N30-'Balance Sheet'!M30 -> 0 | N10: =SUM(B10:M10) -> 35 | O10: ='Balance Sheet'!O30-'Balance Sheet'!N30 -> 118 | P10: ='Balance Sheet'!P30-'Balance Sheet'!O30 -> 58 | Q10: ='Balance Sheet'!Q30-'Balance Sheet'!P30 -> 67 | R10: ='Balance Sheet'!R30-'Balance Sheet'!Q30 -> 61
A11: Change in Accrued Expenses | B11: ='Balance Sheet'!C31-'Balance Sheet'!B31 -> 0 | C11: ='Balance Sheet'!D31-'Balance Sheet'!C31 -> 0 | D11: ='Balance Sheet'!E31-'Balance Sheet'!D31 -> 0 | E11: ='Balance Sheet'!F31-'Balance Sheet'!E31 -> 0 | F11: ='Balance Sheet'!G31-'Balance Sheet'!F31 -> 0 | G11: ='Balance Sheet'!H31-'Balance Sheet'!G31 -> 0 | H11: ='Balance Sheet'!I31-'Balance Sheet'!H31 -> 0 | I11: ='Balance Sheet'!J31-'Balance Sheet'!I31 -> 0 | ... M11: ='Balance Sheet'!N31-'Balance Sheet'!M31 -> 0 | N11: =SUM(B11:M11) -> 0 | O11: ='Balance Sheet'!O31-'Balance Sheet'!N31 -> 5 | P11: ='Balance Sheet'!P31-'Balance Sheet'!O31 -> 6 | Q11: ='Balance Sheet'!Q31-'Balance Sheet'!P31 -> 7 | R11: ='Balance Sheet'!R31-'Balance Sheet'!Q31 -> 7
A12: Change in Other Current Assets | B12: =-('Balance Sheet'!C9-'Balance Sheet'!B9) -> 0 | C12: =-('Balance Sheet'!D9-'Balance Sheet'!C9) -> 0 | D12: =-('Balance Sheet'!E9-'Balance Sheet'!D9) -> 0 | E12: =-('Balance Sheet'!F9-'Balance Sheet'!E9) -> 0 | F12: =-('Balance Sheet'!G9-'Balance Sheet'!F9) -> 0 | G12: =-('Balance Sheet'!H9-'Balance Sheet'!G9) -> 0 | H12: =-('Balance Sheet'!I9-'Balance Sheet'!H9) -> 0 | I12: =-('Balance Sheet'!J9-'Balance Sheet'!I9) -> 0 | ... M12: =-('Balance Sheet'!N9-'Balance Sheet'!M9) -> -18 | N12: =SUM(B12:M12) -> -18 | O12: =-('Balance Sheet'!O9-'Balance Sheet'!N9) -> -12 | P12: =-('Balance Sheet'!P9-'Balance Sheet'!O9) -> -15 | Q12: =-('Balance Sheet'!Q9-'Balance Sheet'!P9) -> -16 | R12: =-('Balance Sheet'!R9-'Balance Sheet'!Q9) -> -16
A13: Change in Other Long-Term Assets | B13: =-('Balance Sheet'!C23-'Balance Sheet'!B23) -> 0 | C13: =-('Balance Sheet'!D23-'Balance Sheet'!C23) -> 0 | D13: =-('Balance Sheet'!E23-'Balance Sheet'!D23) -> 0 | E13: =-('Balance Sheet'!F23-'Balance Sheet'!E23) -> 0 | F13: =-('Balance Sheet'!G23-'Balance Sheet'!F23) -> 0 | G13: =-('Balance Sheet'!H23-'Balance Sheet'!G23) -> 0 | H13: =-('Balance Sheet'!I23-'Balance Sheet'!H23) -> 0 | I13: =-('Balance Sheet'!J23-'Balance Sheet'!I23) -> 0 | ... M13: =-('Balance Sheet'!N23-'Balance Sheet'!M23) -> 0 | N13: =SUM(B13:M13) -> 0 | O13: =-('Balance Sheet'!O23-'Balance Sheet'!N23) -> -37 | P13: =-('Balance Sheet'!P23-'Balance Sheet'!O23) -> -17 | Q13: =-('Balance Sheet'!Q23-'Balance Sheet'!P23) -> -20 | R13: =-('Balance Sheet'!R23-'Balance Sheet'!Q23) -> -20
A14: Total Change in Working Capital | B14: =SUM(B7:B13) -> -306 | C14: =SUM(C7:C13) -> 25 | D14: =SUM(D7:D13) -> -60 | E14: =SUM(E7:E13) -> -63 | F14: =SUM(F7:F13) -> -77 | G14: =SUM(G7:G13) -> -46 | H14: =SUM(H7:H13) -> -48 | I14: =SUM(I7:I13) -> -23 | ... R14: =SUM(R7:R13) -> -187
A15: Cash from Operations (CFO) | B15: =B4+B5+B14 -> -265.48478 | C15: =C4+C5+C14 -> 67.736746 | D15: =D4+D5+D14 -> -3.7603831 | E15: =E4+E5+E14 -> 8.3306791 | F15: =F4+F5+F14 -> 5.3609799 | G15: =G4+G5+G14 -> 43.788677 | H15: =H4+H5+H14 -> 48.009853 | I15: =I4+I5+I14 -> 69.762215 | ... R15: =R4+R5+R14 -> 3155.9932
A17: INVESTING ACTIVITIES
A18: Growth CapEx | B18: =-Assumptions!$C$63/12 -> -85.083333 | C18: =-Assumptions!$C$63/12 -> -85.083333 | D18: =-Assumptions!$C$63/12 -> -85.083333 | E18: =-Assumptions!$C$63/12 -> -85.083333 | F18: =-Assumptions!$C$63/12 -> -85.083333 | G18: =-Assumptions!$C$63/12 -> -85.083333 | H18: =-Assumptions!$C$63/12 -> -85.083333 | I18: =-Assumptions!$C$63/12 -> -85.083333 | ... M18: =-Assumptions!$C$63/12 -> -85.083333 | N18: =SUM(B18:M18) -> -1021 | O18: =-Assumptions!D63 -> -686 | P18: =-Assumptions!E63 -> -821 | Q18: =-Assumptions!F63 -> -934 | R18: =-Assumptions!G63 -> -889
A19: Maintenance CapEx | B19: =-Assumptions!$C$64/12 -> -10.416667 | C19: =-Assumptions!$C$64/12 -> -10.416667 | D19: =-Assumptions!$C$64/12 -> -10.416667 | E19: =-Assumptions!$C$64/12 -> -10.416667 | F19: =-Assumptions!$C$64/12 -> -10.416667 | G19: =-Assumptions!$C$64/12 -> -10.416667 | H19: =-Assumptions!$C$64/12 -> -10.416667 | I19: =-Assumptions!$C$64/12 -> -10.416667 | ... M19: =-Assumptions!$C$64/12 -> -10.416667 | N19: =SUM(B19:M19) -> -125 | O19: =-Assumptions!D64 -> -151 | P19: =-Assumptions!E64 -> -182 | Q19: =-Assumptions!F64 -> -217 | R19: =-Assumptions!G64 -> -250
A20: Total Capital Expenditures | B20: =B18+B19 -> -95.5 | C20: =C18+C19 -> -95.5 | D20: =D18+D19 -> -95.5 | E20: =E18+E19 -> -95.5 | F20: =F18+F19 -> -95.5 | G20: =G18+G19 -> -95.5 | H20: =H18+H19 -> -95.5 | I20: =I18+I19 -> -95.5 | ... M20: =M18+M19 -> -95.5 | N20: =SUM(B20:M20) -> -1146 | O20: =O18+O19 -> -837 | P20: =P18+P19 -> -1003 | Q20: =Q18+Q19 -> -1151 | R20: =R18+R19 -> -1139
A21: Acquisition — Installations Division | B21: 0 | C21: 0 | D21: 0 | E21: 0 | F21: 0 | G21: 0 | H21: 0 | I21: 0 | J21: 0 | K21: -600 | L21: 0 | M21: 0 | N21: =SUM(B21:M21) -> -600 | O21: 0 | P21: 0 | Q21: 0 | R21: 0
A22: Cash from Investing (CFI) | B22: =B20+B21 -> -95.5 | C22: =C20+C21 -> -95.5 | D22: =D20+D21 -> -95.5 | E22: =E20+E21 -> -95.5 | F22: =F20+F21 -> -95.5 | G22: =G20+G21 -> -95.5 | H22: =H20+H21 -> -95.5 | I22: =I20+I21 -> -95.5 | ... R22: =R20+R21 -> -1139
A24: FINANCING ACTIVITIES
A25: Equity Contribution | B25: =Assumptions!B79 -> 1500 | C25: 0 | D25: 0 | E25: 0 | F25: 0 | G25: 0 | H25: 0 | I25: 0 | J25: 0 | K25: 0 | L25: 0 | M25: 0 | N25: =SUM(B25:M25) -> 1500 | O25: 0 | P25: 0 | Q25: 0 | R25: 0
A26: Proceeds from Capital Injection (Debt) | B26: =Assumptions!B78+Assumptions!B80 -> 1500 | C26: 0 | D26: 0 | E26: 0 | F26: 0 | G26: 0 | H26: 0 | I26: 0 | J26: 0 | K26: 0 | L26: 0 | M26: 0 | N26: =SUM(B26:M26) -> 1500 | O26: 0 | P26: 0 | Q26: 0 | R26: 0
A27: Proceeds from New Debt | B27: 0 | C27: 0 | D27: 0 | E27: 0 | F27: =Assumptions!$B$89+Assumptions!$B$90 -> 750 | G27: 0 | H27: 0 | I27: 0 | J27: 0 | K27: 0 | L27: 0 | M27: 0 | N27: =SUM(B27:M27) -> 750 | O27: 0 | P27: 0 | Q27: 0 | R27: 0
A28: Proceeds from Acquisition Note | B28: 0 | C28: 0 | D28: 0 | E28: 0 | F28: 0 | G28: 0 | H28: 0 | I28: 0 | J28: 0 | K28: 300 | L28: 0 | M28: 0 | N28: =SUM(B28:M28) -> 300 | O28: 0 | P28: 0 | Q28: 0 | R28: 0
A29: Revolver Net Draws / (Repayments) | B29: ='Debt Schedule'!B45 -> 600 | C29: ='Debt Schedule'!C49-'Debt Schedule'!B49 -> 0 | D29: ='Debt Schedule'!D49-'Debt Schedule'!C49 -> 0 | E29: ='Debt Schedule'!E49-'Debt Schedule'!D49 -> 0 | F29: ='Debt Schedule'!F49-'Debt Schedule'!E49 -> 0 | G29: ='Debt Schedule'!G49-'Debt Schedule'!F49 -> 0 | H29: ='Debt Schedule'!H49-'Debt Schedule'!G49 -> 0 | I29: ='Debt Schedule'!I49-'Debt Schedule'!H49 -> 0 | J29: ='Debt Schedule'!J49-'Debt Schedule'!I49 -> 0 | ... M29: ='Debt Schedule'!M49-'Debt Schedule'!L49 -> 0 | N29: =SUM(B29:M29) -> 600 | O29: ='Debt Schedule'!O49-'Debt Schedule'!N49 -> -600 | P29: ='Debt Schedule'!P49-'Debt Schedule'!O49 -> 0 | Q29: ='Debt Schedule'!Q49-'Debt Schedule'!P49 -> 0 | R29: ='Debt Schedule'!R49-'Debt Schedule'!Q49 -> 0
A30: Debt Principal Repayment | B30: =-'Debt Schedule'!B70 -> -47.541667 | C30: =-'Debt Schedule'!C70 -> -47.842934 | D30: =-'Debt Schedule'!D70 -> -48.146135 | E30: =-'Debt Schedule'!E70 -> -48.451281 | F30: =-'Debt Schedule'!F70 -> -59.283386 | G30: =-'Debt Schedule'!G70 -> -59.653858 | H30: =-'Debt Schedule'!H70 -> -60.026673 | I30: =-'Debt Schedule'!I70 -> -60.401844 | ... M30: =-'Debt Schedule'!M70 -> -85.697764 | N30: =SUM(B30:M30) -> -747.63614 | O30: =-'Debt Schedule'!O70 -> -1034.7636 | P30: =-'Debt Schedule'!P70 -> -844.52971 | Q30: =-'Debt Schedule'!Q70 -> -792.36739 | R30: =-'Debt Schedule'!R70 -> -853.63793
A31: Owner Distributions | B31: =-'Balance Sheet'!C44 -> -0.15136999 | C31: =-'Balance Sheet'!D44 -> -0.35130715 | D31: =-'Balance Sheet'!E44 -> -1.5665655 | E31: =-'Balance Sheet'!F44 -> -2.9247611 | F31: =-'Balance Sheet'!G44 -> -3.9174882 | G31: =-'Balance Sheet'!H44 -> -4.585981 | H31: =-'Balance Sheet'!I44 -> -5.1458868 | I31: =-'Balance Sheet'!J44 -> -4.8535993 | ... M31: =-'Balance Sheet'!N44 -> 0 | N31: =SUM(B31:M31) -> -27.796501 | O31: =-'Balance Sheet'!O44 -> -47.198458 | P31: =-'Balance Sheet'!P44 -> -88.064391 | Q31: =-'Balance Sheet'!Q44 -> -132.2587 | R31: =-'Balance Sheet'!R44 -> -177.38939
A32: Cash from Financing (CFF) | B32: =SUM(B25:B31) -> 3552.307 | C32: =SUM(C25:C31) -> -48.194241 | D32: =SUM(D25:D31) -> -49.7127 | E32: =SUM(E25:E31) -> -51.376042 | F32: =SUM(F25:F31) -> 686.79913 | G32: =SUM(G25:G31) -> -64.239839 | H32: =SUM(H25:H31) -> -65.17256 | I32: =SUM(I25:I31) -> -65.255444 | ... R32: =SUM(R25:R31) -> -1031.0273
A34: NET CHANGE IN CASH | B34: =B15+B22+B32 -> 3191.3222 | C34: =C15+C22+C32 -> -75.957495 | D34: =D15+D22+D32 -> -148.97308 | E34: =E15+E22+E32 -> -138.54536 | F34: =F15+F22+F32 -> 596.66011 | G34: =G15+G22+G32 -> -115.95116 | H34: =H15+H22+H32 -> -112.66271 | I34: =I15+I22+I32 -> -90.993229 | ... R34: =R15+R22+R32 -> 985.96586
A35: Beginning Cash Balance | B35: ='Balance Sheet'!B5 -> 34 | C35: =B36 -> 3225.3222 | D35: =C36 -> 3149.3647 | E35: =D36 -> 3000.3916 | F35: =E36 -> 2861.8462 | G35: =F36 -> 3458.5063 | H35: =G36 -> 3342.5552 | I35: =H36 -> 3229.8925 | J35: =I36 -> 3138.8993 | ... M35: =L36 -> 2753.9968 | N35: =B35 -> 34 | O35: =N36 -> 2631.0098 | P35: =O36 -> 1024.4751 | Q35: =P36 -> 836.37422 | R35: =Q36 -> 1216.2893
A36: Ending Cash Balance | B36: =B35+B34 -> 3225.3222 | C36: =C35+C34 -> 3149.3647 | D36: =D35+D34 -> 3000.3916 | E36: =E35+E34 -> 2861.8462 | F36: =F35+F34 -> 3458.5063 | G36: =G35+G34 -> 3342.5552 | H36: =H35+H34 -> 3229.8925 | I36: =I35+I34 -> 3138.8993 | ... R36: =R35+R34 -> 2202.2551
A38: Cash Check (vs. Balance Sheet) | B38: =B36-'Balance Sheet'!C5 -> 0 | C38: =C36-'Balance Sheet'!D5 -> 0 | D38: =D36-'Balance Sheet'!E5 -> 0 | E38: =E36-'Balance Sheet'!F5 -> 0 | F38: =F36-'Balance Sheet'!G5 -> 0 | G38: =G36-'Balance Sheet'!H5 -> 0 | H38: =H36-'Balance Sheet'!I5 -> 0 | I38: =I36-'Balance Sheet'!J5 -> 0 | ... M38: =M36-'Balance Sheet'!N5 -> -32.980209 | N38: =N36-'Balance Sheet'!N5 -> 0 | O38: =O36-'Balance Sheet'!O5 -> 0 | P38: =P36-'Balance Sheet'!P5 -> 0 | Q38: =Q36-'Balance Sheet'!Q5 -> 0 | R38: =R36-'Balance Sheet'!R5 -> 0
A39: Apollo Energy Resources — Confidential | Cash Flow | Mar 2026

Sheet Debt Schedule
A1: APOLLO ENERGY RESOURCES — DEBT SCHEDULE & COVENANT TRACKER ($000s)
B2: 46048 | C2: 46079 | D2: 46107 | E2: 46138 | F2: 46168 | G2: 46199 | H2: 46229 | I2: 46260 | J2: 46291 | K2: 46321 | L2: 46352 | M2: 46382 | N2: FY2026 | O2: FY2027E | P2: FY2028E | Q2: FY2029E | R2: FY2030E
A3: EXISTING DEBT
A4: Truck Leases
A5: Beginning Balance | B5: =Assumptions!B84 -> 440 | C5: =B9 -> 424.78333 | D5: =C9 -> 409.48424 | E5: =D9 -> 394.10228 | F5: =E9 -> 378.637 | G5: =F9 -> 363.08795 | H5: =G9 -> 347.45468 | I5: =H9 -> 331.73673 | J5: =I9 -> 315.93363 | ... M5: =L9 -> 268.0089 | N5: =M5 -> 268.0089 | O5: =N9 -> 251.86061 | P5: =O9 -> 57.031553 | Q5: =P9 -> 0 | R5: =Q9 -> 0
A6: Monthly Payment | B6: =IF(B5>0,Assumptions!F84,0) -> 17.6 | C6: =IF(C5>0,Assumptions!F84,0) -> 17.6 | D6: =IF(D5>0,Assumptions!F84,0) -> 17.6 | E6: =IF(E5>0,Assumptions!F84,0) -> 17.6 | F6: =IF(F5>0,Assumptions!F84,0) -> 17.6 | G6: =IF(G5>0,Assumptions!F84,0) -> 17.6 | H6: =IF(H5>0,Assumptions!F84,0) -> 17.6 | I6: =IF(I5>0,Assumptions!F84,0) -> 17.6 | J6: =IF(J5>0,Assumptions!F84,0) -> 17.6 | K6: =IF(K5>0,Assumptions!F84,0) -> 17.6 | L6: =IF(L5>0,Assumptions!F84,0) -> 17.6 | M6: =IF(M5>0,Assumptions!F84,0) -> 17.6 | N6: =SUM(B6:M6) -> 211.2 | O6: =IF(O5>0,MIN(Assumptions!$F$84*12,O5+O5*Assumptions!$D$84),0) -> 211.2 | P6: =IF(P5>0,MIN(Assumptions!$F$84*12,P5+P5*Assumptions!$D$84),0) -> 60.738603 | Q6: =IF(Q5>0,MIN(Assumptions!$F$84*12,Q5+Q5*Assumptions!$D$84),0) -> 0 | R6: =IF(R5>0,MIN(Assumptions!$F$84*12,R5+R5*Assumptions!$D$84),0) -> 0
A7: Interest Expense | B7: =B5*Assumptions!D84/12 -> 2.3833333 | C7: =C5*Assumptions!D84/12 -> 2.3009097 | D7: =D5*Assumptions!D84/12 -> 2.2180396 | E7: =E5*Assumptions!D84/12 -> 2.1347207 | F7: =F5*Assumptions!D84/12 -> 2.0509504 | G7: =G5*Assumptions!D84/12 -> 1.9667264 | H7: =H5*Assumptions!D84/12 -> 1.8820462 | I7: =I5*Assumptions!D84/12 -> 1.7969073 | J7: =J5*Assumptions!D84/12 -> 1.7113072 | K7: =K5*Assumptions!D84/12 -> 1.6252434 | L7: =L5*Assumptions!D84/12 -> 1.5387135 | M7: =M5*Assumptions!D84/12 -> 1.4517149 | N7: =SUM(B7:M7) -> 23.060613 | O7: =O5*Assumptions!$D$84 -> 16.37094 | P7: =P5*Assumptions!$D$84 -> 3.7070509 | Q7: =Q5*Assumptions!$D$84 -> 0 | R7: =R5*Assumptions!$D$84 -> 0
A8: Principal Repayment | B8: =B6-B7 -> 15.216667 | C8: =C6-C7 -> 15.29909 | D8: =D6-D7 -> 15.38196 | E8: =E6-E7 -> 15.465279 | F8: =F6-F7 -> 15.54905 | G8: =G6-G7 -> 15.633274 | H8: =H6-H7 -> 15.717954 | I8: =I6-I7 -> 15.803093 | ... M8: =M6-M7 -> 16.148285 | N8: =SUM(B8:M8) -> 188.13939 | O8: =O6-O7 -> 194.82906 | P8: =P6-P7 -> 57.031553 | Q8: =Q6-Q7 -> 0 | R8: =R6-R7 -> 0
A9: Ending Balance | B9: =MAX(B5-B8,0) -> 424.78333 | C9: =MAX(C5-C8,0) -> 409.48424 | D9: =MAX(D5-D8,0) -> 394.10228 | E9: =MAX(E5-E8,0) -> 378.637 | F9: =MAX(F5-F8,0) -> 363.08795 | G9: =MAX(G5-G8,0) -> 347.45468 | H9: =MAX(H5-H8,0) -> 331.73673 | I9: =MAX(I5-I8,0) -> 315.93363 | ... M9: =MAX(M5-M8,0) -> 251.86061 | N9: =M9 -> 251.86061 | O9: =MAX(O5-O8,0) -> 57.031553 | P9: =MAX(P5-P8,0) -> 0 | Q9: =MAX(Q5-Q8,0) -> 0 | R9: =MAX(R5-R8,0) -> 0
A10: Other Existing Debt
A11: Beginning Balance | B11: =Assumptions!B85 -> 360 | C11: =B15 -> 347.85 | D11: =C15 -> 335.62406 | E11: =D15 -> 323.32171 | F11: =E15 -> 310.94247 | G11: =F15 -> 298.48586 | H11: =G15 -> 285.9514 | I11: =H15 -> 273.3386 | J11: =I15 -> 260.64696 | ... M11: =L15 -> 222.09414 | N11: =SUM(B11:M11) -> 3501.1565 | O11: =N15 -> 209.08223 | P11: =O15 -> 51.963395 | Q11: =P15 -> 0 | R11: =Q15 -> 0
A12: Monthly Payment | B12: =IF(B11>0,Assumptions!F85,0) -> 14.4 | C12: =IF(C11>0,Assumptions!F85,0) -> 14.4 | D12: =IF(D11>0,Assumptions!F85,0) -> 14.4 | E12: =IF(E11>0,Assumptions!F85,0) -> 14.4 | F12: =IF(F11>0,Assumptions!F85,0) -> 14.4 | G12: =IF(G11>0,Assumptions!F85,0) -> 14.4 | H12: =IF(H11>0,Assumptions!F85,0) -> 14.4 | I12: =IF(I11>0,Assumptions!F85,0) -> 14.4 | J12: =IF(J11>0,Assumptions!F85,0) -> 14.4 | K12: =IF(K11>0,Assumptions!F85,0) -> 14.4 | L12: =IF(L11>0,Assumptions!F85,0) -> 14.4 | M12: =IF(M11>0,Assumptions!F85,0) -> 14.4 | N12: =SUM(B12:M12) -> 172.8 | O12: =IF(O11>0,MIN(Assumptions!$F$85*12,O11+O11*Assumptions!$D$85),0) -> 172.8 | P12: =IF(P11>0,MIN(Assumptions!$F$85*12,P11+P11*Assumptions!$D$85),0) -> 55.86065 | Q12: =IF(Q11>0,MIN(Assumptions!$F$85*12,Q11+Q11*Assumptions!$D$85),0) -> 0 | R12: =IF(R11>0,MIN(Assumptions!$F$85*12,R11+R11*Assumptions!$D$85),0) -> 0
A13: Interest Expense | B13: =B11*Assumptions!D85/12 -> 2.25 | C13: =C11*Assumptions!D85/12 -> 2.1740625 | D13: =D11*Assumptions!D85/12 -> 2.0976504 | E13: =E11*Assumptions!D85/12 -> 2.0207607 | F13: =F11*Assumptions!D85/12 -> 1.9433905 | G13: =G11*Assumptions!D85/12 -> 1.8655367 | H13: =H11*Assumptions!D85/12 -> 1.7871963 | I13: =I11*Assumptions!D85/12 -> 1.7083662 | J13: =J11*Assumptions!D85/12 -> 1.6290435 | K13: =K11*Assumptions!D85/12 -> 1.549225 | L13: =L11*Assumptions!D85/12 -> 1.4689077 | M13: =M11*Assumptions!D85/12 -> 1.3880884 | N13: =SUM(B13:M13) -> 21.882228 | O13: =O11*Assumptions!$D$85 -> 15.681167 | P13: =P11*Assumptions!$D$85 -> 3.8972546 | Q13: =Q11*Assumptions!$D$85 -> 0 | R13: =R11*Assumptions!$D$85 -> 0
A14: Principal Repayment | B14: =B12-B13 -> 12.15 | C14: =C12-C13 -> 12.225938 | D14: =D12-D13 -> 12.30235 | E14: =E12-E13 -> 12.379239 | F14: =F12-F13 -> 12.45661 | G14: =G12-G13 -> 12.534463 | H14: =H12-H13 -> 12.612804 | I14: =I12-I13 -> 12.691634 | ... M14: =M12-M13 -> 13.011912 | N14: =SUM(B14:M14) -> 150.91777 | O14: =O12-O13 -> 157.11883 | P14: =P12-P13 -> 51.963395 | Q14: =Q12-Q13 -> 0 | R14: =R12-R13 -> 0
A15: Ending Balance | B15: =MAX(B11-B14,0) -> 347.85 | C15: =MAX(C11-C14,0) -> 335.62406 | D15: =MAX(D11-D14,0) -> 323.32171 | E15: =MAX(E11-E14,0) -> 310.94247 | F15: =MAX(F11-F14,0) -> 298.48586 | G15: =MAX(G11-G14,0) -> 285.9514 | H15: =MAX(H11-H14,0) -> 273.3386 | I15: =MAX(I11-I14,0) -> 260.64696 | ... M15: =MAX(M11-M14,0) -> 209.08223 | N15: =M15 -> 209.08223 | O15: =MAX(O11-O14,0) -> 51.963395 | P15: =MAX(P11-P14,0) -> 0 | Q15: =MAX(Q11-Q14,0) -> 0 | R15: =MAX(R11-R14,0) -> 0
A17: CAPITAL INJECTION DEBT (JAN 2026)
A18: Term Debt ($1,500K)
A19: Beginning Balance | B19: =Assumptions!B78 -> 1500 | C19: =B23 -> 1479.825 | D19: =C23 -> 1459.5071 | E19: =D23 -> 1439.0453 | F19: =E23 -> 1418.4385 | G19: =F23 -> 1397.6858 | H19: =G23 -> 1376.7861 | I19: =H23 -> 1355.7383 | J19: =I23 -> 1334.5414 | ... R19: =Q23 -> 388.64745
A20: Monthly Payment | B20: =ROUND(-PMT(Assumptions!$D$78/12,Assumptions!$E$78*12,Assumptions!$B$78),1) -> 30.8 | C20: =B20 -> 30.8 | D20: =C20 -> 30.8 | E20: =D20 -> 30.8 | F20: =E20 -> 30.8 | G20: =F20 -> 30.8 | H20: =G20 -> 30.8 | I20: =H20 -> 30.8 | J20: =I20 -> 30.8 | ... M20: =L20 -> 30.8 | N20: =SUM(B20:M20) -> 369.6 | O20: =IF(O19>0,B20*12,0) -> 369.6 | P20: =IF(P19>0,B20*12,0) -> 369.6 | Q20: =IF(Q19>0,B20*12,0) -> 369.6 | R20: =IF(R19>0,B20*12,0) -> 369.6
A21: Interest Expense | B21: =B19*Assumptions!$D$78/12 -> 10.625 | C21: =C19*Assumptions!$D$78/12 -> 10.482094 | D21: =D19*Assumptions!$D$78/12 -> 10.338175 | E21: =E19*Assumptions!$D$78/12 -> 10.193237 | F21: =F19*Assumptions!$D$78/12 -> 10.047273 | G21: =G19*Assumptions!$D$78/12 -> 9.9002743 | H21: =H19*Assumptions!$D$78/12 -> 9.7522345 | I21: =I19*Assumptions!$D$78/12 -> 9.6031462 | ... M21: =M19*Assumptions!$D$78/12 -> 8.9961574 | N21: =SUM(B21:M21) -> 117.8419 | O21: =O19*Assumptions!$D$78 -> 106.10056 | P21: =P19*Assumptions!$D$78 -> 83.703109 | Q21: =Q19*Assumptions!$D$78 -> 59.401874 | R21: =R19*Assumptions!$D$78 -> 33.035033
A22: Principal Repayment | B22: =B20-B21 -> 20.175 | C22: =C20-C21 -> 20.317906 | D22: =D20-D21 -> 20.461825 | E22: =E20-E21 -> 20.606763 | F22: =F20-F21 -> 20.752727 | G22: =G20-G21 -> 20.899726 | H22: =H20-H21 -> 21.047765 | I22: =I20-I21 -> 21.196854 | ... M22: =M20-M21 -> 21.803843 | N22: =SUM(B22:M22) -> 251.7581 | O22: =O20-O21 -> 263.49944 | P22: =P20-P21 -> 285.89689 | Q22: =Q20-Q21 -> 310.19813 | R22: =R20-R21 -> 336.56497
A23: Ending Balance | B23: =MAX(B19-B22,0) -> 1479.825 | C23: =MAX(C19-C22,0) -> 1459.5071 | D23: =MAX(D19-D22,0) -> 1439.0453 | E23: =MAX(E19-E22,0) -> 1418.4385 | F23: =MAX(F19-F22,0) -> 1397.6858 | G23: =MAX(G19-G22,0) -> 1376.7861 | H23: =MAX(H19-H22,0) -> 1355.7383 | I23: =MAX(I19-I22,0) -> 1334.5414 | ... M23: =MAX(M19-M22,0) -> 1248.2419 | N23: =M23 -> 1248.2419 | O23: =MAX(O19-O22,0) -> 984.74246 | P23: =MAX(P19-P22,0) -> 698.84557 | Q23: =MAX(Q19-Q22,0) -> 388.64745 | R23: =MAX(R19-R22,0) -> 52.08248
A24: Line of Credit / Mezz ($325K)
A25: Beginning Balance | B25: =Assumptions!B80 -> 0 | C25: =B29 -> 0 | D25: =C29 -> 0 | E25: =D29 -> 0 | F25: =E29 -> 0 | G25: =F29 -> 0 | H25: =G29 -> 0 | I25: =H29 -> 0 | J25: =I29 -> 0 | ... R25: =Q29 -> 0
A26: Monthly Payment (Int Only) | B26: =ROUND(B25*Assumptions!$D$80/12,1) -> 0 | C26: =ROUND(C25*Assumptions!$D$80/12,1) -> 0 | D26: =ROUND(D25*Assumptions!$D$80/12,1) -> 0 | E26: =ROUND(E25*Assumptions!$D$80/12,1) -> 0 | F26: =ROUND(F25*Assumptions!$D$80/12,1) -> 0 | G26: =ROUND(G25*Assumptions!$D$80/12,1) -> 0 | H26: =ROUND(H25*Assumptions!$D$80/12,1) -> 0 | I26: =ROUND(I25*Assumptions!$D$80/12,1) -> 0 | ... M26: =ROUND(M25*Assumptions!$D$80/12,1) -> 0 | N26: =SUM(B26:M26) -> 0 | O26: =O25*Assumptions!$D$80 -> 0 | P26: =P25*Assumptions!$D$80 -> 0 | Q26: =IF(Q25>0,Q25*Assumptions!$D$80,0) -> 0 | R26: 0
A27: Interest Expense | B27: =B26 -> 0 | C27: =C26 -> 0 | D27: =D26 -> 0 | E27: =E26 -> 0 | F27: =F26 -> 0 | G27: =G26 -> 0 | H27: =H26 -> 0 | I27: =I26 -> 0 | ... M27: =M26 -> 0 | N27: =SUM(B27:M27) -> 0 | O27: =O26 -> 0 | P27: =P26 -> 0 | Q27: =IF(Q25>0,Q25*Assumptions!$D$80,0) -> 0 | R27: 0
A28: Principal Repayment | B28: 0 | C28: 0 | D28: 0 | E28: 0 | F28: 0 | G28: 0 | H28: 0 | I28: 0 | J28: 0 | K28: 0 | L28: 0 | M28: 0 | N28: =SUM(B28:M28) -> 0 | O28: 0 | P28: 0 | Q28: =Q25 -> 0 | R28: 0
A29: Ending Balance | B29: =B25-B28 -> 0 | C29: =C25-C28 -> 0 | D29: =D25-D28 -> 0 | E29: =E25-E28 -> 0 | F29: =F25-F28 -> 0 | G29: =G25-G28 -> 0 | H29: =H25-H28 -> 0 | I29: =I25-I28 -> 0 | ... M29: =M25-M28 -> 0 | N29: =M29 -> 0 | O29: =O25 -> 0 | P29: =P25 -> 0 | Q29: =MAX(Q25-Q28,0) -> 0 | R29: 0
A31: NEW DEBT (FROM MAY 2026)
A32: ISO Tank Lease-to-Own
A33: Beginning Balance | B33: 0 | C33: 0 | D33: 0 | E33: 0 | F33: =Assumptions!B89 -> 700 | G33: =F37 -> 690.18333 | H33: =G37 -> 680.3094 | I33: =H37 -> 670.37787 | J33: =I37 -> 660.38841 | K33: =J37 -> 650.34068 | L33: =K37 -> 640.23433 | M33: =L37 -> 630.06903 | N33: =SUM(B33:M33) -> 5321.9031 | O33: =N37 -> 619.84443 | P33: =O37 -> 496.43354 | Q33: =P37 -> 364.38389 | R33: =Q37 -> 223.09077
A34: Monthly Payment | B34: =IF(B33>0,Assumptions!F89,0) -> 0 | C34: =IF(C33>0,Assumptions!F89,0) -> 0 | D34: =IF(D33>0,Assumptions!F89,0) -> 0 | E34: =IF(E33>0,Assumptions!F89,0) -> 0 | F34: =IF(F33>0,Assumptions!F89,0) -> 13.9 | G34: =IF(G33>0,Assumptions!F89,0) -> 13.9 | H34: =IF(H33>0,Assumptions!F89,0) -> 13.9 | I34: =IF(I33>0,Assumptions!F89,0) -> 13.9 | J34: =IF(J33>0,Assumptions!F89,0) -> 13.9 | K34: =IF(K33>0,Assumptions!F89,0) -> 13.9 | L34: =IF(L33>0,Assumptions!F89,0) -> 13.9 | M34: =IF(M33>0,Assumptions!F89,0) -> 13.9 | N34: =SUM(B34:M34) -> 111.2 | O34: =IF(O33>0,Assumptions!$F$89*12,0) -> 166.8 | P34: =IF(P33>0,Assumptions!$F$89*12,0) -> 166.8 | Q34: =IF(Q33>0,Assumptions!$F$89*12,0) -> 166.8 | R34: =IF(R33>0,Assumptions!$F$89*12,0) -> 166.8
A35: Interest Expense | B35: =B33*Assumptions!D89/12 -> 0 | C35: =C33*Assumptions!D89/12 -> 0 | D35: =D33*Assumptions!D89/12 -> 0 | E35: =E33*Assumptions!D89/12 -> 0 | F35: =F33*Assumptions!D89/12 -> 4.0833333 | G35: =G33*Assumptions!D89/12 -> 4.0260694 | H35: =H33*Assumptions!D89/12 -> 3.9684715 | I35: =I33*Assumptions!D89/12 -> 3.9105376 | J35: =J33*Assumptions!D89/12 -> 3.8522657 | K35: =K33*Assumptions!D89/12 -> 3.793654 | L35: =L33*Assumptions!D89/12 -> 3.7347003 | M35: =M33*Assumptions!D89/12 -> 3.6754027 | N35: =SUM(B35:M35) -> 31.044435 | O35: =O33*Assumptions!$D$89 -> 43.38911 | P35: =P33*Assumptions!$D$89 -> 34.750348 | Q35: =Q33*Assumptions!$D$89 -> 25.506873 | R35: =R33*Assumptions!$D$89 -> 15.616354
A36: Principal Repayment | B36: =B34-B35 -> 0 | C36: =C34-C35 -> 0 | D36: =D34-D35 -> 0 | E36: =E34-E35 -> 0 | F36: =F34-F35 -> 9.8166667 | G36: =G34-G35 -> 9.8739306 | H36: =H34-H35 -> 9.9315285 | I36: =I34-I35 -> 9.9894624 | ... M36: =M34-M35 -> 10.224597 | N36: =SUM(B36:M36) -> 80.155565 | O36: =O34-O35 -> 123.41089 | P36: =P34-P35 -> 132.04965 | Q36: =Q34-Q35 -> 141.29313 | R36: =R34-R35 -> 151.18365
A37: Ending Balance | B37: =MAX(B33-B36,0) -> 0 | C37: =MAX(C33-C36,0) -> 0 | D37: =MAX(D33-D36,0) -> 0 | E37: =MAX(E33-E36,0) -> 0 | F37: =MAX(F33-F36,0) -> 690.18333 | G37: =MAX(G33-G36,0) -> 680.3094 | H37: =MAX(H33-H36,0) -> 670.37787 | I37: =MAX(I33-I36,0) -> 660.38841 | ... M37: =MAX(M33-M36,0) -> 619.84443 | N37: =M37 -> 619.84443 | O37: =MAX(O33-O36,0) -> 496.43354 | P37: =MAX(P33-P36,0) -> 364.38389 | Q37: =MAX(Q33-Q36,0) -> 223.09077 | R37: =MAX(R33-R36,0) -> 71.907119
A38: Work Truck Notes
A39: Beginning Balance | B39: 0 | C39: 0 | D39: 0 | E39: 0 | F39: =Assumptions!B90 -> 50 | G39: =F43 -> 49.291667 | H39: =G43 -> 48.579201 | I39: =H43 -> 47.86258 | J39: =I43 -> 47.141778 | K39: =J43 -> 46.416772 | L39: =K43 -> 45.687537 | M39: =L43 -> 44.954047 | N39: =SUM(B39:M39) -> 379.93358 | O39: =N43 -> 44.216279 | P39: =O43 -> 35.311419 | Q39: =P43 -> 25.783218 | R39: =Q43 -> 15.588043
A40: Monthly Payment | B40: =IF(B39>0,Assumptions!F90,0) -> 0 | C40: =IF(C39>0,Assumptions!F90,0) -> 0 | D40: =IF(D39>0,Assumptions!F90,0) -> 0 | E40: =IF(E39>0,Assumptions!F90,0) -> 0 | F40: =IF(F39>0,Assumptions!F90,0) -> 1 | G40: =IF(G39>0,Assumptions!F90,0) -> 1 | H40: =IF(H39>0,Assumptions!F90,0) -> 1 | I40: =IF(I39>0,Assumptions!F90,0) -> 1 | J40: =IF(J39>0,Assumptions!F90,0) -> 1 | K40: =IF(K39>0,Assumptions!F90,0) -> 1 | L40: =IF(L39>0,Assumptions!F90,0) -> 1 | M40: =IF(M39>0,Assumptions!F90,0) -> 1 | N40: =SUM(B40:M40) -> 8 | O40: =IF(O39>0,Assumptions!$F$90*12,0) -> 12 | P40: =IF(P39>0,Assumptions!$F$90*12,0) -> 12 | Q40: =IF(Q39>0,Assumptions!$F$90*12,0) -> 12 | R40: =IF(R39>0,Assumptions!$F$90*12,0) -> 12
A41: Interest Expense | B41: =B39*Assumptions!D90/12 -> 0 | C41: =C39*Assumptions!D90/12 -> 0 | D41: =D39*Assumptions!D90/12 -> 0 | E41: =E39*Assumptions!D90/12 -> 0 | F41: =F39*Assumptions!D90/12 -> 0.29166667 | G41: =G39*Assumptions!D90/12 -> 0.28753472 | H41: =H39*Assumptions!D90/12 -> 0.28337867 | I41: =I39*Assumptions!D90/12 -> 0.27919838 | J41: =J39*Assumptions!D90/12 -> 0.27499371 | K41: =K39*Assumptions!D90/12 -> 0.2707645 | L41: =L39*Assumptions!D90/12 -> 0.26651063 | M41: =M39*Assumptions!D90/12 -> 0.26223194 | N41: =SUM(B41:M41) -> 2.2162792 | O41: =O39*Assumptions!$D$90 -> 3.0951395 | P41: =P39*Assumptions!$D$90 -> 2.4717993 | Q41: =Q39*Assumptions!$D$90 -> 1.8048253 | R41: =R39*Assumptions!$D$90 -> 1.091163
A42: Principal Repayment | B42: =B40-B41 -> 0 | C42: =C40-C41 -> 0 | D42: =D40-D41 -> 0 | E42: =E40-E41 -> 0 | F42: =F40-F41 -> 0.70833333 | G42: =G40-G41 -> 0.71246528 | H42: =H40-H41 -> 0.71662133 | I42: =I40-I41 -> 0.72080162 | ... M42: =M40-M41 -> 0.73776806 | N42: =SUM(B42:M42) -> 5.7837208 | O42: =O40-O41 -> 8.9048605 | P42: =P40-P41 -> 9.5282007 | Q42: =Q40-Q41 -> 10.195175 | R42: =R40-R41 -> 10.908837
A43: Ending Balance | B43: =MAX(B39-B42,0) -> 0 | C43: =MAX(C39-C42,0) -> 0 | D43: =MAX(D39-D42,0) -> 0 | E43: =MAX(E39-E42,0) -> 0 | F43: =MAX(F39-F42,0) -> 49.291667 | G43: =MAX(G39-G42,0) -> 48.579201 | H43: =MAX(H39-H42,0) -> 47.86258 | I43: =MAX(I39-I42,0) -> 47.141778 | ... M43: =MAX(M39-M42,0) -> 44.216279 | N43: =M43 -> 44.216279 | O43: =MAX(O39-O42,0) -> 35.311419 | P43: =MAX(P39-P42,0) -> 25.783218 | Q43: =MAX(Q39-Q42,0) -> 15.588043 | R43: =MAX(R39-R42,0) -> 4.6792064
A44: Revolving Credit Facility (Initial Draw at Close + Cash Sweep)
A45: Beginning Balance | B45: =Assumptions!$G$187*Assumptions!$G$191 -> 600 | C45: =B49 -> 600 | D45: =C49 -> 600 | E45: =D49 -> 600 | F45: =E49 -> 600 | G45: =F49 -> 600 | H45: =G49 -> 600 | I45: =H49 -> 600 | J45: =I49 -> 600 | ... R45: =Q49 -> 0
A46: Draws / (Repayments) | B46: 0 | C46: 0 | D46: 0 | E46: 0 | F46: 0 | G46: 0 | H46: 0 | I46: 0 | J46: 0 | K46: 0 | L46: 0 | M46: 0 | N46: 0 | O46: =IF(Assumptions!$G$187=0,0,_xlfn.LET(_xlpm.nonRevInt,O7+O13+O21+O27+O35+O41,_xlpm.ebit,'Income Statement'!O19,_xlpm.ebt_preRev,_xlpm.ebit-_xlpm.nonRevInt+'Income Statement'!O23,_xlpm.tax,IF(_xlpm.ebt_preRev>0,_xlpm.ebt_preRev*Assumptions!$B$13,0),_xlpm.ni_preRev,_xlpm.ebt_preRev-_xlpm.tax,_xlpm.depr,'Income Statement'!O14,_xlpm.wc,'Cash Flow'!O14,_xlpm.cfo_preRev,_xlpm.ni_preRev+_xlpm.depr+_xlpm.wc,_xlpm.cfi,'Cash Flow'!O22,_xlpm.equity,'Cash Flow'!O25,_xlpm.debtProc,'Cash Flow'!O26+'Cash Flow'!O27,_xlpm.princ,-O70,_xlpm.dist_preRev,IF(_xlpm.ni_preRev>0,-_xlpm.ni_preRev*Assumptions!$B$104,0),_xlpm.cashAvail,'Cash Flow'!N36+_xlpm.cfo_preRev+_xlpm.cfi+_xlpm.equity+_xlpm.debtProc+_xlpm.princ+_xlpm.dist_preRev,_xlpm.draw,IF(_xlpm.cashAvail<Assumptions!$G$101,MIN(Assumptions!$G$101-_xlpm.cashAvail,MAX(0,Assumptions!$G$187-O45)),-MIN(MAX(_xlpm.cashAvail-Assumptions!$G$101,0),O45)),_xlpm.draw)) -> -600 | P46: =IF(Assumptions!$G$187=0,0,_xlfn.LET(_xlpm.nonRevInt,P7+P13+P21+P27+P35+P41,_xlpm.ebit,'Income Statement'!P19,_xlpm.ebt_preRev,_xlpm.ebit-_xlpm.nonRevInt+'Income Statement'!P23,_xlpm.tax,IF(_xlpm.ebt_preRev>0,_xlpm.ebt_preRev*Assumptions!$B$13,0),_xlpm.ni_preRev,_xlpm.ebt_preRev-_xlpm.tax,_xlpm.depr,'Income Statement'!P14,_xlpm.wc,'Cash Flow'!P14,_xlpm.cfo_preRev,_xlpm.ni_preRev+_xlpm.depr+_xlpm.wc,_xlpm.cfi,'Cash Flow'!P22,_xlpm.equity,'Cash Flow'!P25,_xlpm.debtProc,'Cash Flow'!P26+'Cash Flow'!P27,_xlpm.princ,-P70,_xlpm.dist_preRev,IF(_xlpm.ni_preRev>0,-_xlpm.ni_preRev*Assumptions!$B$104,0),_xlpm.cashAvail,'Cash Flow'!O36+_xlpm.cfo_preRev+_xlpm.cfi+_xlpm.equity+_xlpm.debtProc+_xlpm.princ+_xlpm.dist_preRev,_xlpm.draw,IF(_xlpm.cashAvail<Assumptions!$G$101,MIN(Assumptions!$G$101-_xlpm.cashAvail,MAX(0,Assumptions!$G$187-P45)),-MIN(MAX(_xlpm.cashAvail-Assumptions!$G$101,0),P45)),_xlpm.draw)) -> 0 | Q46: =IF(Assumptions!$G$187=0,0,_xlfn.LET(_xlpm.nonRevInt,Q7+Q13+Q21+Q27+Q35+Q41,_xlpm.ebit,'Income Statement'!Q19,_xlpm.ebt_preRev,_xlpm.ebit-_xlpm.nonRevInt+'Income Statement'!Q23,_xlpm.tax,IF(_xlpm.ebt_preRev>0,_xlpm.ebt_preRev*Assumptions!$B$13,0),_xlpm.ni_preRev,_xlpm.ebt_preRev-_xlpm.tax,_xlpm.depr,'Income Statement'!Q14,_xlpm.wc,'Cash Flow'!Q14,_xlpm.cfo_preRev,_xlpm.ni_preRev+_xlpm.depr+_xlpm.wc,_xlpm.cfi,'Cash Flow'!Q22,_xlpm.equity,'Cash Flow'!Q25,_xlpm.debtProc,'Cash Flow'!Q26+'Cash Flow'!Q27,_xlpm.princ,-Q70,_xlpm.dist_preRev,IF(_xlpm.ni_preRev>0,-_xlpm.ni_preRev*Assumptions!$B$104,0),_xlpm.cashAvail,'Cash Flow'!P36+_xlpm.cfo_preRev+_xlpm.cfi+_xlpm.equity+_xlpm.debtProc+_xlpm.princ+_xlpm.dist_preRev,_xlpm.draw,IF(_xlpm.cashAvail<Assumptions!$G$101,MIN(Assumptions!$G$101-_xlpm.cashAvail,MAX(0,Assumptions!$G$187-Q45)),-MIN(MAX(_xlpm.cashAvail-Assumptions!$G$101,0),Q45)),_xlpm.draw)) -> 0 | R46: =IF(Assumptions!$G$187=0,0,_xlfn.LET(_xlpm.nonRevInt,R7+R13+R21+R27+R35+R41,_xlpm.ebit,'Income Statement'!R19,_xlpm.ebt_preRev,_xlpm.ebit-_xlpm.nonRevInt+'Income Statement'!R23,_xlpm.tax,IF(_xlpm.ebt_preRev>0,_xlpm.ebt_preRev*Assumptions!$B$13,0),_xlpm.ni_preRev,_xlpm.ebt_preRev-_xlpm.tax,_xlpm.depr,'Income Statement'!R14,_xlpm.wc,'Cash Flow'!R14,_xlpm.cfo_preRev,_xlpm.ni_preRev+_xlpm.depr+_xlpm.wc,_xlpm.cfi,'Cash Flow'!R22,_xlpm.equity,'Cash Flow'!R25,_xlpm.debtProc,'Cash Flow'!R26+'Cash Flow'!R27,_xlpm.princ,-R70,_xlpm.dist_preRev,IF(_xlpm.ni_preRev>0,-_xlpm.ni_preRev*Assumptions!$B$104,0),_xlpm.cashAvail,'Cash Flow'!Q36+_xlpm.cfo_preRev+_xlpm.cfi+_xlpm.equity+_xlpm.debtProc+_xlpm.princ+_xlpm.dist_preRev,_xlpm.draw,IF(_xlpm.cashAvail<Assumptions!$G$101,MIN(Assumptions!$G$101-_xlpm.cashAvail,MAX(0,Assumptions!$G$187-R45)),-MIN(MAX(_xlpm.cashAvail-Assumptions!$G$101,0),R45)),_xlpm.draw)) -> 0
A47: Interest Expense | B47: =B45*Assumptions!$G$188/12 -> 3 | C47: =C45*Assumptions!$G$188/12 -> 3 | D47: =D45*Assumptions!$G$188/12 -> 3 | E47: =E45*Assumptions!$G$188/12 -> 3 | F47: =F45*Assumptions!$G$188/12 -> 3 | G47: =G45*Assumptions!$G$188/12 -> 3 | H47: =H45*Assumptions!$G$188/12 -> 3 | I47: =I45*Assumptions!$G$188/12 -> 3 | ... M47: =M45*Assumptions!$G$188/12 -> 3 | N47: =SUM(B47:M47) -> 36 | O47: =IF(Assumptions!$G$187=0,0,((O45+MAX(O45+O46,0))/2)*Assumptions!$G$188) -> 18 | P47: =IF(Assumptions!$G$187=0,0,((P45+MAX(P45+P46,0))/2)*Assumptions!$G$188) -> 0 | Q47: =IF(Assumptions!$G$187=0,0,((Q45+MAX(Q45+Q46,0))/2)*Assumptions!$G$188) -> 0 | R47: =IF(Assumptions!$G$187=0,0,((R45+MAX(R45+R46,0))/2)*Assumptions!$G$188) -> 0
A48: Commitment Fee | B48: =(Assumptions!$G$187-B45)*Assumptions!$G$189/12 -> 0.2 | C48: =(Assumptions!$G$187-C45)*Assumptions!$G$189/12 -> 0.2 | D48: =(Assumptions!$G$187-D45)*Assumptions!$G$189/12 -> 0.2 | E48: =(Assumptions!$G$187-E45)*Assumptions!$G$189/12 -> 0.2 | F48: =(Assumptions!$G$187-F45)*Assumptions!$G$189/12 -> 0.2 | G48: =(Assumptions!$G$187-G45)*Assumptions!$G$189/12 -> 0.2 | H48: =(Assumptions!$G$187-H45)*Assumptions!$G$189/12 -> 0.2 | I48: =(Assumptions!$G$187-I45)*Assumptions!$G$189/12 -> 0.2 | ... M48: =(Assumptions!$G$187-M45)*Assumptions!$G$189/12 -> 0.2 | N48: =SUM(B48:M48) -> 2.4 | O48: =IF(Assumptions!$G$187=0,0,(Assumptions!$G$187-(O45+MAX(O45+O46,0))/2)*Assumptions!$G$189) -> 4.2 | P48: =IF(Assumptions!$G$187=0,0,(Assumptions!$G$187-(P45+MAX(P45+P46,0))/2)*Assumptions!$G$189) -> 6 | Q48: =IF(Assumptions!$G$187=0,0,(Assumptions!$G$187-(Q45+MAX(Q45+Q46,0))/2)*Assumptions!$G$189) -> 6 | R48: =IF(Assumptions!$G$187=0,0,(Assumptions!$G$187-(R45+MAX(R45+R46,0))/2)*Assumptions!$G$189) -> 6
A49: Ending Balance | B49: =B45+B46 -> 600 | C49: =C45+C46 -> 600 | D49: =D45+D46 -> 600 | E49: =E45+E46 -> 600 | F49: =F45+F46 -> 600 | G49: =G45+G46 -> 600 | H49: =H45+H46 -> 600 | I49: =I45+I46 -> 600 | ... M49: =M45+M46 -> 600 | N49: =M49 -> 600 | O49: =MAX(O45+O46,0) -> 0 | P49: =MAX(P45+P46,0) -> 0 | Q49: =MAX(Q45+Q46,0) -> 0 | R49: =MAX(R45+R46,0) -> 0
A50: Seller Note — Installations Acquisition ($1,400K @ 7%, 5yr)
A51: Beginning Balance | B51: 0 | C51: 0 | D51: 0 | E51: 0 | F51: 0 | G51: 0 | H51: 0 | I51: 0 | J51: 0 | K51: 1400 | L51: =K55 -> 1380.4667 | M51: =L55 -> 1360.8194 | N51: =M51 -> 1360.8194 | O51: =N55 -> 1341.0575 | P51: =O55 -> 1102.5315 | Q51: =P55 -> 847.30873 | R51: =Q55 -> 574.22035
A52: Monthly Payment | B52: 0 | C52: 0 | D52: 0 | E52: 0 | F52: 0 | G52: 0 | H52: 0 | I52: 0 | J52: 0 | K52: =IF(K51>0,Assumptions!$F$92,0) -> 27.7 | L52: =IF(L51>0,Assumptions!$F$92,0) -> 27.7 | M52: =IF(M51>0,Assumptions!$F$92,0) -> 27.7 | N52: =SUM(B52:M52) -> 83.1 | O52: =IF(O51>0,Assumptions!$F$92*12,0) -> 332.4 | P52: =IF(P51>0,Assumptions!$F$92*12,0) -> 332.4 | Q52: =IF(Q51>0,Assumptions!$F$92*12,0) -> 332.4 | R52: =IF(R51>0,Assumptions!$F$92*12,0) -> 332.4
A53: Interest Expense | B53: 0 | C53: 0 | D53: 0 | E53: 0 | F53: 0 | G53: 0 | H53: 0 | I53: 0 | J53: 0 | K53: =K51*Assumptions!$D$92/12 -> 8.1666667 | L53: =L51*Assumptions!$D$92/12 -> 8.0527222 | M53: =M51*Assumptions!$D$92/12 -> 7.9381131 | N53: =SUM(B53:M53) -> 24.157502 | O53: =O51*Assumptions!$D$92 -> 93.874025 | P53: =P51*Assumptions!$D$92 -> 77.177207 | Q53: =Q51*Assumptions!$D$92 -> 59.311611 | R53: =R51*Assumptions!$D$92 -> 40.195424
A54: Principal Repayment | B54: 0 | C54: 0 | D54: 0 | E54: 0 | F54: 0 | G54: 0 | H54: 0 | I54: 0 | J54: 0 | K54: =K52-K53 -> 19.533333 | L54: =L52-L53 -> 19.647278 | M54: =M52-M53 -> 19.761887 | N54: =SUM(B54:M54) -> 58.942498 | O54: =O52-O53 -> 238.52597 | P54: =P52-P53 -> 255.22279 | Q54: =Q52-Q53 -> 273.08839 | R54: =R52-R53 -> 292.20458
A55: Ending Balance | B55: 0 | C55: 0 | D55: 0 | E55: 0 | F55: 0 | G55: 0 | H55: 0 | I55: 0 | J55: 0 | K55: =MAX(K51-K54,0) -> 1380.4667 | L55: =MAX(L51-L54,0) -> 1360.8194 | M55: =MAX(M51-M54,0) -> 1341.0575 | N55: =M55 -> 1341.0575 | O55: =MAX(O51-O54,0) -> 1102.5315 | P55: =MAX(P51-P54,0) -> 847.30873 | Q55: =MAX(Q51-Q54,0) -> 574.22035 | R55: =MAX(R51-R54,0) -> 282.01577
A57: Apollo Acquisition Term Note ($300K @ 9%, 5yr)
A58: Beginning Balance | B58: 0 | C58: 0 | D58: 0 | E58: 0 | F58: 0 | G58: 0 | H58: 0 | I58: 0 | J58: 0 | K58: 300 | L58: =K62 -> 296.05 | M58: =L62 -> 292.07038 | N58: =M58 -> 292.07038 | O58: =N62 -> 288.0609 | P58: =O62 -> 239.58638 | Q58: =P62 -> 186.74916 | R58: =Q62 -> 129.15658
A59: Monthly Payment | B59: 0 | C59: 0 | D59: 0 | E59: 0 | F59: 0 | G59: 0 | H59: 0 | I59: 0 | J59: 0 | K59: =IF(K58>0,Assumptions!$F$93,0) -> 6.2 | L59: =IF(L58>0,Assumptions!$F$93,0) -> 6.2 | M59: =IF(M58>0,Assumptions!$F$93,0) -> 6.2 | N59: =SUM(B59:M59) -> 18.6 | O59: =IF(O58>0,Assumptions!$F$93*12,0) -> 74.4 | P59: =IF(P58>0,Assumptions!$F$93*12,0) -> 74.4 | Q59: =IF(Q58>0,Assumptions!$F$93*12,0) -> 74.4 | R59: =IF(R58>0,Assumptions!$F$93*12,0) -> 74.4
A60: Interest Expense | B60: 0 | C60: 0 | D60: 0 | E60: 0 | F60: 0 | G60: 0 | H60: 0 | I60: 0 | J60: 0 | K60: =K58*Assumptions!$D$93/12 -> 2.25 | L60: =L58*Assumptions!$D$93/12 -> 2.220375 | M60: =M58*Assumptions!$D$93/12 -> 2.1905278 | N60: =SUM(B60:M60) -> 6.6609028 | O60: =O58*Assumptions!$D$93 -> 25.925481 | P60: =P58*Assumptions!$D$93 -> 21.562775 | Q60: =Q58*Assumptions!$D$93 -> 16.807424 | R60: =R58*Assumptions!$D$93 -> 11.624092
A61: Principal Repayment | B61: 0 | C61: 0 | D61: 0 | E61: 0 | F61: 0 | G61: 0 | H61: 0 | I61: 0 | J61: 0 | K61: =K59-K60 -> 3.95 | L61: =L59-L60 -> 3.979625 | M61: =M59-M60 -> 4.0094722 | N61: =SUM(B61:M61) -> 11.939097 | O61: =O59-O60 -> 48.474519 | P61: =P59-P60 -> 52.837225 | Q61: =Q59-Q60 -> 57.592576 | R61: =R59-R60 -> 62.775908
A62: Ending Balance | B62: 0 | C62: 0 | D62: 0 | E62: 0 | F62: 0 | G62: 0 | H62: 0 | I62: 0 | J62: 0 | K62: =MAX(K58-K61,0) -> 296.05 | L62: =MAX(L58-L61,0) -> 292.07038 | M62: =MAX(M58-M61,0) -> 288.0609 | N62: =M62 -> 288.0609 | O62: =MAX(O58-O61,0) -> 239.58638 | P62: =MAX(P58-P61,0) -> 186.74916 | Q62: =MAX(Q58-Q61,0) -> 129.15658 | R62: =MAX(R58-R61,0) -> 66.380675
A67: DEBT SUMMARY
A68: Total Debt Outstanding | B68: =B9+B15+B23+B29+B37+B43+B49+B55+B62 -> 2852.4583 | C68: =C9+C15+C23+C29+C37+C43+C49+C55+C62 -> 2804.6154 | D68: =D9+D15+D23+D29+D37+D43+D49+D55+D62 -> 2756.4693 | E68: =E9+E15+E23+E29+E37+E43+E49+E55+E62 -> 2708.018 | F68: =F9+F15+F23+F29+F37+F43+F49+F55+F62 -> 3398.7346 | G68: =G9+G15+G23+G29+G37+G43+G49+G55+G62 -> 3339.0807 | H68: =H9+H15+H23+H29+H37+H43+H49+H55+H62 -> 3279.0541 | I68: =I9+I15+I23+I29+I37+I43+I49+I55+I62 -> 3218.6522 | ... M68: =M9+M15+M23+M29+M37+M43+M49+M55+M62 -> 4602.3639 | N68: =M68 -> 4602.3639 | O68: =O9+O15+O23+O29+O37+O43+O49+O55+O62 -> 2967.6003 | P68: =P9+P15+P23+P29+P37+P43+P49+P55+P62 -> 2123.0706 | Q68: =Q9+Q15+Q23+Q29+Q37+Q43+Q49+Q55+Q62 -> 1330.7032 | R68: =R9+R15+R23+R29+R37+R43+R49+R55+R62 -> 477.06525
A69: Total Interest Expense | B69: =B7+B13+B21+B27+B35+B41+B47+B48+B53+B60 -> 18.458333 | C69: =C7+C13+C21+C27+C35+C41+C47+C48+C53+C60 -> 18.157066 | D69: =D7+D13+D21+D27+D35+D41+D47+D48+D53+D60 -> 17.853865 | E69: =E7+E13+E21+E27+E35+E41+E47+E48+E53+E60 -> 17.548719 | F69: =F7+F13+F21+F27+F35+F41+F47+F48+F53+F60 -> 21.616614 | G69: =G7+G13+G21+G27+G35+G41+G47+G48+G53+G60 -> 21.246142 | H69: =H7+H13+H21+H27+H35+H41+H47+H48+H53+H60 -> 20.873327 | I69: =I7+I13+I21+I27+I35+I41+I47+I48+I53+I60 -> 20.498156 | ... M69: =M7+M13+M21+M27+M35+M41+M47+M48+M53+M60 -> 29.102236 | N69: =SUM(B69:M69) -> 265.26386 | O69: =O7+O13+O21+O27+O35+O41+O47+O48+O53+O60 -> 326.63642 | P69: =P7+P13+P21+P27+P35+P41+P47+P48+P53+P60 -> 233.26954 | Q69: =Q7+Q13+Q21+Q27+Q35+Q41+Q47+Q48+Q53+Q60 -> 168.83261 | R69: =R7+R13+R21+R27+R35+R41+R47+R48+R53+R60 -> 107.56207
A70: Total Principal Repayment | B70: =B8+B14+B22+B28+B36+B42+B54+B61 -> 47.541667 | C70: =C8+C14+C22+C28+C36+C42+C54+C61 -> 47.842934 | D70: =D8+D14+D22+D28+D36+D42+D54+D61 -> 48.146135 | E70: =E8+E14+E22+E28+E36+E42+E54+E61 -> 48.451281 | F70: =F8+F14+F22+F28+F36+F42+F54+F61 -> 59.283386 | G70: =G8+G14+G22+G28+G36+G42+G54+G61 -> 59.653858 | H70: =H8+H14+H22+H28+H36+H42+H54+H61 -> 60.026673 | I70: =I8+I14+I22+I28+I36+I42+I54+I61 -> 60.401844 | ... M70: =M8+M14+M22+M28+M36+M42+M54+M61 -> 85.697764 | N70: =SUM(B70:M70) -> 747.63614 | O70: =O8+O14+O22+O28+O36+O42+O54+O61 -> 1034.7636 | P70: =P8+P14+P22+P28+P36+P42+P54+P61 -> 844.52971 | Q70: =Q8+Q14+Q22+Q28+Q36+Q42+Q54+Q61 -> 792.36739 | R70: =R8+R14+R22+R28+R36+R42+R54+R61 -> 853.63793
A71: Total Debt Service | B71: =B69+B70 -> 66 | C71: =C69+C70 -> 66 | D71: =D69+D70 -> 66 | E71: =E69+E70 -> 66 | F71: =F69+F70 -> 80.9 | G71: =G69+G70 -> 80.9 | H71: =H69+H70 -> 80.9 | I71: =I69+I70 -> 80.9 | ... R71: =R69+R70 -> 961.2
A73: COVENANT COMPLIANCE
A74: EBITDA (TTM) | B74: ='Income Statement'!B30*12 -> 716.75024 | C74: =SUM('Income Statement'!B30:'Income Statement'!C30)*(12/2) -> 734.26023 | D74: =SUM('Income Statement'!B30:'Income Statement'!D30)*(12/3) -> 817.16161 | E74: =SUM('Income Statement'!B30:'Income Statement'!E30)*(12/4) -> 923.31017 | F74: =SUM('Income Statement'!B30:'Income Statement'!F30)*(12/5) -> 1035.1285 | G74: =SUM('Income Statement'!B30:'Income Statement'!G30)*(12/6) -> 1130.4627 | H74: =SUM('Income Statement'!B30:'Income Statement'!H30)*(12/7) -> 1213.3758 | I74: =SUM('Income Statement'!B30:'Income Statement'!I30)*(12/8) -> 1267.9377 | J74: =SUM('Income Statement'!B30:'Income Statement'!J30)*(12/9) -> 1277.4642 | K74: =SUM('Income Statement'!B30:'Income Statement'!K30)*(12/10) -> 1250.9667 | L74: =SUM('Income Statement'!B30:'Income Statement'!L30)*(12/11) -> 1199.0749 | M74: =SUM('Income Statement'!B30:'Income Statement'!M30) -> 1152.4848 | N74: ='Income Statement'!N30 -> 1152.4848 | O74: ='Income Statement'!O30 -> 1800.676 | P74: ='Income Statement'!P30 -> 2565.3757 | Q74: ='Income Statement'!Q30 -> 3442.6024 | R74: ='Income Statement'!R30 -> 4336.0739
A75: Debt / EBITDA | B75: =IF(B74>0,B68/B74,"N/A") -> 3.9797103 | C75: =IF(C74>0,C68/C74,"N/A") -> 3.8196477 | D75: =IF(D74>0,D68/D74,"N/A") -> 3.3732241 | E75: =IF(E74>0,E68/E74,"N/A") -> 2.932945 | F75: =IF(F74>0,F68/F74,"N/A") -> 3.2833938 | G75: =IF(G74>0,G68/G74,"N/A") -> 2.9537292 | H75: =IF(H74>0,H68/H74,"N/A") -> 2.7024226 | I75: =IF(I74>0,I68/I74,"N/A") -> 2.5384939 | ... R75: =IF(R74>0,R68/R74,"N/A") -> 0.1100224
A76: Threshold | B76: =Assumptions!$G$98 -> 3.5 | C76: =Assumptions!$G$98 -> 3.5 | D76: =Assumptions!$G$98 -> 3.5 | E76: =Assumptions!$G$98 -> 3.5 | F76: =Assumptions!$G$98 -> 3.5 | G76: =Assumptions!$G$98 -> 3.5 | H76: =Assumptions!$G$98 -> 3.5 | I76: =Assumptions!$G$98 -> 3.5 | ... R76: =Assumptions!$G$98 -> 3.5
A77: Status | B77: HOLIDAY | C77: HOLIDAY | D77: HOLIDAY | E77: HOLIDAY | F77: HOLIDAY | G77: HOLIDAY | H77: HOLIDAY | I77: HOLIDAY | J77: HOLIDAY | K77: HOLIDAY | L77: HOLIDAY | M77: HOLIDAY | N77: HOLIDAY | O77: HOLIDAY | P77: =IF(ISNUMBER(P75),IF(P75<=P76,"PASS","FAIL"),"N/A") -> PASS | Q77: =IF(ISNUMBER(Q75),IF(Q75<=Q76,"PASS","FAIL"),"N/A") -> PASS | R77: =IF(ISNUMBER(R75),IF(R75<=R76,"PASS","FAIL"),"N/A") -> PASS
A78: Interest Coverage (EBITDA/Int) | B78: =IF(B69>0,B74/(B69*12),"N/A") -> 3.2358927 | C78: =IF(C69>0,C74/(C69*12),"N/A") -> 3.3699472 | D78: =IF(D69>0,D74/(D69*12),"N/A") -> 3.8141209 | E78: =IF(E69>0,E74/(E69*12),"N/A") -> 4.3845089 | F78: =IF(F69>0,F74/(F69*12),"N/A") -> 3.9904821 | G78: =IF(G69>0,G74/(G69*12),"N/A") -> 4.4339922 | H78: =IF(H69>0,H74/(H69*12),"N/A") -> 4.8442036 | I78: =IF(I69>0,I74/(I69*12),"N/A") -> 5.1546822 | ... M78: =IF(M69>0,M74/(M69*12),"N/A") -> 3.3001038 | N78: =IF(N69>0,N74/N69,"N/A") -> 4.3446733 | O78: =IF(O69>0,O74/O69,"N/A") -> 5.5127838 | P78: =IF(P69>0,P74/P69,"N/A") -> 10.997474 | Q78: =IF(Q69>0,Q74/Q69,"N/A") -> 20.390625 | R78: =IF(R69>0,R74/R69,"N/A") -> 40.312297
A79: Threshold | B79: =Assumptions!$G$99 -> 2.5 | C79: =Assumptions!$G$99 -> 2.5 | D79: =Assumptions!$G$99 -> 2.5 | E79: =Assumptions!$G$99 -> 2.5 | F79: =Assumptions!$G$99 -> 2.5 | G79: =Assumptions!$G$99 -> 2.5 | H79: =Assumptions!$G$99 -> 2.5 | I79: =Assumptions!$G$99 -> 2.5 | ... R79: =Assumptions!$G$99 -> 2.5
A80: Status | B80: HOLIDAY | C80: HOLIDAY | D80: HOLIDAY | E80: HOLIDAY | F80: HOLIDAY | G80: HOLIDAY | H80: HOLIDAY | I80: HOLIDAY | J80: HOLIDAY | K80: HOLIDAY | L80: HOLIDAY | M80: HOLIDAY | N80: HOLIDAY | O80: HOLIDAY | P80: =IF(ISNUMBER(P78),IF(P78>=P79,"PASS","FAIL"),"N/A") -> PASS | Q80: =IF(ISNUMBER(Q78),IF(Q78>=Q79,"PASS","FAIL"),"N/A") -> PASS | R80: =IF(ISNUMBER(R78),IF(R78>=R79,"PASS","FAIL"),"N/A") -> PASS
A81: Modified FCCR (Maint. CapEx Only) | B81: =IF(B71>0,(B74/12-Assumptions!$C$64/12)/(B71+'Income Statement'!B25),"N/A") -> 0.73870203 | C81: =IF(C71>0,(C74/12-Assumptions!$C$64/12)/(C71+'Income Statement'!C25),"N/A") -> 0.74935658 | D81: =IF(D71>0,(D74/12-Assumptions!$C$64/12)/(D71+'Income Statement'!D25),"N/A") -> 0.78135961 | E81: =IF(E71>0,(E74/12-Assumptions!$C$64/12)/(E71+'Income Statement'!E25),"N/A") -> 0.82538009 | F81: =IF(F71>0,(F74/12-Assumptions!$C$64/12)/(F71+'Income Statement'!F25),"N/A") -> 0.7549984 | G81: =IF(G71>0,(G74/12-Assumptions!$C$64/12)/(G71+'Income Statement'!G25),"N/A") -> 0.80726613 | H81: =IF(H71>0,(H74/12-Assumptions!$C$64/12)/(H71+'Income Statement'!H25),"N/A") -> 0.85092111 | I81: =IF(I71>0,(I74/12-Assumptions!$C$64/12)/(I71+'Income Statement'!I25),"N/A") -> 0.90598108 | ... M81: =IF(M71>0,(M74/12-Assumptions!$C$64/12)/(M71+'Income Statement'!M25),"N/A") -> 0.74585134 | N81: =IF(N71>0,(N74-Assumptions!$C$64)/(N71+'Income Statement'!N25),"N/A") -> 0.91848088 | O81: =IF(O71>0,(O74-Assumptions!$D$64)/(O71+'Income Statement'!O25),"N/A") -> 1.0329764 | P81: =IF(P71>0,(P74-Assumptions!$E$64)/(P71+'Income Statement'!P25),"N/A") -> 1.5706845 | Q81: =IF(Q71>0,(Q74-Assumptions!$F$64)/(Q71+'Income Statement'!Q25),"N/A") -> 1.9893582 | R81: =IF(R71>0,(R74-Assumptions!$G$64)/(R71+'Income Statement'!R25),"N/A") -> 2.2126131
A82: Threshold | B82: =Assumptions!$G$100 -> 1.25 | C82: =Assumptions!$G$100 -> 1.25 | D82: =Assumptions!$G$100 -> 1.25 | E82: =Assumptions!$G$100 -> 1.25 | F82: =Assumptions!$G$100 -> 1.25 | G82: =Assumptions!$G$100 -> 1.25 | H82: =Assumptions!$G$100 -> 1.25 | I82: =Assumptions!$G$100 -> 1.25 | ... R82: =Assumptions!$G$100 -> 1.25
A83: Status | B83: HOLIDAY | C83: HOLIDAY | D83: HOLIDAY | E83: HOLIDAY | F83: HOLIDAY | G83: HOLIDAY | H83: HOLIDAY | I83: HOLIDAY | J83: HOLIDAY | K83: HOLIDAY | L83: HOLIDAY | M83: HOLIDAY | N83: HOLIDAY | O83: HOLIDAY | P83: =IF(ISNUMBER(P81),IF(P81>=P82,"PASS","FAIL"),"N/A") -> PASS | Q83: =IF(ISNUMBER(Q81),IF(Q81>=Q82,"PASS","FAIL"),"N/A") -> PASS | R83: =IF(ISNUMBER(R81),IF(R81>=R82,"PASS","FAIL"),"N/A") -> PASS
A84: Liquidity ($000s) | B84: ='Balance Sheet'!C5 -> 3225.3222 | C84: ='Balance Sheet'!D5 -> 3149.3647 | D84: ='Balance Sheet'!E5 -> 3000.3916 | E84: ='Balance Sheet'!F5 -> 2861.8462 | F84: ='Balance Sheet'!G5 -> 3458.5063 | G84: ='Balance Sheet'!H5 -> 3342.5552 | H84: ='Balance Sheet'!I5 -> 3229.8925 | I84: ='Balance Sheet'!J5 -> 3138.8993 | ... M84: ='Balance Sheet'!N5 -> 2631.0098 | N84: ='Balance Sheet'!N5 -> 2631.0098 | O84: ='Balance Sheet'!O5 -> 1024.4751 | P84: ='Balance Sheet'!P5 -> 836.37422 | Q84: ='Balance Sheet'!Q5 -> 1216.2893 | R84: ='Balance Sheet'!R5 -> 2202.2551
A85: Threshold | B85: =Assumptions!$G$101 -> 200 | C85: =Assumptions!$G$101 -> 200 | D85: =Assumptions!$G$101 -> 200 | E85: =Assumptions!$G$101 -> 200 | F85: =Assumptions!$G$101 -> 200 | G85: =Assumptions!$G$101 -> 200 | H85: =Assumptions!$G$101 -> 200 | I85: =Assumptions!$G$101 -> 200 | ... R85: =Assumptions!$G$101 -> 200
A86: Status | B86: HOLIDAY | C86: HOLIDAY | D86: HOLIDAY | E86: HOLIDAY | F86: HOLIDAY | G86: HOLIDAY | H86: HOLIDAY | I86: HOLIDAY | J86: HOLIDAY | K86: HOLIDAY | L86: HOLIDAY | M86: HOLIDAY | N86: HOLIDAY | O86: HOLIDAY | P86: =IF(P84>=P85,"PASS","FAIL") -> PASS | Q86: =IF(Q84>=Q85,"PASS","FAIL") -> PASS | R86: =IF(R84>=R85,"PASS","FAIL") -> PASS
A89: Apollo Energy Resources — Confidential | Debt Schedule | Mar 2026
A92: CREDIT FACILITY SUMMARY
A93: SECTION 1: UNFUNDED BASE CASE — THE FUNDING GAP
B94: FY2026 | C94: FY2027E | D94: FY2028E | E94: FY2029E | F94: FY2030E | G94: Cumulative
A95: EBITDA | B95: ='Income Statement'!N30 -> 1152.4848 | C95: ='Income Statement'!O30 -> 1800.676 | D95: ='Income Statement'!P30 -> 2565.3757 | E95: ='Income Statement'!Q30 -> 3442.6024 | F95: ='Income Statement'!R30 -> 4336.0739 | G95: =SUM(B95:F95) -> 13297.213
A96: Net Income | B96: ='Income Statement'!N27 -> 235.44245 | C96: ='Income Statement'!O27 -> 524.42731 | D96: ='Income Statement'!P27 -> 978.49323 | E96: ='Income Statement'!Q27 -> 1469.5411 | F96: ='Income Statement'!R27 -> 1970.9932 | G96: =SUM(B96:F96) -> 5178.8973
A97: Free Cash Flow (Levered) | B97: ='Cash Flow'!N15+'Cash Flow'!N22 -> -1277.5575 | C97: ='Cash Flow'!O15+'Cash Flow'!O22 -> 75.427307 | D97: ='Cash Flow'!P15+'Cash Flow'!P22 -> 744.49323 | E97: ='Cash Flow'!Q15+'Cash Flow'!Q22 -> 1304.5411 | F97: ='Cash Flow'!R15+'Cash Flow'!R22 -> 2016.9932 | G97: =SUM(B97:F97) -> 2863.8973
A98: Ending Cash Balance | B98: ='Balance Sheet'!N5 -> 2631.0098 | C98: ='Balance Sheet'!O5 -> 1024.4751 | D98: ='Balance Sheet'!P5 -> 836.37422 | E98: ='Balance Sheet'!Q5 -> 1216.2893 | F98: ='Balance Sheet'!R5 -> 2202.2551 | G98: =F98 -> 2202.2551
A100: Funding Gap (Cash < $0) | B100: =MAX(-B98,0) -> 0 | C100: =MAX(-C98,0) -> 0 | D100: =MAX(-D98,0) -> 0 | E100: =MAX(-E98,0) -> 0 | F100: =MAX(-F98,0) -> 0 | G100: =MAX(B100:F100) -> 0
A101: Peak Funding Need | B101: =B100 -> 0 | C101: =MAX(B101,C100) -> 0 | D101: =MAX(C101,D100) -> 0 | E101: =MAX(D101,E100) -> 0 | F101: =MAX(E101,F100) -> 0 | G101: =F101 -> 0
A102: Covenants Passing (of 4) | B102: =COUNTIF(N77,"PASS")+COUNTIF(N77,"HOLIDAY")+COUNTIF(N80,"PASS")+COUNTIF(N80,"HOLIDAY")+COUNTIF(N83,"PASS")+COUNTIF(N83,"HOLIDAY")+COUNTIF(N86,"PASS")+COUNTIF(N86,"HOLIDAY") -> 4 | C102: =COUNTIF(O77,"PASS")+COUNTIF(O77,"HOLIDAY")+COUNTIF(O80,"PASS")+COUNTIF(O80,"HOLIDAY")+COUNTIF(O83,"PASS")+COUNTIF(O83,"HOLIDAY")+COUNTIF(O86,"PASS")+COUNTIF(O86,"HOLIDAY") -> 4 | D102: =COUNTIF(P77,"PASS")+COUNTIF(P80,"PASS")+COUNTIF(P83,"PASS")+COUNTIF(P86,"PASS") -> 4 | E102: =COUNTIF(Q77,"PASS")+COUNTIF(Q80,"PASS")+COUNTIF(Q83,"PASS")+COUNTIF(Q86,"PASS") -> 4 | F102: =COUNTIF(R77,"PASS")+COUNTIF(R80,"PASS")+COUNTIF(R83,"PASS")+COUNTIF(R86,"PASS") -> 4 | G102: =MIN(B102:F102) -> 4
A103: Liquidity Covenant | B103: =IF(B98>=Assumptions!$G$101,"PASS","FAIL") -> PASS | C103: =IF(C98>=Assumptions!$G$101,"PASS","FAIL") -> PASS | D103: =IF(D98>=Assumptions!$G$101,"PASS","FAIL") -> PASS | E103: =IF(E98>=Assumptions!$G$101,"PASS","FAIL") -> PASS | F103: =IF(F98>=Assumptions!$G$101,"PASS","FAIL") -> PASS | G103: =IF(MIN(B98:F98)>=Assumptions!$G$101,"PASS","FAIL") -> PASS

Sheet DCF & Returns
A1: APOLLO ENERGY RESOURCES — DCF VALUATION ($000s)
B2: FY2026E | C2: FY2027E | D2: FY2028E | E2: FY2029E | F2: FY2030E | G2: Terminal
A3: FREE CASH FLOW BUILD
A4: Revenue | B4: ='Income Statement'!N3 -> 8365.3 | C4: ='Income Statement'!O3 -> 10079.48 | D4: ='Income Statement'!P3 -> 12130.851 | E4: ='Income Statement'!Q3 -> 14465.389 | F4: ='Income Statement'!R3 -> 16688.973
A5: EBITDA | B5: ='Income Statement'!N30 -> 1152.4848 | C5: ='Income Statement'!O30 -> 1800.676 | D5: ='Income Statement'!P30 -> 2565.3757 | E5: ='Income Statement'!Q30 -> 3442.6024 | F5: ='Income Statement'!R30 -> 4336.0739
A6: EBITDA Margin | B6: =B5/B4 -> 0.13776969 | C6: =C5/C4 -> 0.17864771 | D6: =D5/D4 -> 0.21147532 | E6: =E5/E4 -> 0.23798892 | F6: =F5/F4 -> 0.2598167
A7: (-) Taxes on EBIT | B7: =-MAX('Income Statement'!N19,0)*Assumptions!$B$13 -> -188.01029 | C7: =-MAX('Income Statement'!O19,0)*Assumptions!$B$13 -> -336.86956 | D7: =-MAX('Income Statement'!P19,0)*Assumptions!$B$13 -> -511.92646 | E7: =-MAX('Income Statement'!Q19,0)*Assumptions!$B$13 -> -712.56674 | F7: =-MAX('Income Statement'!R19,0)*Assumptions!$B$13 -> -918.86292
A8: (-) CAPEX | B8: ='Cash Flow'!N20 -> -1146 | C8: ='Cash Flow'!O20 -> -837 | D8: ='Cash Flow'!P20 -> -1003 | E8: ='Cash Flow'!Q20 -> -1151 | F8: ='Cash Flow'!R20 -> -1139
A9: (-) Changes in Working Capital | B9: ='Cash Flow'!N14 -> -313 | C9: ='Cash Flow'!O14 -> -326 | D9: ='Cash Flow'!P14 -> -145 | E9: ='Cash Flow'!Q14 -> -158 | F9: ='Cash Flow'!R14 -> -187
A10: Unlevered Free Cash Flow | B10: =B5+B7+B8+B9 -> -494.52548 | C10: =C5+C7+C8+C9 -> 300.80644 | D10: =D5+D7+D8+D9 -> 905.44922 | E10: =E5+E7+E8+E9 -> 1421.0356 | F10: =F5+F7+F8+F9 -> 2091.211
A12: DISCOUNTED CASH FLOW
A13: Discount Period | B13: 0.5 | C13: 1.5 | D13: 2.5 | E13: 3.5 | F13: 4.5 | G13: 4.5
A14: WACC | B14: =Assumptions!B11 -> 0.11147818
A15: Terminal Growth Rate | B15: =Assumptions!B12 -> 0.025
A16: Discount Factor | B16: =1/(1+B14)^B13 -> 0.94852663 | C16: =1/(1+$B$14)^C13 -> 0.85339204 | D16: =1/(1+$B$14)^D13 -> 0.76779918 | E16: =1/(1+$B$14)^E13 -> 0.69079105 | F16: =1/(1+$B$14)^F13 -> 0.62150662 | G16: =1/(1+$B$14)^G13 -> 0.62150662
A17: Terminal Value | G17: =F10*(1+B15)/(B14-B15) -> 24786.497
A18: PV of FCF / Terminal Value | B18: =B10*B16 -> -469.07059 | C18: =C10*C16 -> 256.70582 | D18: =D10*D16 -> 695.20317 | E18: =E10*E16 -> 981.6387 | F18: =F10*F16 -> 1299.7015 | G18: =G17*G16 -> 15404.972
A20: ENTERPRISE & EQUITY VALUE
A22: Sum of PV of FCFs | B22: =ROUND(SUM(B18:F18),1) -> 2764.2
A23: PV of Terminal Value | B23: =ROUND(G18,1) -> 15405
A24: Enterprise Value | B24: =ROUND(B22+B23,1) -> 18169.2
A26: (-) Total Debt (Current) | B26: =-'Debt Schedule'!N68 -> -4602.3639
A27: (+) Cash (Current) | B27: ='Balance Sheet'!N5 -> 2631.0098
A28: Equity Value | B28: =ROUND(B24+B26+B27,1) -> 16197.8
A30: % of EV from Terminal Value | B30: =B23/B24 -> 0.84786342
A31: % of EV from FCFs | B31: =B22/B24 -> 0.15213658
A32: Implied EV / EBITDA (FY2026) | B32: =B24/B5 -> 15.76524
A34: SENSITIVITY ANALYSIS — EQUITY VALUE ($000s)
A35: WACC ↓ / Terminal Growth → | B35: 0.005 | C35: 0.01 | D35: 0.015 | E35: 0.02 | F35: =Assumptions!B12 -> 0.025 | G35: 0.03 | H35: 0.035
A36: 0.08 | B36: =SUM(B10/(1+$A36)^B13,C10/(1+$A36)^C13,D10/(1+$A36)^D13,E10/(1+$A36)^E13,F10/(1+$A36)^F13)+F10*(1+B$35)/($A36-B$35)/(1+$A36)^F13+'Balance Sheet'!N5-'Debt Schedule'!N68 -> 20951.969 | C36: =SUM(B10/(1+$A36)^B13,C10/(1+$A36)^C13,D10/(1+$A36)^D13,E10/(1+$A36)^E13,F10/(1+$A36)^F13)+F10*(1+C$35)/($A36-C$35)/(1+$A36)^F13+'Balance Sheet'!N5-'Debt Schedule'!N68 -> 22473.306 | D36: =SUM(B10/(1+$A36)^B13,C10/(1+$A36)^C13,D10/(1+$A36)^D13,E10/(1+$A36)^E13,F10/(1+$A36)^F13)+F10*(1+D$35)/($A36-D$35)/(1+$A36)^F13+'Balance Sheet'!N5-'Debt Schedule'!N68 -> 24228.695 | E36: =SUM(B10/(1+$A36)^B13,C10/(1+$A36)^C13,D10/(1+$A36)^D13,E10/(1+$A36)^E13,F10/(1+$A36)^F13)+F10*(1+E$35)/($A36-E$35)/(1+$A36)^F13+'Balance Sheet'!N5-'Debt Schedule'!N68 -> 26276.648 | F36: =SUM(B10/(1+$A36)^B13,C10/(1+$A36)^C13,D10/(1+$A36)^D13,E10/(1+$A36)^E13,F10/(1+$A36)^F13)+F10*(1+F$35)/($A36-F$35)/(1+$A36)^F13+'Balance Sheet'!N5-'Debt Schedule'!N68 -> 28696.957 | G36: =SUM(B10/(1+$A36)^B13,C10/(1+$A36)^C13,D10/(1+$A36)^D13,E10/(1+$A36)^E13,F10/(1+$A36)^F13)+F10*(1+G$35)/($A36-G$35)/(1+$A36)^F13+'Balance Sheet'!N5-'Debt Schedule'!N68 -> 31601.327 | H36: =SUM(B10/(1+$A36)^B13,C10/(1+$A36)^C13,D10/(1+$A36)^D13,E10/(1+$A36)^E13,F10/(1+$A36)^F13)+F10*(1+H$35)/($A36-H$35)/(1+$A36)^F13+'Balance Sheet'!N5-'Debt Schedule'!N68 -> 35151.114
A37: 0.09 | B37: =SUM(B10/(1+$A37)^B13,C10/(1+$A37)^C13,D10/(1+$A37)^D13,E10/(1+$A37)^E13,F10/(1+$A37)^F13)+F10*(1+B$35)/($A37-B$35)/(1+$A37)^F13+'Balance Sheet'!N5-'Debt Schedule'!N68 -> 17796.718 | C37: =SUM(B10/(1+$A37)^B13,C10/(1+$A37)^C13,D10/(1+$A37)^D13,E10/(1+$A37)^E13,F10/(1+$A37)^F13)+F10*(1+C$35)/($A37-C$35)/(1+$A37)^F13+'Balance Sheet'!N5-'Debt Schedule'!N68 -> 18933.995 | D37: =SUM(B10/(1+$A37)^B13,C10/(1+$A37)^C13,D10/(1+$A37)^D13,E10/(1+$A37)^E13,F10/(1+$A37)^F13)+F10*(1+D$35)/($A37-D$35)/(1+$A37)^F13+'Balance Sheet'!N5-'Debt Schedule'!N68 -> 20222.908 | E37: =SUM(B10/(1+$A37)^B13,C10/(1+$A37)^C13,D10/(1+$A37)^D13,E10/(1+$A37)^E13,F10/(1+$A37)^F13)+F10*(1+E$35)/($A37-E$35)/(1+$A37)^F13+'Balance Sheet'!N5-'Debt Schedule'!N68 -> 21695.953 | F37: =SUM(B10/(1+$A37)^B13,C10/(1+$A37)^C13,D10/(1+$A37)^D13,E10/(1+$A37)^E13,F10/(1+$A37)^F13)+F10*(1+F$35)/($A37-F$35)/(1+$A37)^F13+'Balance Sheet'!N5-'Debt Schedule'!N68 -> 23395.619 | G37: =SUM(B10/(1+$A37)^B13,C10/(1+$A37)^C13,D10/(1+$A37)^D13,E10/(1+$A37)^E13,F10/(1+$A37)^F13)+F10*(1+G$35)/($A37-G$35)/(1+$A37)^F13+'Balance Sheet'!N5-'Debt Schedule'!N68 -> 25378.564 | H37: =SUM(B10/(1+$A37)^B13,C10/(1+$A37)^C13,D10/(1+$A37)^D13,E10/(1+$A37)^E13,F10/(1+$A37)^F13)+F10*(1+H$35)/($A37-H$35)/(1+$A37)^F13+'Balance Sheet'!N5-'Debt Schedule'!N68 -> 27722.043
A38: 0.1 | B38: =SUM(B10/(1+$A38)^B13,C10/(1+$A38)^C13,D10/(1+$A38)^D13,E10/(1+$A38)^E13,F10/(1+$A38)^F13)+F10*(1+B$35)/($A38-B$35)/(1+$A38)^F13+'Balance Sheet'!N5-'Debt Schedule'!N68 -> 15318.153 | C38: =SUM(B10/(1+$A38)^B13,C10/(1+$A38)^C13,D10/(1+$A38)^D13,E10/(1+$A38)^E13,F10/(1+$A38)^F13)+F10*(1+C$35)/($A38-C$35)/(1+$A38)^F13+'Balance Sheet'!N5-'Debt Schedule'!N68 -> 16194.2 | D38: =SUM(B10/(1+$A38)^B13,C10/(1+$A38)^C13,D10/(1+$A38)^D13,E10/(1+$A38)^E13,F10/(1+$A38)^F13)+F10*(1+D$35)/($A38-D$35)/(1+$A38)^F13+'Balance Sheet'!N5-'Debt Schedule'!N68 -> 17173.311 | E38: =SUM(B10/(1+$A38)^B13,C10/(1+$A38)^C13,D10/(1+$A38)^D13,E10/(1+$A38)^E13,F10/(1+$A38)^F13)+F10*(1+E$35)/($A38-E$35)/(1+$A38)^F13+'Balance Sheet'!N5-'Debt Schedule'!N68 -> 18274.811 | F38: =SUM(B10/(1+$A38)^B13,C10/(1+$A38)^C13,D10/(1+$A38)^D13,E10/(1+$A38)^E13,F10/(1+$A38)^F13)+F10*(1+F$35)/($A38-F$35)/(1+$A38)^F13+'Balance Sheet'!N5-'Debt Schedule'!N68 -> 19523.178 | G38: =SUM(B10/(1+$A38)^B13,C10/(1+$A38)^C13,D10/(1+$A38)^D13,E10/(1+$A38)^E13,F10/(1+$A38)^F13)+F10*(1+G$35)/($A38-G$35)/(1+$A38)^F13+'Balance Sheet'!N5-'Debt Schedule'!N68 -> 20949.883 | H38: =SUM(B10/(1+$A38)^B13,C10/(1+$A38)^C13,D10/(1+$A38)^D13,E10/(1+$A38)^E13,F10/(1+$A38)^F13)+F10*(1+H$35)/($A38-H$35)/(1+$A38)^F13+'Balance Sheet'!N5-'Debt Schedule'!N68 -> 22596.081
A39: =Assumptions!B11 -> 0.11147818 | B39: =SUM(B10/(1+$A39)^B13,C10/(1+$A39)^C13,D10/(1+$A39)^D13,E10/(1+$A39)^E13,F10/(1+$A39)^F13)+F10*(1+B$35)/($A39-B$35)/(1+$A39)^F13+'Balance Sheet'!N5-'Debt Schedule'!N68 -> 13060.126 | C39: =SUM(B10/(1+$A39)^B13,C10/(1+$A39)^C13,D10/(1+$A39)^D13,E10/(1+$A39)^E13,F10/(1+$A39)^F13)+F10*(1+C$35)/($A39-C$35)/(1+$A39)^F13+'Balance Sheet'!N5-'Debt Schedule'!N68 -> 13728.595 | D39: =SUM(B10/(1+$A39)^B13,C10/(1+$A39)^C13,D10/(1+$A39)^D13,E10/(1+$A39)^E13,F10/(1+$A39)^F13)+F10*(1+D$35)/($A39-D$35)/(1+$A39)^F13+'Balance Sheet'!N5-'Debt Schedule'!N68 -> 14466.351 | E39: =SUM(B10/(1+$A39)^B13,C10/(1+$A39)^C13,D10/(1+$A39)^D13,E10/(1+$A39)^E13,F10/(1+$A39)^F13)+F10*(1+E$35)/($A39-E$35)/(1+$A39)^F13+'Balance Sheet'!N5-'Debt Schedule'!N68 -> 15284.755 | F39: =SUM(B10/(1+$A39)^B13,C10/(1+$A39)^C13,D10/(1+$A39)^D13,E10/(1+$A39)^E13,F10/(1+$A39)^F13)+F10*(1+F$35)/($A39-F$35)/(1+$A39)^F13+'Balance Sheet'!N5-'Debt Schedule'!N68 -> 16197.797 | G39: =SUM(B10/(1+$A39)^B13,C10/(1+$A39)^C13,D10/(1+$A39)^D13,E10/(1+$A39)^E13,F10/(1+$A39)^F13)+F10*(1+G$35)/($A39-G$35)/(1+$A39)^F13+'Balance Sheet'!N5-'Debt Schedule'!N68 -> 17222.898 | H39: =SUM(B10/(1+$A39)^B13,C10/(1+$A39)^C13,D10/(1+$A39)^D13,E10/(1+$A39)^E13,F10/(1+$A39)^F13)+F10*(1+H$35)/($A39-H$35)/(1+$A39)^F13+'Balance Sheet'!N5-'Debt Schedule'!N68 -> 18382.037
A40: 0.12 | B40: =SUM(B10/(1+$A40)^B13,C10/(1+$A40)^C13,D10/(1+$A40)^D13,E10/(1+$A40)^E13,F10/(1+$A40)^F13)+F10*(1+B$35)/($A40-B$35)/(1+$A40)^F13+'Balance Sheet'!N5-'Debt Schedule'!N68 -> 11683.239 | C40: =SUM(B10/(1+$A40)^B13,C10/(1+$A40)^C13,D10/(1+$A40)^D13,E10/(1+$A40)^E13,F10/(1+$A40)^F13)+F10*(1+C$35)/($A40-C$35)/(1+$A40)^F13+'Balance Sheet'!N5-'Debt Schedule'!N68 -> 12239.162 | D40: =SUM(B10/(1+$A40)^B13,C10/(1+$A40)^C13,D10/(1+$A40)^D13,E10/(1+$A40)^E13,F10/(1+$A40)^F13)+F10*(1+D$35)/($A40-D$35)/(1+$A40)^F13+'Balance Sheet'!N5-'Debt Schedule'!N68 -> 12848.029 | E40: =SUM(B10/(1+$A40)^B13,C10/(1+$A40)^C13,D10/(1+$A40)^D13,E10/(1+$A40)^E13,F10/(1+$A40)^F13)+F10*(1+E$35)/($A40-E$35)/(1+$A40)^F13+'Balance Sheet'!N5-'Debt Schedule'!N68 -> 13517.783 | F40: =SUM(B10/(1+$A40)^B13,C10/(1+$A40)^C13,D10/(1+$A40)^D13,E10/(1+$A40)^E13,F10/(1+$A40)^F13)+F10*(1+F$35)/($A40-F$35)/(1+$A40)^F13+'Balance Sheet'!N5-'Debt Schedule'!N68 -> 14258.038 | G40: =SUM(B10/(1+$A40)^B13,C10/(1+$A40)^C13,D10/(1+$A40)^D13,E10/(1+$A40)^E13,F10/(1+$A40)^F13)+F10*(1+G$35)/($A40-G$35)/(1+$A40)^F13+'Balance Sheet'!N5-'Debt Schedule'!N68 -> 15080.543 | H40: =SUM(B10/(1+$A40)^B13,C10/(1+$A40)^C13,D10/(1+$A40)^D13,E10/(1+$A40)^E13,F10/(1+$A40)^F13)+F10*(1+H$35)/($A40-H$35)/(1+$A40)^F13+'Balance Sheet'!N5-'Debt Schedule'!N68 -> 15999.814
A41: 0.13 | B41: =SUM(B10/(1+$A41)^B13,C10/(1+$A41)^C13,D10/(1+$A41)^D13,E10/(1+$A41)^E13,F10/(1+$A41)^F13)+F10*(1+B$35)/($A41-B$35)/(1+$A41)^F13+'Balance Sheet'!N5-'Debt Schedule'!N68 -> 10314.589 | C41: =SUM(B10/(1+$A41)^B13,C10/(1+$A41)^C13,D10/(1+$A41)^D13,E10/(1+$A41)^E13,F10/(1+$A41)^F13)+F10*(1+C$35)/($A41-C$35)/(1+$A41)^F13+'Balance Sheet'!N5-'Debt Schedule'!N68 -> 10769.056 | D41: =SUM(B10/(1+$A41)^B13,C10/(1+$A41)^C13,D10/(1+$A41)^D13,E10/(1+$A41)^E13,F10/(1+$A41)^F13)+F10*(1+D$35)/($A41-D$35)/(1+$A41)^F13+'Balance Sheet'!N5-'Debt Schedule'!N68 -> 11263.041 | E41: =SUM(B10/(1+$A41)^B13,C10/(1+$A41)^C13,D10/(1+$A41)^D13,E10/(1+$A41)^E13,F10/(1+$A41)^F13)+F10*(1+E$35)/($A41-E$35)/(1+$A41)^F13+'Balance Sheet'!N5-'Debt Schedule'!N68 -> 11801.934 | F41: =SUM(B10/(1+$A41)^B13,C10/(1+$A41)^C13,D10/(1+$A41)^D13,E10/(1+$A41)^E13,F10/(1+$A41)^F13)+F10*(1+F$35)/($A41-F$35)/(1+$A41)^F13+'Balance Sheet'!N5-'Debt Schedule'!N68 -> 12392.151 | G41: =SUM(B10/(1+$A41)^B13,C10/(1+$A41)^C13,D10/(1+$A41)^D13,E10/(1+$A41)^E13,F10/(1+$A41)^F13)+F10*(1+G$35)/($A41-G$35)/(1+$A41)^F13+'Balance Sheet'!N5-'Debt Schedule'!N68 -> 13041.389 | H41: =SUM(B10/(1+$A41)^B13,C10/(1+$A41)^C13,D10/(1+$A41)^D13,E10/(1+$A41)^E13,F10/(1+$A41)^F13)+F10*(1+H$35)/($A41-H$35)/(1+$A41)^F13+'Balance Sheet'!N5-'Debt Schedule'!N68 -> 13758.968
A42: 0.14 | B42: =SUM(B10/(1+$A42)^B13,C10/(1+$A42)^C13,D10/(1+$A42)^D13,E10/(1+$A42)^E13,F10/(1+$A42)^F13)+F10*(1+B$35)/($A42-B$35)/(1+$A42)^F13+'Balance Sheet'!N5-'Debt Schedule'!N68 -> 9156.059 | C42: =SUM(B10/(1+$A42)^B13,C10/(1+$A42)^C13,D10/(1+$A42)^D13,E10/(1+$A42)^E13,F10/(1+$A42)^F13)+F10*(1+C$35)/($A42-C$35)/(1+$A42)^F13+'Balance Sheet'!N5-'Debt Schedule'!N68 -> 9532.6967 | D42: =SUM(B10/(1+$A42)^B13,C10/(1+$A42)^C13,D10/(1+$A42)^D13,E10/(1+$A42)^E13,F10/(1+$A42)^F13)+F10*(1+D$35)/($A42-D$35)/(1+$A42)^F13+'Balance Sheet'!N5-'Debt Schedule'!N68 -> 9939.4654 | E42: =SUM(B10/(1+$A42)^B13,C10/(1+$A42)^C13,D10/(1+$A42)^D13,E10/(1+$A42)^E13,F10/(1+$A42)^F13)+F10*(1+E$35)/($A42-E$35)/(1+$A42)^F13+'Balance Sheet'!N5-'Debt Schedule'!N68 -> 10380.131 | F42: =SUM(B10/(1+$A42)^B13,C10/(1+$A42)^C13,D10/(1+$A42)^D13,E10/(1+$A42)^E13,F10/(1+$A42)^F13)+F10*(1+F$35)/($A42-F$35)/(1+$A42)^F13+'Balance Sheet'!N5-'Debt Schedule'!N68 -> 10859.116 | G42: =SUM(B10/(1+$A42)^B13,C10/(1+$A42)^C13,D10/(1+$A42)^D13,E10/(1+$A42)^E13,F10/(1+$A42)^F13)+F10*(1+G$35)/($A42-G$35)/(1+$A42)^F13+'Balance Sheet'!N5-'Debt Schedule'!N68 -> 11381.645 | H42: =SUM(B10/(1+$A42)^B13,C10/(1+$A42)^C13,D10/(1+$A42)^D13,E10/(1+$A42)^E13,F10/(1+$A42)^F13)+F10*(1+H$35)/($A42-H$35)/(1+$A42)^F13+'Balance Sheet'!N5-'Debt Schedule'!N68 -> 11953.939
A44: ="Note: This DCF is included as a cross-reference only. With "&TEXT('DCF & Returns'!B30,"0%")&_xlfn._LONGTEXT(" of enterprise value derived from the terminal value and negative/low FCFs in Years 1-2, the perpetuity-growth model overstates precision for a business at this stage. The primary valuation method is the EV/EBITDA multiples-based exit analysis on the IRR ","& MOIC sheet, which uses market-observable multiples (")&TEXT(Assumptions!G165,"0.0")&"x base case) and produces a directly comparable equity value by exit year." -> Note: This DCF is included as a cross-reference only. With 85% of enterprise value derived from the terminal value and negative/low FCFs in Years 1-2, the perpetuity-growth model overstates precision for a business at this stage. The primary valuation method is the EV/EBITDA multiples-based exit analysis on the IRR & MOIC sheet, which uses market-observable multiples (5.0x base case) and produces a directly comparable equity value by exit year.
A47: APOLLO ENERGY RESOURCES — IRR & MOIC ANALYSIS ($000s)
A49: INVESTMENT SUMMARY | E49: ANNUAL CASH FLOWS TO EQUITY
A50: Equity Investment | B50: =Assumptions!B79 -> 1500 | E50: Year | F50: FY2026 | G50: FY2027E | H50: FY2028E | I50: FY2029E | J50: FY2030E
A51: Total Capital Injection | B51: =Assumptions!B81 -> 3000 | E51: EBITDA | F51: ='Income Statement'!N30 -> 1152.4848 | G51: ='Income Statement'!O30 -> 1800.676 | H51: ='Income Statement'!P30 -> 2565.3757 | I51: ='Income Statement'!Q30 -> 3442.6024 | J51: ='Income Statement'!R30 -> 4336.0739
A52: Equity % of Total | B52: =B50/B51 -> 0.5 | E52: Total Debt | F52: ='Debt Schedule'!N68 -> 4602.3639 | G52: ='Debt Schedule'!O68 -> 2967.6003 | H52: ='Debt Schedule'!P68 -> 2123.0706 | I52: ='Debt Schedule'!Q68 -> 1330.7032 | J52: ='Debt Schedule'!R68 -> 477.06525
A53: Entry Date | B53: 46023 | E53: Cash | F53: ='Balance Sheet'!N5 -> 2631.0098 | G53: ='Balance Sheet'!O5 -> 1024.4751 | H53: ='Balance Sheet'!P5 -> 836.37422 | I53: ='Balance Sheet'!Q5 -> 1216.2893 | J53: ='Balance Sheet'!R5 -> 2202.2551
A54: WACC | B54: =Assumptions!B11 -> 0.11147818 | E54: Net Debt | F54: =F52-F53 -> 1971.354 | G54: =G52-G53 -> 1943.1252 | H54: =H52-H53 -> 1286.6964 | I54: =I52-I53 -> 114.41391 | J54: =J52-J53 -> -1725.1899
A55: Terminal Growth Rate | B55: =Assumptions!B12 -> 0.025 | E55: Distributions Received | F55: =-'Cash Flow'!N31 -> 27.796501 | G55: =-'Cash Flow'!O31 -> 47.198458 | H55: =-'Cash Flow'!P31 -> 88.064391 | I55: =-'Cash Flow'!Q31 -> 132.2587 | J55: =-'Cash Flow'!R31 -> 177.38939
E56: Cumulative Distributions | F56: =F55 -> 27.796501 | G56: =F56+G55 -> 74.994959 | H56: =G56+H55 -> 163.05935 | I56: =H56+I55 -> 295.31805 | J56: =I56+J55 -> 472.70744
A57: EXIT ASSUMPTIONS
A58: Base Exit Multiple (EV/EBITDA) | B58: =Assumptions!G165 -> 5
A59: Implied DCF Multiple (FY2026) | B59: =B32 -> 15.76524
A60: Max Distribution (% of NI) | B60: =Assumptions!B102 -> 0.4
A62: EXIT EQUITY VALUE BY YEAR & MULTIPLE ($000s) | E62: EXIT EQUITY VALUE BY YEAR & MULTIPLE ($000s)
A63: Exit Year → | E63: Exit Year → | F63: FY2026 | G63: FY2027E | H63: FY2028E | I63: FY2029E | J63: FY2030E
A64: EBITDA at Exit | E64: EBITDA at Exit | F64: =F51 -> 1152.4848 | G64: =G51 -> 1800.676 | H64: =H51 -> 2565.3757 | I64: =I51 -> 3442.6024 | J64: =J51 -> 4336.0739
A65: Net Debt at Exit | E65: Net Debt at Exit | F65: =F54 -> 1971.354 | G65: =G54 -> 1943.1252 | H65: =H54 -> 1286.6964 | I65: =I54 -> 114.41391 | J65: =J54 -> -1725.1899
A66: Holding Period (Years) | E66: Holding Period (Years) | F66: 1 | G66: 2 | H66: 3 | I66: 4 | J66: 5
A68: EXIT EQUITY VALUE BY MULTIPLE & YEAR ($000s)
A69: EV/EBITDA ↓ \ Exit Year → | F69: FY2026 | G69: FY2027E | H69: FY2028E | I69: FY2029E | J69: FY2030E
A70: =Assumptions!G165-3 -> 2 | F70: =F$64*$A70-F$65 -> 333.61556 | G70: =G$64*$A70-G$65 -> 1658.2268 | H70: =H$64*$A70-H$65 -> 3844.055 | I70: =I$64*$A70-I$65 -> 6770.7909 | J70: =J$64*$A70-J$65 -> 10397.338
A71: =Assumptions!G165-2 -> 3 | F71: =F$64*$A71-F$65 -> 1486.1004 | G71: =G$64*$A71-G$65 -> 3458.9028 | H71: =H$64*$A71-H$65 -> 6409.4307 | I71: =I$64*$A71-I$65 -> 10213.393 | J71: =J$64*$A71-J$65 -> 14733.412
A72: =Assumptions!G165-1 -> 4 | F72: =F$64*$A72-F$65 -> 2638.5852 | G72: =G$64*$A72-G$65 -> 5259.5788 | H72: =H$64*$A72-H$65 -> 8974.8064 | I72: =I$64*$A72-I$65 -> 13655.996 | J72: =J$64*$A72-J$65 -> 19069.486
A73: =Assumptions!G165 -> 5 | F73: =F$64*$A73-F$65 -> 3791.07 | G73: =G$64*$A73-G$65 -> 7060.2548 | H73: =H$64*$A73-H$65 -> 11540.182 | I73: =I$64*$A73-I$65 -> 17098.598 | J73: =J$64*$A73-J$65 -> 23405.559
A74: =Assumptions!G165+1 -> 6 | F74: =F$64*$A74-F$65 -> 4943.5548 | G74: =G$64*$A74-G$65 -> 8860.9308 | H74: =H$64*$A74-H$65 -> 14105.558 | I74: =I$64*$A74-I$65 -> 20541.2 | J74: =J$64*$A74-J$65 -> 27741.633
A75: =Assumptions!G165+2 -> 7 | F75: =F$64*$A75-F$65 -> 6096.0396 | G75: =G$64*$A75-G$65 -> 10661.607 | H75: =H$64*$A75-H$65 -> 16670.933 | I75: =I$64*$A75-I$65 -> 23983.803 | J75: =J$64*$A75-J$65 -> 32077.707
A76: =Assumptions!G165+3 -> 8 | F76: =F$64*$A76-F$65 -> 7248.5244 | G76: =G$64*$A76-G$65 -> 12462.283 | H76: =H$64*$A76-H$65 -> 19236.309 | I76: =I$64*$A76-I$65 -> 27426.405 | J76: =J$64*$A76-J$65 -> 36413.781
A77: =Assumptions!G165+4 -> 9 | F77: =F$64*$A77-F$65 -> 8401.0092 | G77: =G$64*$A77-G$65 -> 14262.959 | H77: =H$64*$A77-H$65 -> 21801.685 | I77: =I$64*$A77-I$65 -> 30869.008 | J77: =J$64*$A77-J$65 -> 40749.855
A79: MOIC SENSITIVITY — EXIT MULTIPLE × EXIT YEAR
A80: EV/EBITDA ↓ \ Exit Year → | F80: FY2026 | G80: FY2027E | H80: FY2028E | I80: FY2029E | J80: FY2030E
A81: =Assumptions!G165-3 -> 2 | F81: =(F70+F56)/$B$50 -> 0.24094137 | G81: =(G70+G56)/$B$50 -> 1.1554812 | H81: =(H70+H56)/$B$50 -> 2.6714096 | I81: =(I70+I56)/$B$50 -> 4.7107393 | J81: =(J70+J56)/$B$50 -> 7.2466968
A82: =Assumptions!G165-2 -> 3 | F82: =(F71+F56)/$B$50 -> 1.0092646 | G82: =(G71+G56)/$B$50 -> 2.3559318 | H82: =(H71+H56)/$B$50 -> 4.38166 | I82: =(I71+I56)/$B$50 -> 7.0058075 | J82: =(J71+J56)/$B$50 -> 10.137413
A83: =Assumptions!G165-1 -> 4 | F83: =(F72+F56)/$B$50 -> 1.7775878 | G83: =(G72+G56)/$B$50 -> 3.5563825 | H83: =(H72+H56)/$B$50 -> 6.0919105 | I83: =(I72+I56)/$B$50 -> 9.3008758 | J83: =(J72+J56)/$B$50 -> 13.028129
A84: =Assumptions!G165 -> 5 | F84: =(F73+F56)/$B$50 -> 2.545911 | G84: =(G73+G56)/$B$50 -> 4.7568332 | H84: =(H73+H56)/$B$50 -> 7.8021609 | I84: =(I73+I56)/$B$50 -> 11.595944 | J84: =(J73+J56)/$B$50 -> 15.918845
A85: =Assumptions!G165+1 -> 6 | F85: =(F74+F56)/$B$50 -> 3.3142342 | G85: =(G74+G56)/$B$50 -> 5.9572838 | H85: =(H74+H56)/$B$50 -> 9.5124114 | I85: =(I74+I56)/$B$50 -> 13.891012 | J85: =(J74+J56)/$B$50 -> 18.809561
A86: =Assumptions!G165+2 -> 7 | F86: =(F75+F56)/$B$50 -> 4.0825574 | G86: =(G75+G56)/$B$50 -> 7.1577345 | H86: =(H75+H56)/$B$50 -> 11.222662 | I86: =(I75+I56)/$B$50 -> 16.186081 | J86: =(J75+J56)/$B$50 -> 21.700277
A87: =Assumptions!G165+3 -> 8 | F87: =(F76+F56)/$B$50 -> 4.8508806 | G87: =(G76+G56)/$B$50 -> 8.3581852 | H87: =(H76+H56)/$B$50 -> 12.932912 | I87: =(I76+I56)/$B$50 -> 18.481149 | J87: =(J76+J56)/$B$50 -> 24.590992
A88: =Assumptions!G165+4 -> 9 | F88: =(F77+F56)/$B$50 -> 5.6192038 | G88: =(G77+G56)/$B$50 -> 9.5586358 | H88: =(H77+H56)/$B$50 -> 14.643163 | I88: =(I77+I56)/$B$50 -> 20.776217 | J88: =(J77+J56)/$B$50 -> 27.481708
A90: IRR SENSITIVITY — EXIT MULTIPLE × EXIT YEAR
A91: EV/EBITDA ↓ \ Exit Year → | F91: FY2026 | G91: FY2027E | H91: FY2028E | I91: FY2029E | J91: FY2030E
A92: =Assumptions!G165-3 -> 2 | F92: =IRR(L103:M103) -> -0.75905863 | G92: =IRR(L113:N113) -> 0.075584412 | H92: =IRR(L123:O123) -> 0.39267885 | I92: =IRR(L133:P133) -> 0.48157833 | J92: =IRR(L143:Q143) -> 0.4967494
A93: =Assumptions!G165-2 -> 3 | F93: =IRR(L104:M104) -> 0.0092645775 | G93: =IRR(L114:N114) -> 0.53814963 | H93: =IRR(L124:O124) -> 0.64277391 | I93: =IRR(L134:P134) -> 0.6357023 | J93: =IRR(L144:Q144) -> 0.59988963
A94: =Assumptions!G165-1 -> 4 | F94: =IRR(L105:M105) -> 0.77758778 | G94: =IRR(L115:N115) -> 0.89020605 | H94: =IRR(L125:O125) -> 0.83331816 | I94: =IRR(L135:P135) -> 0.75526938 | J94: =IRR(L145:Q145) -> 0.68151586
A95: =Assumptions!G165 -> 5 | F95: =IRR(L106:M106) -> 1.545911 | G95: =IRR(L116:N116) -> 1.1860494 | H95: =IRR(L126:O126) -> 0.99064238 | I95: =IRR(L136:P136) -> 0.85428633 | J95: =IRR(L146:Q146) -> 0.74968226
A96: =Assumptions!G165+1 -> 6 | F96: =IRR(L107:M107) -> 2.3142342 | G96: =IRR(L117:N117) -> 1.4462388 | H96: =IRR(L127:O127) -> 1.1262834 | I96: =IRR(L137:P137) -> 0.9394877 | J96: =IRR(L147:Q147) -> 0.80854674
A97: =Assumptions!G165+2 -> 7 | F97: =IRR(L108:M108) -> 3.0825574 | G97: =IRR(L118:N118) -> 1.6812104 | H97: =IRR(L128:O128) -> 1.2464549 | I97: =IRR(L138:P138) -> 1.0146785 | J97: =IRR(L148:Q148) -> 0.86055733
A98: =Assumptions!G165+3 -> 8 | F98: =IRR(L109:M109) -> 3.8508806 | G98: =IRR(L119:N119) -> 1.8971263 | H98: =IRR(L129:O129) -> 1.3549335 | I98: =IRR(L139:P139) -> 1.0822377 | J98: =IRR(L149:Q149) -> 0.90728582
A99: =Assumptions!G165+4 -> 9 | F99: =IRR(L110:M110) -> 4.6192038 | G99: =IRR(L120:N120) -> 2.0979854 | H99: =IRR(L130:O130) -> 1.4542065 | I99: =IRR(L140:P140) -> 1.1437606 | J99: =IRR(L150:Q150) -> 0.94980579
L102: Exit at FY2026 (1-yr hold)
L103: =-$B$50 -> -1500 | M103: =F55+F70 -> 361.41206
L104: =-$B$50 -> -1500 | M104: =F55+F71 -> 1513.8969
L105: =-$B$50 -> -1500 | M105: =F55+F72 -> 2666.3817
L106: =-$B$50 -> -1500 | M106: =F55+F73 -> 3818.8665
L107: =-$B$50 -> -1500 | M107: =F55+F74 -> 4971.3513
L108: =-$B$50 -> -1500 | M108: =F55+F75 -> 6123.8361
L109: =-$B$50 -> -1500 | M109: =F55+F76 -> 7276.3209
L110: =-$B$50 -> -1500 | M110: =F55+F77 -> 8428.8057
L112: Exit at FY2027E (2-yr hold)
L113: =-$B$50 -> -1500 | M113: =F55 -> 27.796501 | N113: =G55+G70 -> 1705.4253
L114: =-$B$50 -> -1500 | M114: =F55 -> 27.796501 | N114: =G55+G71 -> 3506.1013
L115: =-$B$50 -> -1500 | M115: =F55 -> 27.796501 | N115: =G55+G72 -> 5306.7773
L116: =-$B$50 -> -1500 | M116: =F55 -> 27.796501 | N116: =G55+G73 -> 7107.4533
L117: =-$B$50 -> -1500 | M117: =F55 -> 27.796501 | N117: =G55+G74 -> 8908.1293
...
